[ {
  "date" : "2005-03-01",
  "value" : 14262.16,
  "symbol" : "BANSANDER-B"
}, {
  "date" : "2005-03-02",
  "value" : 14354.89,
  "symbol" : "BANSANDER-B"
}, {
  "date" : "2005-03-03",
  "value" : 14425.92,
  "symbol" : "BANSANDER-B"
}, {
  "date" : "2005-03-04",
  "value" : 14380.56,
  "symbol" : "BANSANDER-B"
}, {
  "date" : "2005-03-05",
  "value" : 14380.56,
  "symbol" : "BANSANDER-B"
}, {
  "date" : "2005-03-06",
  "value" : 14380.56,
  "symbol" : "BANSANDER-B"
}, {
  "date" : "2005-03-07",
  "value" : 14414.00,
  "symbol" : "BANSANDER-B"
}, {
  "date" : "2005-03-08",
  "value" : 14423.20,
  "symbol" : "BANSANDER-B"
}, {
  "date" : "2005-03-09",
  "value" : 14470.79,
  "symbol" : "BANSANDER-B"
}, {
  "date" : "2005-03-10",
  "value" : 14525.54,
  "symbol" : "BANSANDER-B"
}, {
  "date" : "2005-03-11",
  "value" : 14475.29,
  "symbol" : "BANSANDER-B"
}, {
  "date" : "2005-03-12",
  "value" : 14475.29,
  "symbol" : "BANSANDER-B"
}, {
  "date" : "2005-03-13",
  "value" : 14475.29,
  "symbol" : "BANSANDER-B"
}, {
  "date" : "2005-03-14",
  "value" : 14406.78,
  "symbol" : "BANSANDER-B"
}, {
  "date" : "2005-03-15",
  "value" : 14410.72,
  "symbol" : "BANSANDER-B"
}, {
  "date" : "2005-03-16",
  "value" : 14357.46,
  "symbol" : "BANSANDER-B"
}, {
  "date" : "2005-03-17",
  "value" : 14350.07,
  "symbol" : "BANSANDER-B"
}, {
  "date" : "2005-03-18",
  "value" : 14311.11,
  "symbol" : "BANSANDER-B"
}, {
  "date" : "2005-03-19",
  "value" : 14311.11,
  "symbol" : "BANSANDER-B"
}, {
  "date" : "2005-03-20",
  "value" : 14311.11,
  "symbol" : "BANSANDER-B"
}, {
  "date" : "2005-03-21",
  "value" : 14281.93,
  "symbol" : "BANSANDER-B"
}, {
  "date" : "2005-03-22",
  "value" : 14342.82,
  "symbol" : "BANSANDER-B"
}, {
  "date" : "2005-03-23",
  "value" : 14291.44,
  "symbol" : "BANSANDER-B"
}, {
  "date" : "2005-03-24",
  "value" : 14284.40,
  "symbol" : "BANSANDER-B"
}, {
  "date" : "2005-03-25",
  "value" : 14284.40,
  "symbol" : "BANSANDER-B"
}, {
  "date" : "2005-03-26",
  "value" : 14284.40,
  "symbol" : "BANSANDER-B"
}, {
  "date" : "2005-03-27",
  "value" : 14284.40,
  "symbol" : "BANSANDER-B"
}, {
  "date" : "2005-03-28",
  "value" : 14197.47,
  "symbol" : "BANSANDER-B"
}, {
  "date" : "2005-03-29",
  "value" : 14243.70,
  "symbol" : "BANSANDER-B"
}, {
  "date" : "2005-03-30",
  "value" : 14245.84,
  "symbol" : "BANSANDER-B"
}, {
  "date" : "2005-03-31",
  "value" : 14195.02,
  "symbol" : "BANSANDER-B"
}, {
  "date" : "2005-04-01",
  "value" : 14223.28,
  "symbol" : "BANSANDER-B"
}, {
  "date" : "2005-04-02",
  "value" : 14223.28,
  "symbol" : "BANSANDER-B"
}, {
  "date" : "2005-04-03",
  "value" : 14223.28,
  "symbol" : "BANSANDER-B"
}, {
  "date" : "2005-04-04",
  "value" : 14258.14,
  "symbol" : "BANSANDER-B"
}, {
  "date" : "2005-04-05",
  "value" : 14285.48,
  "symbol" : "BANSANDER-B"
}, {
  "date" : "2005-04-06",
  "value" : 14237.85,
  "symbol" : "BANSANDER-B"
}, {
  "date" : "2005-04-07",
  "value" : 14268.73,
  "symbol" : "BANSANDER-B"
}, {
  "date" : "2005-04-08",
  "value" : 14269.28,
  "symbol" : "BANSANDER-B"
}, {
  "date" : "2005-04-09",
  "value" : 14269.28,
  "symbol" : "BANSANDER-B"
}, {
  "date" : "2005-04-10",
  "value" : 14269.28,
  "symbol" : "BANSANDER-B"
}, {
  "date" : "2005-04-11",
  "value" : 14328.41,
  "symbol" : "BANSANDER-B"
}, {
  "date" : "2005-04-12",
  "value" : 14325.61,
  "symbol" : "BANSANDER-B"
}, {
  "date" : "2005-04-13",
  "value" : 14363.05,
  "symbol" : "BANSANDER-B"
}, {
  "date" : "2005-04-14",
  "value" : 14348.05,
  "symbol" : "BANSANDER-B"
}, {
  "date" : "2005-04-15",
  "value" : 14351.61,
  "symbol" : "BANSANDER-B"
}, {
  "date" : "2005-04-16",
  "value" : 14351.61,
  "symbol" : "BANSANDER-B"
}, {
  "date" : "2005-04-17",
  "value" : 14351.61,
  "symbol" : "BANSANDER-B"
}, {
  "date" : "2005-04-18",
  "value" : 14263.91,
  "symbol" : "BANSANDER-B"
}, {
  "date" : "2005-04-19",
  "value" : 14229.15,
  "symbol" : "BANSANDER-B"
}, {
  "date" : "2005-04-20",
  "value" : 14135.09,
  "symbol" : "BANSANDER-B"
}, {
  "date" : "2005-04-21",
  "value" : 14219.39,
  "symbol" : "BANSANDER-B"
}, {
  "date" : "2005-04-22",
  "value" : 14213.10,
  "symbol" : "BANSANDER-B"
}, {
  "date" : "2005-04-23",
  "value" : 14213.10,
  "symbol" : "BANSANDER-B"
}, {
  "date" : "2005-04-24",
  "value" : 14213.10,
  "symbol" : "BANSANDER-B"
}, {
  "date" : "2005-04-25",
  "value" : 14218.88,
  "symbol" : "BANSANDER-B"
}, {
  "date" : "2005-04-26",
  "value" : 14227.11,
  "symbol" : "BANSANDER-B"
}, {
  "date" : "2005-04-27",
  "value" : 14283.21,
  "symbol" : "BANSANDER-B"
}, {
  "date" : "2005-04-28",
  "value" : 14243.39,
  "symbol" : "BANSANDER-B"
}, {
  "date" : "2005-04-29",
  "value" : 14209.10,
  "symbol" : "BANSANDER-B"
}, {
  "date" : "2005-04-30",
  "value" : 14209.10,
  "symbol" : "BANSANDER-B"
}, {
  "date" : "2005-05-01",
  "value" : 14209.10,
  "symbol" : "BANSANDER-B"
}, {
  "date" : "2005-05-02",
  "value" : 14139.90,
  "symbol" : "BANSANDER-B"
}, {
  "date" : "2005-05-03",
  "value" : 14159.41,
  "symbol" : "BANSANDER-B"
}, {
  "date" : "2005-05-04",
  "value" : 14179.91,
  "symbol" : "BANSANDER-B"
}, {
  "date" : "2005-05-05",
  "value" : 14200.06,
  "symbol" : "BANSANDER-B"
}, {
  "date" : "2005-05-06",
  "value" : 14270.85,
  "symbol" : "BANSANDER-B"
}, {
  "date" : "2005-05-07",
  "value" : 14270.85,
  "symbol" : "BANSANDER-B"
}, {
  "date" : "2005-05-08",
  "value" : 14270.85,
  "symbol" : "BANSANDER-B"
}, {
  "date" : "2005-05-09",
  "value" : 14272.64,
  "symbol" : "BANSANDER-B"
}, {
  "date" : "2005-05-10",
  "value" : 14343.50,
  "symbol" : "BANSANDER-B"
}, {
  "date" : "2005-05-11",
  "value" : 14345.55,
  "symbol" : "BANSANDER-B"
}, {
  "date" : "2005-05-12",
  "value" : 14307.57,
  "symbol" : "BANSANDER-B"
}, {
  "date" : "2005-05-13",
  "value" : 14260.74,
  "symbol" : "BANSANDER-B"
}, {
  "date" : "2005-05-14",
  "value" : 14260.74,
  "symbol" : "BANSANDER-B"
}, {
  "date" : "2005-05-15",
  "value" : 14260.74,
  "symbol" : "BANSANDER-B"
}, {
  "date" : "2005-05-16",
  "value" : 14210.52,
  "symbol" : "BANSANDER-B"
}, {
  "date" : "2005-05-17",
  "value" : 14193.64,
  "symbol" : "BANSANDER-B"
}, {
  "date" : "2005-05-18",
  "value" : 14185.48,
  "symbol" : "BANSANDER-B"
}, {
  "date" : "2005-05-19",
  "value" : 14233.32,
  "symbol" : "BANSANDER-B"
}, {
  "date" : "2005-05-20",
  "value" : 14260.69,
  "symbol" : "BANSANDER-B"
}, {
  "date" : "2005-05-21",
  "value" : 14260.69,
  "symbol" : "BANSANDER-B"
}, {
  "date" : "2005-05-22",
  "value" : 14260.69,
  "symbol" : "BANSANDER-B"
}, {
  "date" : "2005-05-23",
  "value" : 14260.69,
  "symbol" : "BANSANDER-B"
}, {
  "date" : "2005-05-24",
  "value" : 14340.71,
  "symbol" : "BANSANDER-B"
}, {
  "date" : "2005-05-25",
  "value" : 14296.68,
  "symbol" : "BANSANDER-B"
}, {
  "date" : "2005-05-26",
  "value" : 14313.86,
  "symbol" : "BANSANDER-B"
}, {
  "date" : "2005-05-27",
  "value" : 14317.19,
  "symbol" : "BANSANDER-B"
}, {
  "date" : "2005-05-28",
  "value" : 14317.19,
  "symbol" : "BANSANDER-B"
}, {
  "date" : "2005-05-29",
  "value" : 14317.19,
  "symbol" : "BANSANDER-B"
}, {
  "date" : "2005-05-30",
  "value" : 14336.46,
  "symbol" : "BANSANDER-B"
}, {
  "date" : "2005-05-31",
  "value" : 14369.26,
  "symbol" : "BANSANDER-B"
}, {
  "date" : "2005-06-01",
  "value" : 14400.16,
  "symbol" : "BANSANDER-B"
}, {
  "date" : "2005-06-02",
  "value" : 14410.27,
  "symbol" : "BANSANDER-B"
}, {
  "date" : "2005-06-03",
  "value" : 14449.62,
  "symbol" : "BANSANDER-B"
}, {
  "date" : "2005-06-04",
  "value" : 14449.62,
  "symbol" : "BANSANDER-B"
}, {
  "date" : "2005-06-05",
  "value" : 14449.62,
  "symbol" : "BANSANDER-B"
}, {
  "date" : "2005-06-06",
  "value" : 14520.84,
  "symbol" : "BANSANDER-B"
}, {
  "date" : "2005-06-07",
  "value" : 14600.17,
  "symbol" : "BANSANDER-B"
}, {
  "date" : "2005-06-08",
  "value" : 14556.59,
  "symbol" : "BANSANDER-B"
}, {
  "date" : "2005-06-09",
  "value" : 14554.04,
  "symbol" : "BANSANDER-B"
}, {
  "date" : "2005-06-10",
  "value" : 14581.78,
  "symbol" : "BANSANDER-B"
}, {
  "date" : "2005-06-11",
  "value" : 14581.78,
  "symbol" : "BANSANDER-B"
}, {
  "date" : "2005-06-12",
  "value" : 14581.78,
  "symbol" : "BANSANDER-B"
}, {
  "date" : "2005-06-13",
  "value" : 14577.66,
  "symbol" : "BANSANDER-B"
}, {
  "date" : "2005-06-14",
  "value" : 14595.89,
  "symbol" : "BANSANDER-B"
}, {
  "date" : "2005-06-15",
  "value" : 14580.59,
  "symbol" : "BANSANDER-B"
}, {
  "date" : "2005-06-16",
  "value" : 14624.84,
  "symbol" : "BANSANDER-B"
}, {
  "date" : "2005-06-17",
  "value" : 14650.00,
  "symbol" : "BANSANDER-B"
}, {
  "date" : "2005-06-18",
  "value" : 14650.00,
  "symbol" : "BANSANDER-B"
}, {
  "date" : "2005-06-19",
  "value" : 14650.00,
  "symbol" : "BANSANDER-B"
}, {
  "date" : "2005-06-20",
  "value" : 14696.49,
  "symbol" : "BANSANDER-B"
}, {
  "date" : "2005-06-21",
  "value" : 14743.07,
  "symbol" : "BANSANDER-B"
}, {
  "date" : "2005-06-22",
  "value" : 14712.11,
  "symbol" : "BANSANDER-B"
}, {
  "date" : "2005-06-23",
  "value" : 14751.01,
  "symbol" : "BANSANDER-B"
}, {
  "date" : "2005-06-24",
  "value" : 14784.22,
  "symbol" : "BANSANDER-B"
}, {
  "date" : "2005-06-25",
  "value" : 14784.22,
  "symbol" : "BANSANDER-B"
}, {
  "date" : "2005-06-26",
  "value" : 14784.22,
  "symbol" : "BANSANDER-B"
}, {
  "date" : "2005-06-27",
  "value" : 14784.22,
  "symbol" : "BANSANDER-B"
}, {
  "date" : "2005-06-28",
  "value" : 14739.59,
  "symbol" : "BANSANDER-B"
}, {
  "date" : "2005-06-29",
  "value" : 14698.55,
  "symbol" : "BANSANDER-B"
}, {
  "date" : "2005-06-30",
  "value" : 14728.33,
  "symbol" : "BANSANDER-B"
}, {
  "date" : "2005-07-01",
  "value" : 14733.84,
  "symbol" : "BANSANDER-B"
}, {
  "date" : "2005-07-02",
  "value" : 14733.84,
  "symbol" : "BANSANDER-B"
}, {
  "date" : "2005-07-03",
  "value" : 14733.84,
  "symbol" : "BANSANDER-B"
}, {
  "date" : "2005-07-04",
  "value" : 14698.31,
  "symbol" : "BANSANDER-B"
}, {
  "date" : "2005-07-05",
  "value" : 14746.74,
  "symbol" : "BANSANDER-B"
}, {
  "date" : "2005-07-06",
  "value" : 14735.09,
  "symbol" : "BANSANDER-B"
}, {
  "date" : "2005-07-07",
  "value" : 14750.75,
  "symbol" : "BANSANDER-B"
}, {
  "date" : "2005-07-08",
  "value" : 14754.81,
  "symbol" : "BANSANDER-B"
}, {
  "date" : "2005-07-09",
  "value" : 14754.81,
  "symbol" : "BANSANDER-B"
}, {
  "date" : "2005-07-10",
  "value" : 14754.81,
  "symbol" : "BANSANDER-B"
}, {
  "date" : "2005-07-11",
  "value" : 14718.15,
  "symbol" : "BANSANDER-B"
}, {
  "date" : "2005-07-12",
  "value" : 14777.77,
  "symbol" : "BANSANDER-B"
}, {
  "date" : "2005-07-13",
  "value" : 14820.75,
  "symbol" : "BANSANDER-B"
}, {
  "date" : "2005-07-14",
  "value" : 14863.55,
  "symbol" : "BANSANDER-B"
}, {
  "date" : "2005-07-15",
  "value" : 14892.55,
  "symbol" : "BANSANDER-B"
}, {
  "date" : "2005-07-16",
  "value" : 14892.55,
  "symbol" : "BANSANDER-B"
}, {
  "date" : "2005-07-17",
  "value" : 14892.55,
  "symbol" : "BANSANDER-B"
}, {
  "date" : "2005-07-18",
  "value" : 14898.71,
  "symbol" : "BANSANDER-B"
}, {
  "date" : "2005-07-19",
  "value" : 14865.99,
  "symbol" : "BANSANDER-B"
}, {
  "date" : "2005-07-20",
  "value" : 14882.32,
  "symbol" : "BANSANDER-B"
}, {
  "date" : "2005-07-21",
  "value" : 14980.31,
  "symbol" : "BANSANDER-B"
}, {
  "date" : "2005-07-22",
  "value" : 14957.81,
  "symbol" : "BANSANDER-B"
}, {
  "date" : "2005-07-23",
  "value" : 14957.81,
  "symbol" : "BANSANDER-B"
}, {
  "date" : "2005-07-24",
  "value" : 14957.81,
  "symbol" : "BANSANDER-B"
}, {
  "date" : "2005-07-25",
  "value" : 14979.74,
  "symbol" : "BANSANDER-B"
}, {
  "date" : "2005-07-26",
  "value" : 15034.26,
  "symbol" : "BANSANDER-B"
}, {
  "date" : "2005-07-27",
  "value" : 14992.05,
  "symbol" : "BANSANDER-B"
}, {
  "date" : "2005-07-28",
  "value" : 15011.99,
  "symbol" : "BANSANDER-B"
}, {
  "date" : "2005-07-29",
  "value" : 15070.97,
  "symbol" : "BANSANDER-B"
}, {
  "date" : "2005-07-30",
  "value" : 15070.97,
  "symbol" : "BANSANDER-B"
}, {
  "date" : "2005-07-31",
  "value" : 15070.97,
  "symbol" : "BANSANDER-B"
}, {
  "date" : "2005-08-01",
  "value" : 15116.35,
  "symbol" : "BANSANDER-B"
}, {
  "date" : "2005-08-02",
  "value" : 15149.72,
  "symbol" : "BANSANDER-B"
}, {
  "date" : "2005-08-03",
  "value" : 15205.28,
  "symbol" : "BANSANDER-B"
}, {
  "date" : "2005-08-04",
  "value" : 15269.48,
  "symbol" : "BANSANDER-B"
}, {
  "date" : "2005-08-05",
  "value" : 15200.76,
  "symbol" : "BANSANDER-B"
}, {
  "date" : "2005-08-06",
  "value" : 15200.76,
  "symbol" : "BANSANDER-B"
}, {
  "date" : "2005-08-07",
  "value" : 15200.76,
  "symbol" : "BANSANDER-B"
}, {
  "date" : "2005-08-08",
  "value" : 15116.09,
  "symbol" : "BANSANDER-B"
}, {
  "date" : "2005-08-09",
  "value" : 15132.97,
  "symbol" : "BANSANDER-B"
}, {
  "date" : "2005-08-10",
  "value" : 15178.98,
  "symbol" : "BANSANDER-B"
}, {
  "date" : "2005-08-11",
  "value" : 15169.97,
  "symbol" : "BANSANDER-B"
}, {
  "date" : "2005-08-12",
  "value" : 15172.82,
  "symbol" : "BANSANDER-B"
}, {
  "date" : "2005-08-13",
  "value" : 15172.82,
  "symbol" : "BANSANDER-B"
}, {
  "date" : "2005-08-14",
  "value" : 15172.82,
  "symbol" : "BANSANDER-B"
}, {
  "date" : "2005-08-15",
  "value" : 15172.82,
  "symbol" : "BANSANDER-B"
}, {
  "date" : "2005-08-16",
  "value" : 15158.83,
  "symbol" : "BANSANDER-B"
}, {
  "date" : "2005-08-17",
  "value" : 15096.59,
  "symbol" : "BANSANDER-B"
}, {
  "date" : "2005-08-18",
  "value" : 15095.39,
  "symbol" : "BANSANDER-B"
}, {
  "date" : "2005-08-19",
  "value" : 15148.45,
  "symbol" : "BANSANDER-B"
}, {
  "date" : "2005-08-20",
  "value" : 15148.45,
  "symbol" : "BANSANDER-B"
}, {
  "date" : "2005-08-21",
  "value" : 15148.45,
  "symbol" : "BANSANDER-B"
}, {
  "date" : "2005-08-22",
  "value" : 15153.61,
  "symbol" : "BANSANDER-B"
}, {
  "date" : "2005-08-23",
  "value" : 15073.08,
  "symbol" : "BANSANDER-B"
}, {
  "date" : "2005-08-24",
  "value" : 15158.35,
  "symbol" : "BANSANDER-B"
}, {
  "date" : "2005-08-25",
  "value" : 15213.85,
  "symbol" : "BANSANDER-B"
}, {
  "date" : "2005-08-26",
  "value" : 15122.61,
  "symbol" : "BANSANDER-B"
}, {
  "date" : "2005-08-27",
  "value" : 15122.61,
  "symbol" : "BANSANDER-B"
}, {
  "date" : "2005-08-28",
  "value" : 15122.61,
  "symbol" : "BANSANDER-B"
}, {
  "date" : "2005-08-29",
  "value" : 15164.17,
  "symbol" : "BANSANDER-B"
}, {
  "date" : "2005-08-30",
  "value" : 15173.19,
  "symbol" : "BANSANDER-B"
}, {
  "date" : "2005-08-31",
  "value" : 15102.88,
  "symbol" : "BANSANDER-B"
}, {
  "date" : "2005-09-01",
  "value" : 15088.24,
  "symbol" : "BANSANDER-B"
}, {
  "date" : "2005-09-02",
  "value" : 15161.20,
  "symbol" : "BANSANDER-B"
}, {
  "date" : "2005-09-03",
  "value" : 15161.20,
  "symbol" : "BANSANDER-B"
}, {
  "date" : "2005-09-04",
  "value" : 15161.20,
  "symbol" : "BANSANDER-B"
}, {
  "date" : "2005-09-05",
  "value" : 15166.50,
  "symbol" : "BANSANDER-B"
}, {
  "date" : "2005-09-06",
  "value" : 15205.84,
  "symbol" : "BANSANDER-B"
}, {
  "date" : "2005-09-07",
  "value" : 15216.39,
  "symbol" : "BANSANDER-B"
}, {
  "date" : "2005-09-08",
  "value" : 15287.39,
  "symbol" : "BANSANDER-B"
}, {
  "date" : "2005-09-09",
  "value" : 15227.99,
  "symbol" : "BANSANDER-B"
}, {
  "date" : "2005-09-10",
  "value" : 15227.99,
  "symbol" : "BANSANDER-B"
}, {
  "date" : "2005-09-11",
  "value" : 15227.99,
  "symbol" : "BANSANDER-B"
}, {
  "date" : "2005-09-12",
  "value" : 15283.49,
  "symbol" : "BANSANDER-B"
}, {
  "date" : "2005-09-13",
  "value" : 15340.95,
  "symbol" : "BANSANDER-B"
}, {
  "date" : "2005-09-14",
  "value" : 15379.87,
  "symbol" : "BANSANDER-B"
}, {
  "date" : "2005-09-15",
  "value" : 15330.89,
  "symbol" : "BANSANDER-B"
}, {
  "date" : "2005-09-16",
  "value" : 15344.18,
  "symbol" : "BANSANDER-B"
}, {
  "date" : "2005-09-17",
  "value" : 15344.18,
  "symbol" : "BANSANDER-B"
}, {
  "date" : "2005-09-18",
  "value" : 15344.18,
  "symbol" : "BANSANDER-B"
}, {
  "date" : "2005-09-19",
  "value" : 15344.18,
  "symbol" : "BANSANDER-B"
}, {
  "date" : "2005-09-20",
  "value" : 15353.36,
  "symbol" : "BANSANDER-B"
}, {
  "date" : "2005-09-21",
  "value" : 15432.48,
  "symbol" : "BANSANDER-B"
}, {
  "date" : "2005-09-22",
  "value" : 15477.33,
  "symbol" : "BANSANDER-B"
}, {
  "date" : "2005-09-23",
  "value" : 15515.54,
  "symbol" : "BANSANDER-B"
}, {
  "date" : "2005-09-24",
  "value" : 15515.54,
  "symbol" : "BANSANDER-B"
}, {
  "date" : "2005-09-25",
  "value" : 15515.54,
  "symbol" : "BANSANDER-B"
}, {
  "date" : "2005-09-26",
  "value" : 15493.19,
  "symbol" : "BANSANDER-B"
}, {
  "date" : "2005-09-27",
  "value" : 15503.71,
  "symbol" : "BANSANDER-B"
}, {
  "date" : "2005-09-28",
  "value" : 15527.04,
  "symbol" : "BANSANDER-B"
}, {
  "date" : "2005-09-29",
  "value" : 15518.24,
  "symbol" : "BANSANDER-B"
}, {
  "date" : "2005-09-30",
  "value" : 15508.39,
  "symbol" : "BANSANDER-B"
}, {
  "date" : "2005-10-01",
  "value" : 15508.39,
  "symbol" : "BANSANDER-B"
}, {
  "date" : "2005-10-02",
  "value" : 15508.39,
  "symbol" : "BANSANDER-B"
}, {
  "date" : "2005-10-03",
  "value" : 15515.58,
  "symbol" : "BANSANDER-B"
}, {
  "date" : "2005-10-04",
  "value" : 15551.50,
  "symbol" : "BANSANDER-B"
}, {
  "date" : "2005-10-05",
  "value" : 15599.88,
  "symbol" : "BANSANDER-B"
}, {
  "date" : "2005-10-06",
  "value" : 15610.94,
  "symbol" : "BANSANDER-B"
}, {
  "date" : "2005-10-07",
  "value" : 15508.16,
  "symbol" : "BANSANDER-B"
}, {
  "date" : "2005-10-08",
  "value" : 15508.16,
  "symbol" : "BANSANDER-B"
}, {
  "date" : "2005-10-09",
  "value" : 15508.16,
  "symbol" : "BANSANDER-B"
}, {
  "date" : "2005-10-10",
  "value" : 15508.16,
  "symbol" : "BANSANDER-B"
}, {
  "date" : "2005-10-11",
  "value" : 15426.07,
  "symbol" : "BANSANDER-B"
}, {
  "date" : "2005-10-12",
  "value" : 15403.25,
  "symbol" : "BANSANDER-B"
}, {
  "date" : "2005-10-13",
  "value" : 15436.18,
  "symbol" : "BANSANDER-B"
}, {
  "date" : "2005-10-14",
  "value" : 15405.37,
  "symbol" : "BANSANDER-B"
}, {
  "date" : "2005-10-15",
  "value" : 15405.37,
  "symbol" : "BANSANDER-B"
}, {
  "date" : "2005-10-16",
  "value" : 15405.37,
  "symbol" : "BANSANDER-B"
}, {
  "date" : "2005-10-17",
  "value" : 15323.70,
  "symbol" : "BANSANDER-B"
}, {
  "date" : "2005-10-18",
  "value" : 15254.44,
  "symbol" : "BANSANDER-B"
}, {
  "date" : "2005-10-19",
  "value" : 15254.72,
  "symbol" : "BANSANDER-B"
}, {
  "date" : "2005-10-20",
  "value" : 15217.14,
  "symbol" : "BANSANDER-B"
}, {
  "date" : "2005-10-21",
  "value" : 15106.21,
  "symbol" : "BANSANDER-B"
}, {
  "date" : "2005-10-22",
  "value" : 15106.21,
  "symbol" : "BANSANDER-B"
}, {
  "date" : "2005-10-23",
  "value" : 15106.21,
  "symbol" : "BANSANDER-B"
}, {
  "date" : "2005-10-24",
  "value" : 15111.43,
  "symbol" : "BANSANDER-B"
}, {
  "date" : "2005-10-25",
  "value" : 15147.15,
  "symbol" : "BANSANDER-B"
}, {
  "date" : "2005-10-26",
  "value" : 15188.58,
  "symbol" : "BANSANDER-B"
}, {
  "date" : "2005-10-27",
  "value" : 15213.78,
  "symbol" : "BANSANDER-B"
}, {
  "date" : "2005-10-28",
  "value" : 15188.07,
  "symbol" : "BANSANDER-B"
}, {
  "date" : "2005-10-29",
  "value" : 15188.07,
  "symbol" : "BANSANDER-B"
}, {
  "date" : "2005-10-30",
  "value" : 15188.07,
  "symbol" : "BANSANDER-B"
}, {
  "date" : "2005-10-31",
  "value" : 15050.43,
  "symbol" : "BANSANDER-B"
}, {
  "date" : "2005-11-01",
  "value" : 15050.43,
  "symbol" : "BANSANDER-B"
}, {
  "date" : "2005-11-02",
  "value" : 15057.49,
  "symbol" : "BANSANDER-B"
}, {
  "date" : "2005-11-03",
  "value" : 15216.63,
  "symbol" : "BANSANDER-B"
}, {
  "date" : "2005-11-04",
  "value" : 15244.08,
  "symbol" : "BANSANDER-B"
}, {
  "date" : "2005-11-05",
  "value" : 15244.08,
  "symbol" : "BANSANDER-B"
}, {
  "date" : "2005-11-06",
  "value" : 15244.08,
  "symbol" : "BANSANDER-B"
}, {
  "date" : "2005-11-07",
  "value" : 15207.94,
  "symbol" : "BANSANDER-B"
}, {
  "date" : "2005-11-08",
  "value" : 15130.12,
  "symbol" : "BANSANDER-B"
}, {
  "date" : "2005-11-09",
  "value" : 15117.63,
  "symbol" : "BANSANDER-B"
}, {
  "date" : "2005-11-10",
  "value" : 15054.93,
  "symbol" : "BANSANDER-B"
}, {
  "date" : "2005-11-11",
  "value" : 15116.79,
  "symbol" : "BANSANDER-B"
}, {
  "date" : "2005-11-12",
  "value" : 15116.79,
  "symbol" : "BANSANDER-B"
}, {
  "date" : "2005-11-13",
  "value" : 15116.79,
  "symbol" : "BANSANDER-B"
}, {
  "date" : "2005-11-14",
  "value" : 15084.74,
  "symbol" : "BANSANDER-B"
}, {
  "date" : "2005-11-15",
  "value" : 15163.55,
  "symbol" : "BANSANDER-B"
}, {
  "date" : "2005-11-16",
  "value" : 15113.81,
  "symbol" : "BANSANDER-B"
}, {
  "date" : "2005-11-17",
  "value" : 15099.21,
  "symbol" : "BANSANDER-B"
}, {
  "date" : "2005-11-18",
  "value" : 15143.83,
  "symbol" : "BANSANDER-B"
}, {
  "date" : "2005-11-19",
  "value" : 15143.83,
  "symbol" : "BANSANDER-B"
}, {
  "date" : "2005-11-20",
  "value" : 15143.83,
  "symbol" : "BANSANDER-B"
}, {
  "date" : "2005-11-21",
  "value" : 15278.29,
  "symbol" : "BANSANDER-B"
}, {
  "date" : "2005-11-22",
  "value" : 15278.85,
  "symbol" : "BANSANDER-B"
}, {
  "date" : "2005-11-23",
  "value" : 15300.02,
  "symbol" : "BANSANDER-B"
}, {
  "date" : "2005-11-24",
  "value" : 15271.21,
  "symbol" : "BANSANDER-B"
}, {
  "date" : "2005-11-25",
  "value" : 15326.86,
  "symbol" : "BANSANDER-B"
}, {
  "date" : "2005-11-26",
  "value" : 15326.86,
  "symbol" : "BANSANDER-B"
}, {
  "date" : "2005-11-27",
  "value" : 15326.86,
  "symbol" : "BANSANDER-B"
}, {
  "date" : "2005-11-28",
  "value" : 15300.90,
  "symbol" : "BANSANDER-B"
}, {
  "date" : "2005-11-29",
  "value" : 15309.80,
  "symbol" : "BANSANDER-B"
}, {
  "date" : "2005-11-30",
  "value" : 15270.89,
  "symbol" : "BANSANDER-B"
}, {
  "date" : "2005-12-01",
  "value" : 15258.29,
  "symbol" : "BANSANDER-B"
}, {
  "date" : "2005-12-02",
  "value" : 15220.05,
  "symbol" : "BANSANDER-B"
}, {
  "date" : "2005-12-03",
  "value" : 15220.05,
  "symbol" : "BANSANDER-B"
}, {
  "date" : "2005-12-04",
  "value" : 15220.05,
  "symbol" : "BANSANDER-B"
}, {
  "date" : "2005-12-05",
  "value" : 15286.18,
  "symbol" : "BANSANDER-B"
}, {
  "date" : "2005-12-06",
  "value" : 15388.20,
  "symbol" : "BANSANDER-B"
}, {
  "date" : "2005-12-07",
  "value" : 15355.59,
  "symbol" : "BANSANDER-B"
}, {
  "date" : "2005-12-08",
  "value" : 15355.59,
  "symbol" : "BANSANDER-B"
}, {
  "date" : "2005-12-09",
  "value" : 15354.28,
  "symbol" : "BANSANDER-B"
}, {
  "date" : "2005-12-10",
  "value" : 15354.28,
  "symbol" : "BANSANDER-B"
}, {
  "date" : "2005-12-11",
  "value" : 15354.28,
  "symbol" : "BANSANDER-B"
}, {
  "date" : "2005-12-12",
  "value" : 15389.80,
  "symbol" : "BANSANDER-B"
}, {
  "date" : "2005-12-13",
  "value" : 15319.59,
  "symbol" : "BANSANDER-B"
}, {
  "date" : "2005-12-14",
  "value" : 15333.38,
  "symbol" : "BANSANDER-B"
}, {
  "date" : "2005-12-15",
  "value" : 15408.10,
  "symbol" : "BANSANDER-B"
}, {
  "date" : "2005-12-16",
  "value" : 15387.32,
  "symbol" : "BANSANDER-B"
}, {
  "date" : "2005-12-17",
  "value" : 15387.32,
  "symbol" : "BANSANDER-B"
}, {
  "date" : "2005-12-18",
  "value" : 15387.32,
  "symbol" : "BANSANDER-B"
}, {
  "date" : "2005-12-19",
  "value" : 15435.06,
  "symbol" : "BANSANDER-B"
}, {
  "date" : "2005-12-20",
  "value" : 15447.94,
  "symbol" : "BANSANDER-B"
}, {
  "date" : "2005-12-21",
  "value" : 15357.27,
  "symbol" : "BANSANDER-B"
}, {
  "date" : "2005-12-22",
  "value" : 15311.43,
  "symbol" : "BANSANDER-B"
}, {
  "date" : "2005-12-23",
  "value" : 15409.35,
  "symbol" : "BANSANDER-B"
}, {
  "date" : "2005-12-24",
  "value" : 15409.35,
  "symbol" : "BANSANDER-B"
}, {
  "date" : "2005-12-25",
  "value" : 15409.35,
  "symbol" : "BANSANDER-B"
}, {
  "date" : "2005-12-26",
  "value" : 15431.60,
  "symbol" : "BANSANDER-B"
}, {
  "date" : "2005-12-27",
  "value" : 15433.53,
  "symbol" : "BANSANDER-B"
}, {
  "date" : "2005-12-28",
  "value" : 15425.65,
  "symbol" : "BANSANDER-B"
}, {
  "date" : "2005-12-29",
  "value" : 15414.31,
  "symbol" : "BANSANDER-B"
}, {
  "date" : "2005-12-30",
  "value" : 15424.61,
  "symbol" : "BANSANDER-B"
}, {
  "date" : "2005-12-31",
  "value" : 15424.61,
  "symbol" : "BANSANDER-B"
}, {
  "date" : "2006-01-01",
  "value" : 15424.61,
  "symbol" : "BANSANDER-B"
}, {
  "date" : "2006-01-02",
  "value" : 15457.85,
  "symbol" : "BANSANDER-B"
}, {
  "date" : "2006-01-03",
  "value" : 15459.18,
  "symbol" : "BANSANDER-B"
}, {
  "date" : "2006-01-04",
  "value" : 15483.50,
  "symbol" : "BANSANDER-B"
}, {
  "date" : "2006-01-05",
  "value" : 15604.02,
  "symbol" : "BANSANDER-B"
}, {
  "date" : "2006-01-06",
  "value" : 15746.75,
  "symbol" : "BANSANDER-B"
}, {
  "date" : "2006-01-07",
  "value" : 15746.75,
  "symbol" : "BANSANDER-B"
}, {
  "date" : "2006-01-08",
  "value" : 15746.75,
  "symbol" : "BANSANDER-B"
}, {
  "date" : "2006-01-09",
  "value" : 15845.26,
  "symbol" : "BANSANDER-B"
}, {
  "date" : "2006-01-10",
  "value" : 15906.07,
  "symbol" : "BANSANDER-B"
}, {
  "date" : "2006-01-11",
  "value" : 15952.45,
  "symbol" : "BANSANDER-B"
}, {
  "date" : "2006-01-12",
  "value" : 15927.28,
  "symbol" : "BANSANDER-B"
}, {
  "date" : "2006-01-13",
  "value" : 15979.17,
  "symbol" : "BANSANDER-B"
}, {
  "date" : "2006-01-14",
  "value" : 15979.17,
  "symbol" : "BANSANDER-B"
}, {
  "date" : "2006-01-15",
  "value" : 15979.17,
  "symbol" : "BANSANDER-B"
}, {
  "date" : "2006-01-16",
  "value" : 16041.12,
  "symbol" : "BANSANDER-B"
}, {
  "date" : "2006-01-17",
  "value" : 16030.16,
  "symbol" : "BANSANDER-B"
}, {
  "date" : "2006-01-18",
  "value" : 16044.10,
  "symbol" : "BANSANDER-B"
}, {
  "date" : "2006-01-19",
  "value" : 15992.74,
  "symbol" : "BANSANDER-B"
}, {
  "date" : "2006-01-20",
  "value" : 15917.32,
  "symbol" : "BANSANDER-B"
}, {
  "date" : "2006-01-21",
  "value" : 15917.32,
  "symbol" : "BANSANDER-B"
}, {
  "date" : "2006-01-22",
  "value" : 15917.32,
  "symbol" : "BANSANDER-B"
}, {
  "date" : "2006-01-23",
  "value" : 16015.54,
  "symbol" : "BANSANDER-B"
}, {
  "date" : "2006-01-24",
  "value" : 16002.07,
  "symbol" : "BANSANDER-B"
}, {
  "date" : "2006-01-25",
  "value" : 15932.69,
  "symbol" : "BANSANDER-B"
}, {
  "date" : "2006-01-26",
  "value" : 15998.47,
  "symbol" : "BANSANDER-B"
}, {
  "date" : "2006-01-27",
  "value" : 16092.26,
  "symbol" : "BANSANDER-B"
}, {
  "date" : "2006-01-28",
  "value" : 16092.26,
  "symbol" : "BANSANDER-B"
}, {
  "date" : "2006-01-29",
  "value" : 16092.26,
  "symbol" : "BANSANDER-B"
}, {
  "date" : "2006-01-30",
  "value" : 16156.07,
  "symbol" : "BANSANDER-B"
}, {
  "date" : "2006-01-31",
  "value" : 16230.02,
  "symbol" : "BANSANDER-B"
}, {
  "date" : "2006-02-01",
  "value" : 16262.29,
  "symbol" : "BANSANDER-B"
}, {
  "date" : "2006-02-02",
  "value" : 16276.41,
  "symbol" : "BANSANDER-B"
}, {
  "date" : "2006-02-03",
  "value" : 16284.99,
  "symbol" : "BANSANDER-B"
}, {
  "date" : "2006-02-04",
  "value" : 16284.99,
  "symbol" : "BANSANDER-B"
}, {
  "date" : "2006-02-05",
  "value" : 16284.99,
  "symbol" : "BANSANDER-B"
}, {
  "date" : "2006-02-06",
  "value" : 16232.30,
  "symbol" : "BANSANDER-B"
}, {
  "date" : "2006-02-07",
  "value" : 16170.18,
  "symbol" : "BANSANDER-B"
}, {
  "date" : "2006-02-08",
  "value" : 16205.69,
  "symbol" : "BANSANDER-B"
}, {
  "date" : "2006-02-09",
  "value" : 16183.70,
  "symbol" : "BANSANDER-B"
}, {
  "date" : "2006-02-10",
  "value" : 16136.59,
  "symbol" : "BANSANDER-B"
}, {
  "date" : "2006-02-11",
  "value" : 16136.59,
  "symbol" : "BANSANDER-B"
}, {
  "date" : "2006-02-12",
  "value" : 16136.59,
  "symbol" : "BANSANDER-B"
}, {
  "date" : "2006-02-13",
  "value" : 16186.22,
  "symbol" : "BANSANDER-B"
}, {
  "date" : "2006-02-14",
  "value" : 16210.06,
  "symbol" : "BANSANDER-B"
}, {
  "date" : "2006-02-15",
  "value" : 16143.92,
  "symbol" : "BANSANDER-B"
}, {
  "date" : "2006-02-16",
  "value" : 16142.93,
  "symbol" : "BANSANDER-B"
}, {
  "date" : "2006-02-17",
  "value" : 16132.14,
  "symbol" : "BANSANDER-B"
}, {
  "date" : "2006-02-18",
  "value" : 16132.14,
  "symbol" : "BANSANDER-B"
}, {
  "date" : "2006-02-19",
  "value" : 16132.14,
  "symbol" : "BANSANDER-B"
}, {
  "date" : "2006-02-20",
  "value" : 16143.71,
  "symbol" : "BANSANDER-B"
}, {
  "date" : "2006-02-21",
  "value" : 16186.97,
  "symbol" : "BANSANDER-B"
}, {
  "date" : "2006-02-22",
  "value" : 16181.35,
  "symbol" : "BANSANDER-B"
}, {
  "date" : "2006-02-23",
  "value" : 16228.40,
  "symbol" : "BANSANDER-B"
}, {
  "date" : "2006-02-24",
  "value" : 16261.70,
  "symbol" : "BANSANDER-B"
}, {
  "date" : "2006-02-25",
  "value" : 16261.70,
  "symbol" : "BANSANDER-B"
}, {
  "date" : "2006-02-26",
  "value" : 16261.70,
  "symbol" : "BANSANDER-B"
}, {
  "date" : "2006-02-27",
  "value" : 16304.37,
  "symbol" : "BANSANDER-B"
}, {
  "date" : "2006-02-28",
  "value" : 16357.15,
  "symbol" : "BANSANDER-B"
}, {
  "date" : "2006-03-01",
  "value" : 16429.12,
  "symbol" : "BANSANDER-B"
}, {
  "date" : "2006-03-02",
  "value" : 16345.38,
  "symbol" : "BANSANDER-B"
}, {
  "date" : "2006-03-03",
  "value" : 16377.65,
  "symbol" : "BANSANDER-B"
}, {
  "date" : "2006-03-04",
  "value" : 16377.65,
  "symbol" : "BANSANDER-B"
}, {
  "date" : "2006-03-05",
  "value" : 16377.65,
  "symbol" : "BANSANDER-B"
}, {
  "date" : "2006-03-06",
  "value" : 16398.21,
  "symbol" : "BANSANDER-B"
}, {
  "date" : "2006-03-07",
  "value" : 16411.77,
  "symbol" : "BANSANDER-B"
}, {
  "date" : "2006-03-08",
  "value" : 16392.73,
  "symbol" : "BANSANDER-B"
}, {
  "date" : "2006-03-09",
  "value" : 16309.24,
  "symbol" : "BANSANDER-B"
}, {
  "date" : "2006-03-10",
  "value" : 16193.51,
  "symbol" : "BANSANDER-B"
}, {
  "date" : "2006-03-11",
  "value" : 16193.51,
  "symbol" : "BANSANDER-B"
}, {
  "date" : "2006-03-12",
  "value" : 16193.51,
  "symbol" : "BANSANDER-B"
}, {
  "date" : "2006-03-13",
  "value" : 16197.36,
  "symbol" : "BANSANDER-B"
}, {
  "date" : "2006-03-14",
  "value" : 16250.18,
  "symbol" : "BANSANDER-B"
}, {
  "date" : "2006-03-15",
  "value" : 16313.76,
  "symbol" : "BANSANDER-B"
}, {
  "date" : "2006-03-16",
  "value" : 16357.14,
  "symbol" : "BANSANDER-B"
}, {
  "date" : "2006-03-17",
  "value" : 16433.72,
  "symbol" : "BANSANDER-B"
}, {
  "date" : "2006-03-18",
  "value" : 16433.72,
  "symbol" : "BANSANDER-B"
}, {
  "date" : "2006-03-19",
  "value" : 16433.72,
  "symbol" : "BANSANDER-B"
}, {
  "date" : "2006-03-20",
  "value" : 16482.32,
  "symbol" : "BANSANDER-B"
}, {
  "date" : "2006-03-21",
  "value" : 16532.09,
  "symbol" : "BANSANDER-B"
}, {
  "date" : "2006-03-22",
  "value" : 16552.33,
  "symbol" : "BANSANDER-B"
}, {
  "date" : "2006-03-23",
  "value" : 16496.02,
  "symbol" : "BANSANDER-B"
}, {
  "date" : "2006-03-24",
  "value" : 16466.35,
  "symbol" : "BANSANDER-B"
}, {
  "date" : "2006-03-25",
  "value" : 16466.35,
  "symbol" : "BANSANDER-B"
}, {
  "date" : "2006-03-26",
  "value" : 16466.35,
  "symbol" : "BANSANDER-B"
}, {
  "date" : "2006-03-27",
  "value" : 16513.32,
  "symbol" : "BANSANDER-B"
}, {
  "date" : "2006-03-28",
  "value" : 16550.50,
  "symbol" : "BANSANDER-B"
}, {
  "date" : "2006-03-29",
  "value" : 16544.68,
  "symbol" : "BANSANDER-B"
}, {
  "date" : "2006-03-30",
  "value" : 16503.54,
  "symbol" : "BANSANDER-B"
}, {
  "date" : "2006-03-31",
  "value" : 16557.20,
  "symbol" : "BANSANDER-B"
}, {
  "date" : "2006-04-01",
  "value" : 16557.20,
  "symbol" : "BANSANDER-B"
}, {
  "date" : "2006-04-02",
  "value" : 16557.20,
  "symbol" : "BANSANDER-B"
}, {
  "date" : "2006-04-03",
  "value" : 16574.84,
  "symbol" : "BANSANDER-B"
}, {
  "date" : "2006-04-04",
  "value" : 16604.61,
  "symbol" : "BANSANDER-B"
}, {
  "date" : "2006-04-05",
  "value" : 16655.93,
  "symbol" : "BANSANDER-B"
}, {
  "date" : "2006-04-06",
  "value" : 16700.14,
  "symbol" : "BANSANDER-B"
}, {
  "date" : "2006-04-07",
  "value" : 16723.97,
  "symbol" : "BANSANDER-B"
}, {
  "date" : "2006-04-08",
  "value" : 16723.97,
  "symbol" : "BANSANDER-B"
}, {
  "date" : "2006-04-09",
  "value" : 16723.97,
  "symbol" : "BANSANDER-B"
}, {
  "date" : "2006-04-10",
  "value" : 16748.60,
  "symbol" : "BANSANDER-B"
}, {
  "date" : "2006-04-11",
  "value" : 16709.36,
  "symbol" : "BANSANDER-B"
}, {
  "date" : "2006-04-12",
  "value" : 16684.58,
  "symbol" : "BANSANDER-B"
}, {
  "date" : "2006-04-13",
  "value" : 16606.25,
  "symbol" : "BANSANDER-B"
}, {
  "date" : "2006-04-14",
  "value" : 16606.25,
  "symbol" : "BANSANDER-B"
}, {
  "date" : "2006-04-15",
  "value" : 16606.25,
  "symbol" : "BANSANDER-B"
}, {
  "date" : "2006-04-16",
  "value" : 16606.25,
  "symbol" : "BANSANDER-B"
}, {
  "date" : "2006-04-17",
  "value" : 16618.95,
  "symbol" : "BANSANDER-B"
}, {
  "date" : "2006-04-18",
  "value" : 16641.45,
  "symbol" : "BANSANDER-B"
}, {
  "date" : "2006-04-19",
  "value" : 16693.90,
  "symbol" : "BANSANDER-B"
}, {
  "date" : "2006-04-20",
  "value" : 16822.72,
  "symbol" : "BANSANDER-B"
}, {
  "date" : "2006-04-21",
  "value" : 16904.79,
  "symbol" : "BANSANDER-B"
}, {
  "date" : "2006-04-22",
  "value" : 16904.79,
  "symbol" : "BANSANDER-B"
}, {
  "date" : "2006-04-23",
  "value" : 16904.79,
  "symbol" : "BANSANDER-B"
}, {
  "date" : "2006-04-24",
  "value" : 16946.89,
  "symbol" : "BANSANDER-B"
}, {
  "date" : "2006-04-25",
  "value" : 16988.66,
  "symbol" : "BANSANDER-B"
}, {
  "date" : "2006-04-26",
  "value" : 16979.15,
  "symbol" : "BANSANDER-B"
}, {
  "date" : "2006-04-27",
  "value" : 16982.96,
  "symbol" : "BANSANDER-B"
}, {
  "date" : "2006-04-28",
  "value" : 17030.88,
  "symbol" : "BANSANDER-B"
}, {
  "date" : "2006-04-29",
  "value" : 17030.88,
  "symbol" : "BANSANDER-B"
}, {
  "date" : "2006-04-30",
  "value" : 17030.88,
  "symbol" : "BANSANDER-B"
}, {
  "date" : "2006-05-01",
  "value" : 17030.88,
  "symbol" : "BANSANDER-B"
}, {
  "date" : "2006-05-02",
  "value" : 16985.83,
  "symbol" : "BANSANDER-B"
}, {
  "date" : "2006-05-03",
  "value" : 17021.70,
  "symbol" : "BANSANDER-B"
}, {
  "date" : "2006-05-04",
  "value" : 17083.78,
  "symbol" : "BANSANDER-B"
}, {
  "date" : "2006-05-05",
  "value" : 17107.81,
  "symbol" : "BANSANDER-B"
}, {
  "date" : "2006-05-06",
  "value" : 17107.81,
  "symbol" : "BANSANDER-B"
}, {
  "date" : "2006-05-07",
  "value" : 17107.81,
  "symbol" : "BANSANDER-B"
}, {
  "date" : "2006-05-08",
  "value" : 17151.57,
  "symbol" : "BANSANDER-B"
}, {
  "date" : "2006-05-09",
  "value" : 17238.79,
  "symbol" : "BANSANDER-B"
}, {
  "date" : "2006-05-10",
  "value" : 17325.80,
  "symbol" : "BANSANDER-B"
}, {
  "date" : "2006-05-11",
  "value" : 17313.46,
  "symbol" : "BANSANDER-B"
}, {
  "date" : "2006-05-12",
  "value" : 17291.31,
  "symbol" : "BANSANDER-B"
}, {
  "date" : "2006-05-13",
  "value" : 17291.31,
  "symbol" : "BANSANDER-B"
}, {
  "date" : "2006-05-14",
  "value" : 17291.31,
  "symbol" : "BANSANDER-B"
}, {
  "date" : "2006-05-15",
  "value" : 17220.54,
  "symbol" : "BANSANDER-B"
}, {
  "date" : "2006-05-16",
  "value" : 17123.50,
  "symbol" : "BANSANDER-B"
}, {
  "date" : "2006-05-17",
  "value" : 16912.11,
  "symbol" : "BANSANDER-B"
}, {
  "date" : "2006-05-18",
  "value" : 16890.38,
  "symbol" : "BANSANDER-B"
}, {
  "date" : "2006-05-19",
  "value" : 16789.85,
  "symbol" : "BANSANDER-B"
}, {
  "date" : "2006-05-20",
  "value" : 16789.85,
  "symbol" : "BANSANDER-B"
}, {
  "date" : "2006-05-21",
  "value" : 16789.85,
  "symbol" : "BANSANDER-B"
}, {
  "date" : "2006-05-22",
  "value" : 16633.28,
  "symbol" : "BANSANDER-B"
}, {
  "date" : "2006-05-23",
  "value" : 16600.00,
  "symbol" : "BANSANDER-B"
}, {
  "date" : "2006-05-24",
  "value" : 16405.18,
  "symbol" : "BANSANDER-B"
}, {
  "date" : "2006-05-25",
  "value" : 16412.89,
  "symbol" : "BANSANDER-B"
}, {
  "date" : "2006-05-26",
  "value" : 16343.77,
  "symbol" : "BANSANDER-B"
}, {
  "date" : "2006-05-27",
  "value" : 16343.77,
  "symbol" : "BANSANDER-B"
}, {
  "date" : "2006-05-28",
  "value" : 16343.77,
  "symbol" : "BANSANDER-B"
}, {
  "date" : "2006-05-29",
  "value" : 16387.60,
  "symbol" : "BANSANDER-B"
}, {
  "date" : "2006-05-30",
  "value" : 16527.13,
  "symbol" : "BANSANDER-B"
}, {
  "date" : "2006-05-31",
  "value" : 16567.14,
  "symbol" : "BANSANDER-B"
}, {
  "date" : "2006-06-01",
  "value" : 16430.36,
  "symbol" : "BANSANDER-B"
}, {
  "date" : "2006-06-02",
  "value" : 16440.79,
  "symbol" : "BANSANDER-B"
}, {
  "date" : "2006-06-03",
  "value" : 16440.79,
  "symbol" : "BANSANDER-B"
}, {
  "date" : "2006-06-04",
  "value" : 16440.79,
  "symbol" : "BANSANDER-B"
}, {
  "date" : "2006-06-05",
  "value" : 16506.99,
  "symbol" : "BANSANDER-B"
}, {
  "date" : "2006-06-06",
  "value" : 16586.96,
  "symbol" : "BANSANDER-B"
}, {
  "date" : "2006-06-07",
  "value" : 16519.48,
  "symbol" : "BANSANDER-B"
}, {
  "date" : "2006-06-08",
  "value" : 16383.41,
  "symbol" : "BANSANDER-B"
}, {
  "date" : "2006-06-09",
  "value" : 16228.09,
  "symbol" : "BANSANDER-B"
}, {
  "date" : "2006-06-10",
  "value" : 16228.09,
  "symbol" : "BANSANDER-B"
}, {
  "date" : "2006-06-11",
  "value" : 16228.09,
  "symbol" : "BANSANDER-B"
}, {
  "date" : "2006-06-12",
  "value" : 16228.09,
  "symbol" : "BANSANDER-B"
}, {
  "date" : "2006-06-13",
  "value" : 16092.65,
  "symbol" : "BANSANDER-B"
}, {
  "date" : "2006-06-14",
  "value" : 15935.96,
  "symbol" : "BANSANDER-B"
}, {
  "date" : "2006-06-15",
  "value" : 15698.09,
  "symbol" : "BANSANDER-B"
}, {
  "date" : "2006-06-16",
  "value" : 15750.98,
  "symbol" : "BANSANDER-B"
}, {
  "date" : "2006-06-17",
  "value" : 15750.98,
  "symbol" : "BANSANDER-B"
}, {
  "date" : "2006-06-18",
  "value" : 15750.98,
  "symbol" : "BANSANDER-B"
}, {
  "date" : "2006-06-19",
  "value" : 15982.39,
  "symbol" : "BANSANDER-B"
}, {
  "date" : "2006-06-20",
  "value" : 16043.00,
  "symbol" : "BANSANDER-B"
}, {
  "date" : "2006-06-21",
  "value" : 16025.30,
  "symbol" : "BANSANDER-B"
}, {
  "date" : "2006-06-22",
  "value" : 16021.69,
  "symbol" : "BANSANDER-B"
}, {
  "date" : "2006-06-23",
  "value" : 16084.72,
  "symbol" : "BANSANDER-B"
}, {
  "date" : "2006-06-24",
  "value" : 16084.72,
  "symbol" : "BANSANDER-B"
}, {
  "date" : "2006-06-25",
  "value" : 16084.72,
  "symbol" : "BANSANDER-B"
}, {
  "date" : "2006-06-26",
  "value" : 16084.72,
  "symbol" : "BANSANDER-B"
}, {
  "date" : "2006-06-27",
  "value" : 16113.42,
  "symbol" : "BANSANDER-B"
}, {
  "date" : "2006-06-28",
  "value" : 16138.01,
  "symbol" : "BANSANDER-B"
}, {
  "date" : "2006-06-29",
  "value" : 16120.54,
  "symbol" : "BANSANDER-B"
}, {
  "date" : "2006-06-30",
  "value" : 16189.02,
  "symbol" : "BANSANDER-B"
}, {
  "date" : "2006-07-01",
  "value" : 16189.02,
  "symbol" : "BANSANDER-B"
}, {
  "date" : "2006-07-02",
  "value" : 16189.02,
  "symbol" : "BANSANDER-B"
}, {
  "date" : "2006-07-03",
  "value" : 16375.45,
  "symbol" : "BANSANDER-B"
}, {
  "date" : "2006-07-04",
  "value" : 16465.47,
  "symbol" : "BANSANDER-B"
}, {
  "date" : "2006-07-05",
  "value" : 16562.45,
  "symbol" : "BANSANDER-B"
}, {
  "date" : "2006-07-06",
  "value" : 16572.24,
  "symbol" : "BANSANDER-B"
}, {
  "date" : "2006-07-07",
  "value" : 16486.74,
  "symbol" : "BANSANDER-B"
}, {
  "date" : "2006-07-08",
  "value" : 16486.74,
  "symbol" : "BANSANDER-B"
}, {
  "date" : "2006-07-09",
  "value" : 16486.74,
  "symbol" : "BANSANDER-B"
}, {
  "date" : "2006-07-10",
  "value" : 16510.82,
  "symbol" : "BANSANDER-B"
}, {
  "date" : "2006-07-11",
  "value" : 16504.36,
  "symbol" : "BANSANDER-B"
}, {
  "date" : "2006-07-12",
  "value" : 16517.12,
  "symbol" : "BANSANDER-B"
}, {
  "date" : "2006-07-13",
  "value" : 16496.93,
  "symbol" : "BANSANDER-B"
}, {
  "date" : "2006-07-14",
  "value" : 16456.71,
  "symbol" : "BANSANDER-B"
}, {
  "date" : "2006-07-15",
  "value" : 16456.71,
  "symbol" : "BANSANDER-B"
}, {
  "date" : "2006-07-16",
  "value" : 16456.71,
  "symbol" : "BANSANDER-B"
}, {
  "date" : "2006-07-17",
  "value" : 16328.71,
  "symbol" : "BANSANDER-B"
}, {
  "date" : "2006-07-18",
  "value" : 16242.11,
  "symbol" : "BANSANDER-B"
}, {
  "date" : "2006-07-19",
  "value" : 16163.62,
  "symbol" : "BANSANDER-B"
}, {
  "date" : "2006-07-20",
  "value" : 16175.05,
  "symbol" : "BANSANDER-B"
}, {
  "date" : "2006-07-21",
  "value" : 16277.97,
  "symbol" : "BANSANDER-B"
}, {
  "date" : "2006-07-22",
  "value" : 16277.97,
  "symbol" : "BANSANDER-B"
}, {
  "date" : "2006-07-23",
  "value" : 16277.97,
  "symbol" : "BANSANDER-B"
}, {
  "date" : "2006-07-24",
  "value" : 16350.64,
  "symbol" : "BANSANDER-B"
}, {
  "date" : "2006-07-25",
  "value" : 16308.17,
  "symbol" : "BANSANDER-B"
}, {
  "date" : "2006-07-26",
  "value" : 16381.85,
  "symbol" : "BANSANDER-B"
}, {
  "date" : "2006-07-27",
  "value" : 16464.89,
  "symbol" : "BANSANDER-B"
}, {
  "date" : "2006-07-28",
  "value" : 16510.30,
  "symbol" : "BANSANDER-B"
}, {
  "date" : "2006-07-29",
  "value" : 16510.30,
  "symbol" : "BANSANDER-B"
}, {
  "date" : "2006-07-30",
  "value" : 16510.30,
  "symbol" : "BANSANDER-B"
}, {
  "date" : "2006-07-31",
  "value" : 16589.63,
  "symbol" : "BANSANDER-B"
}, {
  "date" : "2006-08-01",
  "value" : 16645.35,
  "symbol" : "BANSANDER-B"
}, {
  "date" : "2006-08-02",
  "value" : 16659.20,
  "symbol" : "BANSANDER-B"
}, {
  "date" : "2006-08-03",
  "value" : 16616.19,
  "symbol" : "BANSANDER-B"
}, {
  "date" : "2006-08-04",
  "value" : 16671.42,
  "symbol" : "BANSANDER-B"
}, {
  "date" : "2006-08-05",
  "value" : 16671.42,
  "symbol" : "BANSANDER-B"
}, {
  "date" : "2006-08-06",
  "value" : 16671.42,
  "symbol" : "BANSANDER-B"
}, {
  "date" : "2006-08-07",
  "value" : 16706.30,
  "symbol" : "BANSANDER-B"
}, {
  "date" : "2006-08-08",
  "value" : 16742.20,
  "symbol" : "BANSANDER-B"
}, {
  "date" : "2006-08-09",
  "value" : 16738.19,
  "symbol" : "BANSANDER-B"
}, {
  "date" : "2006-08-10",
  "value" : 16758.99,
  "symbol" : "BANSANDER-B"
}, {
  "date" : "2006-08-11",
  "value" : 16776.01,
  "symbol" : "BANSANDER-B"
}, {
  "date" : "2006-08-12",
  "value" : 16776.01,
  "symbol" : "BANSANDER-B"
}, {
  "date" : "2006-08-13",
  "value" : 16776.01,
  "symbol" : "BANSANDER-B"
}, {
  "date" : "2006-08-14",
  "value" : 16739.58,
  "symbol" : "BANSANDER-B"
}, {
  "date" : "2006-08-15",
  "value" : 16739.58,
  "symbol" : "BANSANDER-B"
}, {
  "date" : "2006-08-16",
  "value" : 16729.39,
  "symbol" : "BANSANDER-B"
}, {
  "date" : "2006-08-17",
  "value" : 16823.00,
  "symbol" : "BANSANDER-B"
}, {
  "date" : "2006-08-18",
  "value" : 16848.15,
  "symbol" : "BANSANDER-B"
}, {
  "date" : "2006-08-19",
  "value" : 16848.15,
  "symbol" : "BANSANDER-B"
}, {
  "date" : "2006-08-20",
  "value" : 16848.15,
  "symbol" : "BANSANDER-B"
}, {
  "date" : "2006-08-21",
  "value" : 16870.98,
  "symbol" : "BANSANDER-B"
}, {
  "date" : "2006-08-22",
  "value" : 16840.38,
  "symbol" : "BANSANDER-B"
}, {
  "date" : "2006-08-23",
  "value" : 16821.56,
  "symbol" : "BANSANDER-B"
}, {
  "date" : "2006-08-24",
  "value" : 16840.69,
  "symbol" : "BANSANDER-B"
}, {
  "date" : "2006-08-25",
  "value" : 16793.21,
  "symbol" : "BANSANDER-B"
}, {
  "date" : "2006-08-26",
  "value" : 16793.21,
  "symbol" : "BANSANDER-B"
}, {
  "date" : "2006-08-27",
  "value" : 16793.21,
  "symbol" : "BANSANDER-B"
}, {
  "date" : "2006-08-28",
  "value" : 16786.51,
  "symbol" : "BANSANDER-B"
}, {
  "date" : "2006-08-29",
  "value" : 16796.72,
  "symbol" : "BANSANDER-B"
}, {
  "date" : "2006-08-30",
  "value" : 16839.43,
  "symbol" : "BANSANDER-B"
}, {
  "date" : "2006-08-31",
  "value" : 16896.52,
  "symbol" : "BANSANDER-B"
}, {
  "date" : "2006-09-01",
  "value" : 16938.99,
  "symbol" : "BANSANDER-B"
}, {
  "date" : "2006-09-02",
  "value" : 16938.99,
  "symbol" : "BANSANDER-B"
}, {
  "date" : "2006-09-03",
  "value" : 16938.99,
  "symbol" : "BANSANDER-B"
}, {
  "date" : "2006-09-04",
  "value" : 16982.03,
  "symbol" : "BANSANDER-B"
}, {
  "date" : "2006-09-05",
  "value" : 17034.88,
  "symbol" : "BANSANDER-B"
}, {
  "date" : "2006-09-06",
  "value" : 17061.09,
  "symbol" : "BANSANDER-B"
}, {
  "date" : "2006-09-07",
  "value" : 17066.45,
  "symbol" : "BANSANDER-B"
}, {
  "date" : "2006-09-08",
  "value" : 16972.10,
  "symbol" : "BANSANDER-B"
}, {
  "date" : "2006-09-09",
  "value" : 16972.10,
  "symbol" : "BANSANDER-B"
}, {
  "date" : "2006-09-10",
  "value" : 16972.10,
  "symbol" : "BANSANDER-B"
}, {
  "date" : "2006-09-11",
  "value" : 16933.67,
  "symbol" : "BANSANDER-B"
}, {
  "date" : "2006-09-12",
  "value" : 16921.50,
  "symbol" : "BANSANDER-B"
}, {
  "date" : "2006-09-13",
  "value" : 16837.40,
  "symbol" : "BANSANDER-B"
}, {
  "date" : "2006-09-14",
  "value" : 16875.63,
  "symbol" : "BANSANDER-B"
}, {
  "date" : "2006-09-15",
  "value" : 16960.96,
  "symbol" : "BANSANDER-B"
}, {
  "date" : "2006-09-16",
  "value" : 16960.96,
  "symbol" : "BANSANDER-B"
}, {
  "date" : "2006-09-17",
  "value" : 16960.96,
  "symbol" : "BANSANDER-B"
}, {
  "date" : "2006-09-18",
  "value" : 16960.96,
  "symbol" : "BANSANDER-B"
}, {
  "date" : "2006-09-19",
  "value" : 16960.96,
  "symbol" : "BANSANDER-B"
}, {
  "date" : "2006-09-20",
  "value" : 16969.14,
  "symbol" : "BANSANDER-B"
}, {
  "date" : "2006-09-21",
  "value" : 17005.41,
  "symbol" : "BANSANDER-B"
}, {
  "date" : "2006-09-22",
  "value" : 17044.98,
  "symbol" : "BANSANDER-B"
}, {
  "date" : "2006-09-23",
  "value" : 17044.98,
  "symbol" : "BANSANDER-B"
}, {
  "date" : "2006-09-24",
  "value" : 17044.98,
  "symbol" : "BANSANDER-B"
}, {
  "date" : "2006-09-25",
  "value" : 17004.21,
  "symbol" : "BANSANDER-B"
}, {
  "date" : "2006-09-26",
  "value" : 16944.62,
  "symbol" : "BANSANDER-B"
}, {
  "date" : "2006-09-27",
  "value" : 16969.93,
  "symbol" : "BANSANDER-B"
}, {
  "date" : "2006-09-28",
  "value" : 17078.23,
  "symbol" : "BANSANDER-B"
}, {
  "date" : "2006-09-29",
  "value" : 17118.11,
  "symbol" : "BANSANDER-B"
}, {
  "date" : "2006-09-30",
  "value" : 17118.11,
  "symbol" : "BANSANDER-B"
}, {
  "date" : "2006-10-01",
  "value" : 17118.11,
  "symbol" : "BANSANDER-B"
}, {
  "date" : "2006-10-02",
  "value" : 17141.32,
  "symbol" : "BANSANDER-B"
}, {
  "date" : "2006-10-03",
  "value" : 17147.88,
  "symbol" : "BANSANDER-B"
}, {
  "date" : "2006-10-04",
  "value" : 17139.30,
  "symbol" : "BANSANDER-B"
}, {
  "date" : "2006-10-05",
  "value" : 17141.27,
  "symbol" : "BANSANDER-B"
}, {
  "date" : "2006-10-06",
  "value" : 17235.09,
  "symbol" : "BANSANDER-B"
}, {
  "date" : "2006-10-07",
  "value" : 17235.09,
  "symbol" : "BANSANDER-B"
}, {
  "date" : "2006-10-08",
  "value" : 17235.09,
  "symbol" : "BANSANDER-B"
}, {
  "date" : "2006-10-09",
  "value" : 17235.09,
  "symbol" : "BANSANDER-B"
}, {
  "date" : "2006-10-10",
  "value" : 17284.53,
  "symbol" : "BANSANDER-B"
}, {
  "date" : "2006-10-11",
  "value" : 17279.88,
  "symbol" : "BANSANDER-B"
}, {
  "date" : "2006-10-12",
  "value" : 17318.99,
  "symbol" : "BANSANDER-B"
}, {
  "date" : "2006-10-13",
  "value" : 17328.15,
  "symbol" : "BANSANDER-B"
}, {
  "date" : "2006-10-14",
  "value" : 17328.15,
  "symbol" : "BANSANDER-B"
}, {
  "date" : "2006-10-15",
  "value" : 17328.15,
  "symbol" : "BANSANDER-B"
}, {
  "date" : "2006-10-16",
  "value" : 17375.76,
  "symbol" : "BANSANDER-B"
}, {
  "date" : "2006-10-17",
  "value" : 17421.99,
  "symbol" : "BANSANDER-B"
}, {
  "date" : "2006-10-18",
  "value" : 17440.50,
  "symbol" : "BANSANDER-B"
}, {
  "date" : "2006-10-19",
  "value" : 17412.54,
  "symbol" : "BANSANDER-B"
}, {
  "date" : "2006-10-20",
  "value" : 17460.12,
  "symbol" : "BANSANDER-B"
}, {
  "date" : "2006-10-21",
  "value" : 17460.12,
  "symbol" : "BANSANDER-B"
}, {
  "date" : "2006-10-22",
  "value" : 17460.12,
  "symbol" : "BANSANDER-B"
}, {
  "date" : "2006-10-23",
  "value" : 17457.45,
  "symbol" : "BANSANDER-B"
}, {
  "date" : "2006-10-24",
  "value" : 17455.16,
  "symbol" : "BANSANDER-B"
}, {
  "date" : "2006-10-25",
  "value" : 17488.41,
  "symbol" : "BANSANDER-B"
}, {
  "date" : "2006-10-26",
  "value" : 17529.75,
  "symbol" : "BANSANDER-B"
}, {
  "date" : "2006-10-27",
  "value" : 17584.69,
  "symbol" : "BANSANDER-B"
}, {
  "date" : "2006-10-28",
  "value" : 17584.69,
  "symbol" : "BANSANDER-B"
}, {
  "date" : "2006-10-29",
  "value" : 17584.69,
  "symbol" : "BANSANDER-B"
}, {
  "date" : "2006-10-30",
  "value" : 17621.97,
  "symbol" : "BANSANDER-B"
}, {
  "date" : "2006-10-31",
  "value" : 17611.49,
  "symbol" : "BANSANDER-B"
}, {
  "date" : "2006-11-01",
  "value" : 17611.49,
  "symbol" : "BANSANDER-B"
}, {
  "date" : "2006-11-02",
  "value" : 17563.04,
  "symbol" : "BANSANDER-B"
}, {
  "date" : "2006-11-03",
  "value" : 17612.93,
  "symbol" : "BANSANDER-B"
}, {
  "date" : "2006-11-04",
  "value" : 17612.93,
  "symbol" : "BANSANDER-B"
}, {
  "date" : "2006-11-05",
  "value" : 17612.93,
  "symbol" : "BANSANDER-B"
}, {
  "date" : "2006-11-06",
  "value" : 17589.13,
  "symbol" : "BANSANDER-B"
}, {
  "date" : "2006-11-07",
  "value" : 17594.26,
  "symbol" : "BANSANDER-B"
}, {
  "date" : "2006-11-08",
  "value" : 17695.71,
  "symbol" : "BANSANDER-B"
}, {
  "date" : "2006-11-09",
  "value" : 17760.00,
  "symbol" : "BANSANDER-B"
}, {
  "date" : "2006-11-10",
  "value" : 17799.42,
  "symbol" : "BANSANDER-B"
}, {
  "date" : "2006-11-11",
  "value" : 17799.42,
  "symbol" : "BANSANDER-B"
}, {
  "date" : "2006-11-12",
  "value" : 17799.42,
  "symbol" : "BANSANDER-B"
}, {
  "date" : "2006-11-13",
  "value" : 17829.37,
  "symbol" : "BANSANDER-B"
}, {
  "date" : "2006-11-14",
  "value" : 17814.45,
  "symbol" : "BANSANDER-B"
}, {
  "date" : "2006-11-15",
  "value" : 17829.38,
  "symbol" : "BANSANDER-B"
}, {
  "date" : "2006-11-16",
  "value" : 17924.73,
  "symbol" : "BANSANDER-B"
}, {
  "date" : "2006-11-17",
  "value" : 17961.56,
  "symbol" : "BANSANDER-B"
}, {
  "date" : "2006-11-18",
  "value" : 17961.56,
  "symbol" : "BANSANDER-B"
}, {
  "date" : "2006-11-19",
  "value" : 17961.56,
  "symbol" : "BANSANDER-B"
}, {
  "date" : "2006-11-20",
  "value" : 17981.26,
  "symbol" : "BANSANDER-B"
}, {
  "date" : "2006-11-21",
  "value" : 17918.05,
  "symbol" : "BANSANDER-B"
}, {
  "date" : "2006-11-22",
  "value" : 17914.80,
  "symbol" : "BANSANDER-B"
}, {
  "date" : "2006-11-23",
  "value" : 18007.54,
  "symbol" : "BANSANDER-B"
}, {
  "date" : "2006-11-24",
  "value" : 18085.21,
  "symbol" : "BANSANDER-B"
}, {
  "date" : "2006-11-25",
  "value" : 18085.21,
  "symbol" : "BANSANDER-B"
}, {
  "date" : "2006-11-26",
  "value" : 18085.21,
  "symbol" : "BANSANDER-B"
}, {
  "date" : "2006-11-27",
  "value" : 18135.46,
  "symbol" : "BANSANDER-B"
}, {
  "date" : "2006-11-28",
  "value" : 18112.07,
  "symbol" : "BANSANDER-B"
}, {
  "date" : "2006-11-29",
  "value" : 18060.01,
  "symbol" : "BANSANDER-B"
}, {
  "date" : "2006-11-30",
  "value" : 18040.36,
  "symbol" : "BANSANDER-B"
}, {
  "date" : "2006-12-01",
  "value" : 18175.11,
  "symbol" : "BANSANDER-B"
}, {
  "date" : "2006-12-02",
  "value" : 18175.11,
  "symbol" : "BANSANDER-B"
}, {
  "date" : "2006-12-03",
  "value" : 18175.11,
  "symbol" : "BANSANDER-B"
}, {
  "date" : "2006-12-04",
  "value" : 18216.76,
  "symbol" : "BANSANDER-B"
}, {
  "date" : "2006-12-05",
  "value" : 18202.23,
  "symbol" : "BANSANDER-B"
}, {
  "date" : "2006-12-06",
  "value" : 18235.01,
  "symbol" : "BANSANDER-B"
}, {
  "date" : "2006-12-07",
  "value" : 18332.63,
  "symbol" : "BANSANDER-B"
}, {
  "date" : "2006-12-08",
  "value" : 18332.63,
  "symbol" : "BANSANDER-B"
}, {
  "date" : "2006-12-09",
  "value" : 18332.63,
  "symbol" : "BANSANDER-B"
}, {
  "date" : "2006-12-10",
  "value" : 18332.63,
  "symbol" : "BANSANDER-B"
}, {
  "date" : "2006-12-11",
  "value" : 18345.01,
  "symbol" : "BANSANDER-B"
}, {
  "date" : "2006-12-12",
  "value" : 18340.02,
  "symbol" : "BANSANDER-B"
}, {
  "date" : "2006-12-13",
  "value" : 18366.40,
  "symbol" : "BANSANDER-B"
}, {
  "date" : "2006-12-14",
  "value" : 18364.60,
  "symbol" : "BANSANDER-B"
}, {
  "date" : "2006-12-15",
  "value" : 18431.36,
  "symbol" : "BANSANDER-B"
}, {
  "date" : "2006-12-16",
  "value" : 18431.36,
  "symbol" : "BANSANDER-B"
}, {
  "date" : "2006-12-17",
  "value" : 18431.36,
  "symbol" : "BANSANDER-B"
}, {
  "date" : "2006-12-18",
  "value" : 18511.31,
  "symbol" : "BANSANDER-B"
}, {
  "date" : "2006-12-19",
  "value" : 18609.57,
  "symbol" : "BANSANDER-B"
}, {
  "date" : "2006-12-20",
  "value" : 18592.42,
  "symbol" : "BANSANDER-B"
}, {
  "date" : "2006-12-21",
  "value" : 18542.90,
  "symbol" : "BANSANDER-B"
}, {
  "date" : "2006-12-22",
  "value" : 18616.32,
  "symbol" : "BANSANDER-B"
}, {
  "date" : "2006-12-23",
  "value" : 18616.32,
  "symbol" : "BANSANDER-B"
}, {
  "date" : "2006-12-24",
  "value" : 18616.32,
  "symbol" : "BANSANDER-B"
}, {
  "date" : "2006-12-25",
  "value" : 18616.32,
  "symbol" : "BANSANDER-B"
}, {
  "date" : "2006-12-26",
  "value" : 18612.07,
  "symbol" : "BANSANDER-B"
}, {
  "date" : "2006-12-27",
  "value" : 18620.97,
  "symbol" : "BANSANDER-B"
}, {
  "date" : "2006-12-28",
  "value" : 18657.97,
  "symbol" : "BANSANDER-B"
}, {
  "date" : "2006-12-29",
  "value" : 18739.28,
  "symbol" : "BANSANDER-B"
}, {
  "date" : "2006-12-30",
  "value" : 18739.28,
  "symbol" : "BANSANDER-B"
}, {
  "date" : "2006-12-31",
  "value" : 18739.28,
  "symbol" : "BANSANDER-B"
}, {
  "date" : "2007-01-01",
  "value" : 18739.28,
  "symbol" : "BANSANDER-B"
}, {
  "date" : "2007-01-02",
  "value" : 18754.49,
  "symbol" : "BANSANDER-B"
}, {
  "date" : "2007-01-03",
  "value" : 18810.61,
  "symbol" : "BANSANDER-B"
}, {
  "date" : "2007-01-04",
  "value" : 18851.83,
  "symbol" : "BANSANDER-B"
}, {
  "date" : "2007-01-05",
  "value" : 18884.29,
  "symbol" : "BANSANDER-B"
}, {
  "date" : "2007-01-06",
  "value" : 18884.29,
  "symbol" : "BANSANDER-B"
}, {
  "date" : "2007-01-07",
  "value" : 18884.29,
  "symbol" : "BANSANDER-B"
}, {
  "date" : "2007-01-08",
  "value" : 18844.58,
  "symbol" : "BANSANDER-B"
}, {
  "date" : "2007-01-09",
  "value" : 18778.69,
  "symbol" : "BANSANDER-B"
}, {
  "date" : "2007-01-10",
  "value" : 18756.52,
  "symbol" : "BANSANDER-B"
}, {
  "date" : "2007-01-11",
  "value" : 18688.25,
  "symbol" : "BANSANDER-B"
}, {
  "date" : "2007-01-12",
  "value" : 18571.33,
  "symbol" : "BANSANDER-B"
}, {
  "date" : "2007-01-13",
  "value" : 18571.33,
  "symbol" : "BANSANDER-B"
}, {
  "date" : "2007-01-14",
  "value" : 18571.33,
  "symbol" : "BANSANDER-B"
}, {
  "date" : "2007-01-15",
  "value" : 18716.19,
  "symbol" : "BANSANDER-B"
}, {
  "date" : "2007-01-16",
  "value" : 18826.25,
  "symbol" : "BANSANDER-B"
}, {
  "date" : "2007-01-17",
  "value" : 18907.12,
  "symbol" : "BANSANDER-B"
}, {
  "date" : "2007-01-18",
  "value" : 18910.88,
  "symbol" : "BANSANDER-B"
}, {
  "date" : "2007-01-19",
  "value" : 18919.19,
  "symbol" : "BANSANDER-B"
}, {
  "date" : "2007-01-20",
  "value" : 18919.19,
  "symbol" : "BANSANDER-B"
}, {
  "date" : "2007-01-21",
  "value" : 18919.19,
  "symbol" : "BANSANDER-B"
}, {
  "date" : "2007-01-22",
  "value" : 18970.22,
  "symbol" : "BANSANDER-B"
}, {
  "date" : "2007-01-23",
  "value" : 18998.84,
  "symbol" : "BANSANDER-B"
}, {
  "date" : "2007-01-24",
  "value" : 19066.36,
  "symbol" : "BANSANDER-B"
}, {
  "date" : "2007-01-25",
  "value" : 19116.33,
  "symbol" : "BANSANDER-B"
}, {
  "date" : "2007-01-26",
  "value" : 19214.21,
  "symbol" : "BANSANDER-B"
}, {
  "date" : "2007-01-27",
  "value" : 19214.21,
  "symbol" : "BANSANDER-B"
}, {
  "date" : "2007-01-28",
  "value" : 19214.21,
  "symbol" : "BANSANDER-B"
}, {
  "date" : "2007-01-29",
  "value" : 19139.88,
  "symbol" : "BANSANDER-B"
}, {
  "date" : "2007-01-30",
  "value" : 19092.48,
  "symbol" : "BANSANDER-B"
}, {
  "date" : "2007-01-31",
  "value" : 19062.55,
  "symbol" : "BANSANDER-B"
}, {
  "date" : "2007-02-01",
  "value" : 19106.30,
  "symbol" : "BANSANDER-B"
}, {
  "date" : "2007-02-02",
  "value" : 19191.92,
  "symbol" : "BANSANDER-B"
}, {
  "date" : "2007-02-03",
  "value" : 19191.92,
  "symbol" : "BANSANDER-B"
}, {
  "date" : "2007-02-04",
  "value" : 19191.92,
  "symbol" : "BANSANDER-B"
}, {
  "date" : "2007-02-05",
  "value" : 19365.47,
  "symbol" : "BANSANDER-B"
}, {
  "date" : "2007-02-06",
  "value" : 19408.05,
  "symbol" : "BANSANDER-B"
}, {
  "date" : "2007-02-07",
  "value" : 19441.08,
  "symbol" : "BANSANDER-B"
}, {
  "date" : "2007-02-08",
  "value" : 19532.02,
  "symbol" : "BANSANDER-B"
}, {
  "date" : "2007-02-09",
  "value" : 19572.10,
  "symbol" : "BANSANDER-B"
}, {
  "date" : "2007-02-10",
  "value" : 19572.10,
  "symbol" : "BANSANDER-B"
}, {
  "date" : "2007-02-11",
  "value" : 19572.10,
  "symbol" : "BANSANDER-B"
}, {
  "date" : "2007-02-12",
  "value" : 19553.83,
  "symbol" : "BANSANDER-B"
}, {
  "date" : "2007-02-13",
  "value" : 19578.88,
  "symbol" : "BANSANDER-B"
}, {
  "date" : "2007-02-14",
  "value" : 19521.41,
  "symbol" : "BANSANDER-B"
}, {
  "date" : "2007-02-15",
  "value" : 19595.41,
  "symbol" : "BANSANDER-B"
}, {
  "date" : "2007-02-16",
  "value" : 19723.79,
  "symbol" : "BANSANDER-B"
}, {
  "date" : "2007-02-17",
  "value" : 19723.79,
  "symbol" : "BANSANDER-B"
}, {
  "date" : "2007-02-18",
  "value" : 19723.79,
  "symbol" : "BANSANDER-B"
}, {
  "date" : "2007-02-19",
  "value" : 19755.60,
  "symbol" : "BANSANDER-B"
}, {
  "date" : "2007-02-20",
  "value" : 19762.19,
  "symbol" : "BANSANDER-B"
}, {
  "date" : "2007-02-21",
  "value" : 19699.02,
  "symbol" : "BANSANDER-B"
}, {
  "date" : "2007-02-22",
  "value" : 19581.52,
  "symbol" : "BANSANDER-B"
}, {
  "date" : "2007-02-23",
  "value" : 19538.59,
  "symbol" : "BANSANDER-B"
}, {
  "date" : "2007-02-24",
  "value" : 19538.59,
  "symbol" : "BANSANDER-B"
}, {
  "date" : "2007-02-25",
  "value" : 19538.59,
  "symbol" : "BANSANDER-B"
}, {
  "date" : "2007-02-26",
  "value" : 19621.44,
  "symbol" : "BANSANDER-B"
}, {
  "date" : "2007-02-27",
  "value" : 19521.07,
  "symbol" : "BANSANDER-B"
}, {
  "date" : "2007-02-28",
  "value" : 19432.89,
  "symbol" : "BANSANDER-B"
}, {
  "date" : "2007-03-01",
  "value" : 19171.71,
  "symbol" : "BANSANDER-B"
}, {
  "date" : "2007-03-02",
  "value" : 19058.42,
  "symbol" : "BANSANDER-B"
}, {
  "date" : "2007-03-03",
  "value" : 19058.42,
  "symbol" : "BANSANDER-B"
}, {
  "date" : "2007-03-04",
  "value" : 19058.42,
  "symbol" : "BANSANDER-B"
}, {
  "date" : "2007-03-05",
  "value" : 19033.71,
  "symbol" : "BANSANDER-B"
}, {
  "date" : "2007-03-06",
  "value" : 18959.80,
  "symbol" : "BANSANDER-B"
}, {
  "date" : "2007-03-07",
  "value" : 18774.61,
  "symbol" : "BANSANDER-B"
}, {
  "date" : "2007-03-08",
  "value" : 18955.10,
  "symbol" : "BANSANDER-B"
}, {
  "date" : "2007-03-09",
  "value" : 19008.46,
  "symbol" : "BANSANDER-B"
}, {
  "date" : "2007-03-10",
  "value" : 19008.46,
  "symbol" : "BANSANDER-B"
}, {
  "date" : "2007-03-11",
  "value" : 19008.46,
  "symbol" : "BANSANDER-B"
}, {
  "date" : "2007-03-12",
  "value" : 19152.96,
  "symbol" : "BANSANDER-B"
}, {
  "date" : "2007-03-13",
  "value" : 19229.75,
  "symbol" : "BANSANDER-B"
}, {
  "date" : "2007-03-14",
  "value" : 19275.27,
  "symbol" : "BANSANDER-B"
}, {
  "date" : "2007-03-15",
  "value" : 19111.05,
  "symbol" : "BANSANDER-B"
}, {
  "date" : "2007-03-16",
  "value" : 19059.42,
  "symbol" : "BANSANDER-B"
}, {
  "date" : "2007-03-17",
  "value" : 19059.42,
  "symbol" : "BANSANDER-B"
}, {
  "date" : "2007-03-18",
  "value" : 19059.42,
  "symbol" : "BANSANDER-B"
}, {
  "date" : "2007-03-19",
  "value" : 19168.93,
  "symbol" : "BANSANDER-B"
}, {
  "date" : "2007-03-20",
  "value" : 19200.72,
  "symbol" : "BANSANDER-B"
}, {
  "date" : "2007-03-21",
  "value" : 19309.63,
  "symbol" : "BANSANDER-B"
}, {
  "date" : "2007-03-22",
  "value" : 19364.51,
  "symbol" : "BANSANDER-B"
}, {
  "date" : "2007-03-23",
  "value" : 19471.69,
  "symbol" : "BANSANDER-B"
}, {
  "date" : "2007-03-24",
  "value" : 19471.69,
  "symbol" : "BANSANDER-B"
}, {
  "date" : "2007-03-25",
  "value" : 19471.69,
  "symbol" : "BANSANDER-B"
}, {
  "date" : "2007-03-26",
  "value" : 19545.58,
  "symbol" : "BANSANDER-B"
}, {
  "date" : "2007-03-27",
  "value" : 19541.16,
  "symbol" : "BANSANDER-B"
}, {
  "date" : "2007-03-28",
  "value" : 19529.19,
  "symbol" : "BANSANDER-B"
}, {
  "date" : "2007-03-29",
  "value" : 19469.76,
  "symbol" : "BANSANDER-B"
}, {
  "date" : "2007-03-30",
  "value" : 19440.14,
  "symbol" : "BANSANDER-B"
}, {
  "date" : "2007-03-31",
  "value" : 19440.14,
  "symbol" : "BANSANDER-B"
}, {
  "date" : "2007-04-01",
  "value" : 19440.14,
  "symbol" : "BANSANDER-B"
}, {
  "date" : "2007-04-02",
  "value" : 19518.62,
  "symbol" : "BANSANDER-B"
}, {
  "date" : "2007-04-03",
  "value" : 19546.95,
  "symbol" : "BANSANDER-B"
}, {
  "date" : "2007-04-04",
  "value" : 19596.36,
  "symbol" : "BANSANDER-B"
}, {
  "date" : "2007-04-05",
  "value" : 19721.93,
  "symbol" : "BANSANDER-B"
}, {
  "date" : "2007-04-06",
  "value" : 19721.93,
  "symbol" : "BANSANDER-B"
}, {
  "date" : "2007-04-07",
  "value" : 19721.93,
  "symbol" : "BANSANDER-B"
}, {
  "date" : "2007-04-08",
  "value" : 19721.93,
  "symbol" : "BANSANDER-B"
}, {
  "date" : "2007-04-09",
  "value" : 19797.25,
  "symbol" : "BANSANDER-B"
}, {
  "date" : "2007-04-10",
  "value" : 19811.72,
  "symbol" : "BANSANDER-B"
}, {
  "date" : "2007-04-11",
  "value" : 19897.72,
  "symbol" : "BANSANDER-B"
}, {
  "date" : "2007-04-12",
  "value" : 19937.20,
  "symbol" : "BANSANDER-B"
}, {
  "date" : "2007-04-13",
  "value" : 19906.84,
  "symbol" : "BANSANDER-B"
}, {
  "date" : "2007-04-14",
  "value" : 19906.84,
  "symbol" : "BANSANDER-B"
}, {
  "date" : "2007-04-15",
  "value" : 19906.84,
  "symbol" : "BANSANDER-B"
}, {
  "date" : "2007-04-16",
  "value" : 19953.29,
  "symbol" : "BANSANDER-B"
}, {
  "date" : "2007-04-17",
  "value" : 20046.98,
  "symbol" : "BANSANDER-B"
}, {
  "date" : "2007-04-18",
  "value" : 20106.29,
  "symbol" : "BANSANDER-B"
}, {
  "date" : "2007-04-19",
  "value" : 20085.96,
  "symbol" : "BANSANDER-B"
}, {
  "date" : "2007-04-20",
  "value" : 20090.62,
  "symbol" : "BANSANDER-B"
}, {
  "date" : "2007-04-21",
  "value" : 20090.62,
  "symbol" : "BANSANDER-B"
}, {
  "date" : "2007-04-22",
  "value" : 20090.62,
  "symbol" : "BANSANDER-B"
}, {
  "date" : "2007-04-23",
  "value" : 20158.34,
  "symbol" : "BANSANDER-B"
}, {
  "date" : "2007-04-24",
  "value" : 20236.46,
  "symbol" : "BANSANDER-B"
}, {
  "date" : "2007-04-25",
  "value" : 20182.48,
  "symbol" : "BANSANDER-B"
}, {
  "date" : "2007-04-26",
  "value" : 20186.98,
  "symbol" : "BANSANDER-B"
}, {
  "date" : "2007-04-27",
  "value" : 20243.87,
  "symbol" : "BANSANDER-B"
}, {
  "date" : "2007-04-28",
  "value" : 20243.87,
  "symbol" : "BANSANDER-B"
}, {
  "date" : "2007-04-29",
  "value" : 20243.87,
  "symbol" : "BANSANDER-B"
}, {
  "date" : "2007-04-30",
  "value" : 20232.62,
  "symbol" : "BANSANDER-B"
}, {
  "date" : "2007-05-01",
  "value" : 20232.62,
  "symbol" : "BANSANDER-B"
}, {
  "date" : "2007-05-02",
  "value" : 20226.53,
  "symbol" : "BANSANDER-B"
}, {
  "date" : "2007-05-03",
  "value" : 20214.87,
  "symbol" : "BANSANDER-B"
}, {
  "date" : "2007-05-04",
  "value" : 20270.90,
  "symbol" : "BANSANDER-B"
}, {
  "date" : "2007-05-05",
  "value" : 20270.90,
  "symbol" : "BANSANDER-B"
}, {
  "date" : "2007-05-06",
  "value" : 20270.90,
  "symbol" : "BANSANDER-B"
}, {
  "date" : "2007-05-07",
  "value" : 20342.73,
  "symbol" : "BANSANDER-B"
}, {
  "date" : "2007-05-08",
  "value" : 20389.33,
  "symbol" : "BANSANDER-B"
}, {
  "date" : "2007-05-09",
  "value" : 20395.56,
  "symbol" : "BANSANDER-B"
}, {
  "date" : "2007-05-10",
  "value" : 20361.83,
  "symbol" : "BANSANDER-B"
}, {
  "date" : "2007-05-11",
  "value" : 20407.20,
  "symbol" : "BANSANDER-B"
}, {
  "date" : "2007-05-12",
  "value" : 20407.20,
  "symbol" : "BANSANDER-B"
}, {
  "date" : "2007-05-13",
  "value" : 20407.20,
  "symbol" : "BANSANDER-B"
}, {
  "date" : "2007-05-14",
  "value" : 20357.97,
  "symbol" : "BANSANDER-B"
}, {
  "date" : "2007-05-15",
  "value" : 20400.88,
  "symbol" : "BANSANDER-B"
}, {
  "date" : "2007-05-16",
  "value" : 20333.69,
  "symbol" : "BANSANDER-B"
}, {
  "date" : "2007-05-17",
  "value" : 20304.85,
  "symbol" : "BANSANDER-B"
}, {
  "date" : "2007-05-18",
  "value" : 20371.62,
  "symbol" : "BANSANDER-B"
}, {
  "date" : "2007-05-19",
  "value" : 20371.62,
  "symbol" : "BANSANDER-B"
}, {
  "date" : "2007-05-20",
  "value" : 20371.62,
  "symbol" : "BANSANDER-B"
}, {
  "date" : "2007-05-21",
  "value" : 20371.62,
  "symbol" : "BANSANDER-B"
}, {
  "date" : "2007-05-22",
  "value" : 20433.40,
  "symbol" : "BANSANDER-B"
}, {
  "date" : "2007-05-23",
  "value" : 20464.81,
  "symbol" : "BANSANDER-B"
}, {
  "date" : "2007-05-24",
  "value" : 20404.29,
  "symbol" : "BANSANDER-B"
}, {
  "date" : "2007-05-25",
  "value" : 20441.37,
  "symbol" : "BANSANDER-B"
}, {
  "date" : "2007-05-26",
  "value" : 20441.37,
  "symbol" : "BANSANDER-B"
}, {
  "date" : "2007-05-27",
  "value" : 20441.37,
  "symbol" : "BANSANDER-B"
}, {
  "date" : "2007-05-28",
  "value" : 20362.15,
  "symbol" : "BANSANDER-B"
}, {
  "date" : "2007-05-29",
  "value" : 20440.98,
  "symbol" : "BANSANDER-B"
}, {
  "date" : "2007-05-30",
  "value" : 20536.08,
  "symbol" : "BANSANDER-B"
}, {
  "date" : "2007-05-31",
  "value" : 20497.96,
  "symbol" : "BANSANDER-B"
}, {
  "date" : "2007-06-01",
  "value" : 20594.25,
  "symbol" : "BANSANDER-B"
}, {
  "date" : "2007-06-02",
  "value" : 20594.25,
  "symbol" : "BANSANDER-B"
}, {
  "date" : "2007-06-03",
  "value" : 20594.25,
  "symbol" : "BANSANDER-B"
}, {
  "date" : "2007-06-04",
  "value" : 20694.81,
  "symbol" : "BANSANDER-B"
}, {
  "date" : "2007-06-05",
  "value" : 20811.40,
  "symbol" : "BANSANDER-B"
}, {
  "date" : "2007-06-06",
  "value" : 20830.98,
  "symbol" : "BANSANDER-B"
}, {
  "date" : "2007-06-07",
  "value" : 20795.58,
  "symbol" : "BANSANDER-B"
}, {
  "date" : "2007-06-08",
  "value" : 20700.79,
  "symbol" : "BANSANDER-B"
}, {
  "date" : "2007-06-09",
  "value" : 20700.79,
  "symbol" : "BANSANDER-B"
}, {
  "date" : "2007-06-10",
  "value" : 20700.79,
  "symbol" : "BANSANDER-B"
}, {
  "date" : "2007-06-11",
  "value" : 20550.53,
  "symbol" : "BANSANDER-B"
}, {
  "date" : "2007-06-12",
  "value" : 20628.68,
  "symbol" : "BANSANDER-B"
}, {
  "date" : "2007-06-13",
  "value" : 20684.37,
  "symbol" : "BANSANDER-B"
}, {
  "date" : "2007-06-14",
  "value" : 20673.27,
  "symbol" : "BANSANDER-B"
}, {
  "date" : "2007-06-15",
  "value" : 20761.11,
  "symbol" : "BANSANDER-B"
}, {
  "date" : "2007-06-16",
  "value" : 20761.11,
  "symbol" : "BANSANDER-B"
}, {
  "date" : "2007-06-17",
  "value" : 20761.11,
  "symbol" : "BANSANDER-B"
}, {
  "date" : "2007-06-18",
  "value" : 20916.39,
  "symbol" : "BANSANDER-B"
}, {
  "date" : "2007-06-19",
  "value" : 21021.92,
  "symbol" : "BANSANDER-B"
}, {
  "date" : "2007-06-20",
  "value" : 21035.46,
  "symbol" : "BANSANDER-B"
}, {
  "date" : "2007-06-21",
  "value" : 21107.08,
  "symbol" : "BANSANDER-B"
}, {
  "date" : "2007-06-22",
  "value" : 21055.96,
  "symbol" : "BANSANDER-B"
}, {
  "date" : "2007-06-23",
  "value" : 21055.96,
  "symbol" : "BANSANDER-B"
}, {
  "date" : "2007-06-24",
  "value" : 21055.96,
  "symbol" : "BANSANDER-B"
}, {
  "date" : "2007-06-25",
  "value" : 21111.03,
  "symbol" : "BANSANDER-B"
}, {
  "date" : "2007-06-26",
  "value" : 21112.95,
  "symbol" : "BANSANDER-B"
}, {
  "date" : "2007-06-27",
  "value" : 21082.29,
  "symbol" : "BANSANDER-B"
}, {
  "date" : "2007-06-28",
  "value" : 21026.35,
  "symbol" : "BANSANDER-B"
}, {
  "date" : "2007-06-29",
  "value" : 21037.15,
  "symbol" : "BANSANDER-B"
}, {
  "date" : "2007-06-30",
  "value" : 21037.15,
  "symbol" : "BANSANDER-B"
}, {
  "date" : "2007-07-01",
  "value" : 21037.15,
  "symbol" : "BANSANDER-B"
}, {
  "date" : "2007-07-02",
  "value" : 21037.15,
  "symbol" : "BANSANDER-B"
}, {
  "date" : "2007-07-03",
  "value" : 21169.85,
  "symbol" : "BANSANDER-B"
}, {
  "date" : "2007-07-04",
  "value" : 21334.19,
  "symbol" : "BANSANDER-B"
}, {
  "date" : "2007-07-05",
  "value" : 21378.52,
  "symbol" : "BANSANDER-B"
}, {
  "date" : "2007-07-06",
  "value" : 21384.07,
  "symbol" : "BANSANDER-B"
}, {
  "date" : "2007-07-07",
  "value" : 21384.07,
  "symbol" : "BANSANDER-B"
}, {
  "date" : "2007-07-08",
  "value" : 21384.07,
  "symbol" : "BANSANDER-B"
}, {
  "date" : "2007-07-09",
  "value" : 21373.15,
  "symbol" : "BANSANDER-B"
}, {
  "date" : "2007-07-10",
  "value" : 21401.02,
  "symbol" : "BANSANDER-B"
}, {
  "date" : "2007-07-11",
  "value" : 21455.20,
  "symbol" : "BANSANDER-B"
}, {
  "date" : "2007-07-12",
  "value" : 21391.47,
  "symbol" : "BANSANDER-B"
}, {
  "date" : "2007-07-13",
  "value" : 21372.39,
  "symbol" : "BANSANDER-B"
}, {
  "date" : "2007-07-14",
  "value" : 21372.39,
  "symbol" : "BANSANDER-B"
}, {
  "date" : "2007-07-15",
  "value" : 21372.39,
  "symbol" : "BANSANDER-B"
}, {
  "date" : "2007-07-16",
  "value" : 21372.39,
  "symbol" : "BANSANDER-B"
}, {
  "date" : "2007-07-17",
  "value" : 21463.83,
  "symbol" : "BANSANDER-B"
}, {
  "date" : "2007-07-18",
  "value" : 21527.22,
  "symbol" : "BANSANDER-B"
}, {
  "date" : "2007-07-19",
  "value" : 21526.01,
  "symbol" : "BANSANDER-B"
}, {
  "date" : "2007-07-20",
  "value" : 21496.93,
  "symbol" : "BANSANDER-B"
}, {
  "date" : "2007-07-21",
  "value" : 21496.93,
  "symbol" : "BANSANDER-B"
}, {
  "date" : "2007-07-22",
  "value" : 21496.93,
  "symbol" : "BANSANDER-B"
}, {
  "date" : "2007-07-23",
  "value" : 21572.56,
  "symbol" : "BANSANDER-B"
}, {
  "date" : "2007-07-24",
  "value" : 21566.23,
  "symbol" : "BANSANDER-B"
}, {
  "date" : "2007-07-25",
  "value" : 21662.32,
  "symbol" : "BANSANDER-B"
}, {
  "date" : "2007-07-26",
  "value" : 21568.27,
  "symbol" : "BANSANDER-B"
}, {
  "date" : "2007-07-27",
  "value" : 21422.44,
  "symbol" : "BANSANDER-B"
}, {
  "date" : "2007-07-28",
  "value" : 21422.44,
  "symbol" : "BANSANDER-B"
}, {
  "date" : "2007-07-29",
  "value" : 21422.44,
  "symbol" : "BANSANDER-B"
}, {
  "date" : "2007-07-30",
  "value" : 21164.04,
  "symbol" : "BANSANDER-B"
}, {
  "date" : "2007-07-31",
  "value" : 21098.00,
  "symbol" : "BANSANDER-B"
}, {
  "date" : "2007-08-01",
  "value" : 21252.44,
  "symbol" : "BANSANDER-B"
}, {
  "date" : "2007-08-02",
  "value" : 21230.53,
  "symbol" : "BANSANDER-B"
}, {
  "date" : "2007-08-03",
  "value" : 21071.43,
  "symbol" : "BANSANDER-B"
}, {
  "date" : "2007-08-04",
  "value" : 21071.43,
  "symbol" : "BANSANDER-B"
}, {
  "date" : "2007-08-05",
  "value" : 21071.43,
  "symbol" : "BANSANDER-B"
}, {
  "date" : "2007-08-06",
  "value" : 21153.99,
  "symbol" : "BANSANDER-B"
}, {
  "date" : "2007-08-07",
  "value" : 21009.35,
  "symbol" : "BANSANDER-B"
}, {
  "date" : "2007-08-08",
  "value" : 20888.20,
  "symbol" : "BANSANDER-B"
}, {
  "date" : "2007-08-09",
  "value" : 20912.11,
  "symbol" : "BANSANDER-B"
}, {
  "date" : "2007-08-10",
  "value" : 21065.97,
  "symbol" : "BANSANDER-B"
}, {
  "date" : "2007-08-11",
  "value" : 21065.97,
  "symbol" : "BANSANDER-B"
}, {
  "date" : "2007-08-12",
  "value" : 21065.97,
  "symbol" : "BANSANDER-B"
}, {
  "date" : "2007-08-13",
  "value" : 20843.15,
  "symbol" : "BANSANDER-B"
}, {
  "date" : "2007-08-14",
  "value" : 20684.30,
  "symbol" : "BANSANDER-B"
}, {
  "date" : "2007-08-15",
  "value" : 20684.30,
  "symbol" : "BANSANDER-B"
}, {
  "date" : "2007-08-16",
  "value" : 20657.20,
  "symbol" : "BANSANDER-B"
}, {
  "date" : "2007-08-17",
  "value" : 20209.02,
  "symbol" : "BANSANDER-B"
}, {
  "date" : "2007-08-18",
  "value" : 20209.02,
  "symbol" : "BANSANDER-B"
}, {
  "date" : "2007-08-19",
  "value" : 20209.02,
  "symbol" : "BANSANDER-B"
}, {
  "date" : "2007-08-20",
  "value" : 19870.85,
  "symbol" : "BANSANDER-B"
}, {
  "date" : "2007-08-21",
  "value" : 20026.76,
  "symbol" : "BANSANDER-B"
}, {
  "date" : "2007-08-22",
  "value" : 20204.27,
  "symbol" : "BANSANDER-B"
}, {
  "date" : "2007-08-23",
  "value" : 20341.11,
  "symbol" : "BANSANDER-B"
}, {
  "date" : "2007-08-24",
  "value" : 20567.46,
  "symbol" : "BANSANDER-B"
}, {
  "date" : "2007-08-25",
  "value" : 20567.46,
  "symbol" : "BANSANDER-B"
}, {
  "date" : "2007-08-26",
  "value" : 20567.46,
  "symbol" : "BANSANDER-B"
}, {
  "date" : "2007-08-27",
  "value" : 20668.74,
  "symbol" : "BANSANDER-B"
}, {
  "date" : "2007-08-28",
  "value" : 20800.64,
  "symbol" : "BANSANDER-B"
}, {
  "date" : "2007-08-29",
  "value" : 20833.01,
  "symbol" : "BANSANDER-B"
}, {
  "date" : "2007-08-30",
  "value" : 20692.37,
  "symbol" : "BANSANDER-B"
}, {
  "date" : "2007-08-31",
  "value" : 20832.12,
  "symbol" : "BANSANDER-B"
}, {
  "date" : "2007-09-01",
  "value" : 20832.12,
  "symbol" : "BANSANDER-B"
}, {
  "date" : "2007-09-02",
  "value" : 20832.12,
  "symbol" : "BANSANDER-B"
}, {
  "date" : "2007-09-03",
  "value" : 20949.45,
  "symbol" : "BANSANDER-B"
}, {
  "date" : "2007-09-04",
  "value" : 21119.35,
  "symbol" : "BANSANDER-B"
}, {
  "date" : "2007-09-05",
  "value" : 21147.40,
  "symbol" : "BANSANDER-B"
}, {
  "date" : "2007-09-06",
  "value" : 21154.43,
  "symbol" : "BANSANDER-B"
}, {
  "date" : "2007-09-07",
  "value" : 21089.13,
  "symbol" : "BANSANDER-B"
}, {
  "date" : "2007-09-08",
  "value" : 21089.13,
  "symbol" : "BANSANDER-B"
}, {
  "date" : "2007-09-09",
  "value" : 21089.13,
  "symbol" : "BANSANDER-B"
}, {
  "date" : "2007-09-10",
  "value" : 21081.51,
  "symbol" : "BANSANDER-B"
}, {
  "date" : "2007-09-11",
  "value" : 20914.70,
  "symbol" : "BANSANDER-B"
}, {
  "date" : "2007-09-12",
  "value" : 20835.09,
  "symbol" : "BANSANDER-B"
}, {
  "date" : "2007-09-13",
  "value" : 20898.70,
  "symbol" : "BANSANDER-B"
}, {
  "date" : "2007-09-14",
  "value" : 20908.90,
  "symbol" : "BANSANDER-B"
}, {
  "date" : "2007-09-15",
  "value" : 20908.90,
  "symbol" : "BANSANDER-B"
}, {
  "date" : "2007-09-16",
  "value" : 20908.90,
  "symbol" : "BANSANDER-B"
}, {
  "date" : "2007-09-17",
  "value" : 20908.90,
  "symbol" : "BANSANDER-B"
}, {
  "date" : "2007-09-18",
  "value" : 20908.90,
  "symbol" : "BANSANDER-B"
}, {
  "date" : "2007-09-19",
  "value" : 20908.90,
  "symbol" : "BANSANDER-B"
}, {
  "date" : "2007-09-20",
  "value" : 20981.04,
  "symbol" : "BANSANDER-B"
}, {
  "date" : "2007-09-21",
  "value" : 21343.11,
  "symbol" : "BANSANDER-B"
}, {
  "date" : "2007-09-22",
  "value" : 21343.11,
  "symbol" : "BANSANDER-B"
}, {
  "date" : "2007-09-23",
  "value" : 21343.11,
  "symbol" : "BANSANDER-B"
}, {
  "date" : "2007-09-24",
  "value" : 21375.19,
  "symbol" : "BANSANDER-B"
}, {
  "date" : "2007-09-25",
  "value" : 21427.38,
  "symbol" : "BANSANDER-B"
}, {
  "date" : "2007-09-26",
  "value" : 21480.75,
  "symbol" : "BANSANDER-B"
}, {
  "date" : "2007-09-27",
  "value" : 21451.33,
  "symbol" : "BANSANDER-B"
}, {
  "date" : "2007-09-28",
  "value" : 21566.05,
  "symbol" : "BANSANDER-B"
}, {
  "date" : "2007-09-29",
  "value" : 21566.05,
  "symbol" : "BANSANDER-B"
}, {
  "date" : "2007-09-30",
  "value" : 21566.05,
  "symbol" : "BANSANDER-B"
}, {
  "date" : "2007-10-01",
  "value" : 21711.68,
  "symbol" : "BANSANDER-B"
}, {
  "date" : "2007-10-02",
  "value" : 21752.16,
  "symbol" : "BANSANDER-B"
}, {
  "date" : "2007-10-03",
  "value" : 21928.89,
  "symbol" : "BANSANDER-B"
}, {
  "date" : "2007-10-04",
  "value" : 21985.61,
  "symbol" : "BANSANDER-B"
}, {
  "date" : "2007-10-05",
  "value" : 21894.37,
  "symbol" : "BANSANDER-B"
}, {
  "date" : "2007-10-06",
  "value" : 21894.37,
  "symbol" : "BANSANDER-B"
}, {
  "date" : "2007-10-07",
  "value" : 21894.37,
  "symbol" : "BANSANDER-B"
}, {
  "date" : "2007-10-08",
  "value" : 21907.21,
  "symbol" : "BANSANDER-B"
}, {
  "date" : "2007-10-09",
  "value" : 22036.56,
  "symbol" : "BANSANDER-B"
}, {
  "date" : "2007-10-10",
  "value" : 22064.36,
  "symbol" : "BANSANDER-B"
}, {
  "date" : "2007-10-11",
  "value" : 22105.47,
  "symbol" : "BANSANDER-B"
}, {
  "date" : "2007-10-12",
  "value" : 22210.40,
  "symbol" : "BANSANDER-B"
}, {
  "date" : "2007-10-13",
  "value" : 22210.40,
  "symbol" : "BANSANDER-B"
}, {
  "date" : "2007-10-14",
  "value" : 22210.40,
  "symbol" : "BANSANDER-B"
}, {
  "date" : "2007-10-15",
  "value" : 22210.40,
  "symbol" : "BANSANDER-B"
}, {
  "date" : "2007-10-16",
  "value" : 22245.04,
  "symbol" : "BANSANDER-B"
}, {
  "date" : "2007-10-17",
  "value" : 22276.77,
  "symbol" : "BANSANDER-B"
}, {
  "date" : "2007-10-18",
  "value" : 22203.83,
  "symbol" : "BANSANDER-B"
}, {
  "date" : "2007-10-19",
  "value" : 22301.50,
  "symbol" : "BANSANDER-B"
}, {
  "date" : "2007-10-20",
  "value" : 22301.50,
  "symbol" : "BANSANDER-B"
}, {
  "date" : "2007-10-21",
  "value" : 22301.50,
  "symbol" : "BANSANDER-B"
}, {
  "date" : "2007-10-22",
  "value" : 22316.08,
  "symbol" : "BANSANDER-B"
}, {
  "date" : "2007-10-23",
  "value" : 22138.68,
  "symbol" : "BANSANDER-B"
}, {
  "date" : "2007-10-24",
  "value" : 22140.86,
  "symbol" : "BANSANDER-B"
}, {
  "date" : "2007-10-25",
  "value" : 22303.15,
  "symbol" : "BANSANDER-B"
}, {
  "date" : "2007-10-26",
  "value" : 22322.12,
  "symbol" : "BANSANDER-B"
}, {
  "date" : "2007-10-27",
  "value" : 22322.12,
  "symbol" : "BANSANDER-B"
}, {
  "date" : "2007-10-28",
  "value" : 22322.12,
  "symbol" : "BANSANDER-B"
}, {
  "date" : "2007-10-29",
  "value" : 22402.56,
  "symbol" : "BANSANDER-B"
}, {
  "date" : "2007-10-30",
  "value" : 22561.81,
  "symbol" : "BANSANDER-B"
}, {
  "date" : "2007-10-31",
  "value" : 22689.25,
  "symbol" : "BANSANDER-B"
}, {
  "date" : "2007-11-01",
  "value" : 22689.25,
  "symbol" : "BANSANDER-B"
}, {
  "date" : "2007-11-02",
  "value" : 22650.18,
  "symbol" : "BANSANDER-B"
}, {
  "date" : "2007-11-03",
  "value" : 22650.18,
  "symbol" : "BANSANDER-B"
}, {
  "date" : "2007-11-04",
  "value" : 22650.18,
  "symbol" : "BANSANDER-B"
}, {
  "date" : "2007-11-05",
  "value" : 22606.89,
  "symbol" : "BANSANDER-B"
}, {
  "date" : "2007-11-06",
  "value" : 22309.99,
  "symbol" : "BANSANDER-B"
}, {
  "date" : "2007-11-07",
  "value" : 22348.27,
  "symbol" : "BANSANDER-B"
}, {
  "date" : "2007-11-08",
  "value" : 22363.18,
  "symbol" : "BANSANDER-B"
}, {
  "date" : "2007-11-09",
  "value" : 22206.65,
  "symbol" : "BANSANDER-B"
}, {
  "date" : "2007-11-10",
  "value" : 22206.65,
  "symbol" : "BANSANDER-B"
}, {
  "date" : "2007-11-11",
  "value" : 22206.65,
  "symbol" : "BANSANDER-B"
}, {
  "date" : "2007-11-12",
  "value" : 22115.51,
  "symbol" : "BANSANDER-B"
}, {
  "date" : "2007-11-13",
  "value" : 21894.78,
  "symbol" : "BANSANDER-B"
}, {
  "date" : "2007-11-14",
  "value" : 21871.24,
  "symbol" : "BANSANDER-B"
}, {
  "date" : "2007-11-15",
  "value" : 22059.27,
  "symbol" : "BANSANDER-B"
}, {
  "date" : "2007-11-16",
  "value" : 22008.52,
  "symbol" : "BANSANDER-B"
}, {
  "date" : "2007-11-17",
  "value" : 22008.52,
  "symbol" : "BANSANDER-B"
}, {
  "date" : "2007-11-18",
  "value" : 22008.52,
  "symbol" : "BANSANDER-B"
}, {
  "date" : "2007-11-19",
  "value" : 21935.59,
  "symbol" : "BANSANDER-B"
}, {
  "date" : "2007-11-20",
  "value" : 21762.13,
  "symbol" : "BANSANDER-B"
}, {
  "date" : "2007-11-21",
  "value" : 21679.31,
  "symbol" : "BANSANDER-B"
}, {
  "date" : "2007-11-22",
  "value" : 21435.72,
  "symbol" : "BANSANDER-B"
}, {
  "date" : "2007-11-23",
  "value" : 21359.00,
  "symbol" : "BANSANDER-B"
}, {
  "date" : "2007-11-24",
  "value" : 21359.00,
  "symbol" : "BANSANDER-B"
}, {
  "date" : "2007-11-25",
  "value" : 21359.00,
  "symbol" : "BANSANDER-B"
}, {
  "date" : "2007-11-26",
  "value" : 21431.83,
  "symbol" : "BANSANDER-B"
}, {
  "date" : "2007-11-27",
  "value" : 21483.89,
  "symbol" : "BANSANDER-B"
}, {
  "date" : "2007-11-28",
  "value" : 21362.33,
  "symbol" : "BANSANDER-B"
}, {
  "date" : "2007-11-29",
  "value" : 21523.47,
  "symbol" : "BANSANDER-B"
}, {
  "date" : "2007-11-30",
  "value" : 21698.29,
  "symbol" : "BANSANDER-B"
}, {
  "date" : "2007-12-01",
  "value" : 21698.29,
  "symbol" : "BANSANDER-B"
}, {
  "date" : "2007-12-02",
  "value" : 21698.29,
  "symbol" : "BANSANDER-B"
}, {
  "date" : "2007-12-03",
  "value" : 21820.93,
  "symbol" : "BANSANDER-B"
}, {
  "date" : "2007-12-04",
  "value" : 21842.85,
  "symbol" : "BANSANDER-B"
}, {
  "date" : "2007-12-05",
  "value" : 21792.77,
  "symbol" : "BANSANDER-B"
}, {
  "date" : "2007-12-06",
  "value" : 21900.46,
  "symbol" : "BANSANDER-B"
}, {
  "date" : "2007-12-07",
  "value" : 21986.95,
  "symbol" : "BANSANDER-B"
}, {
  "date" : "2007-12-08",
  "value" : 21986.95,
  "symbol" : "BANSANDER-B"
}, {
  "date" : "2007-12-09",
  "value" : 21986.95,
  "symbol" : "BANSANDER-B"
}, {
  "date" : "2007-12-10",
  "value" : 22065.42,
  "symbol" : "BANSANDER-B"
}, {
  "date" : "2007-12-11",
  "value" : 22088.18,
  "symbol" : "BANSANDER-B"
}, {
  "date" : "2007-12-12",
  "value" : 21979.01,
  "symbol" : "BANSANDER-B"
}, {
  "date" : "2007-12-13",
  "value" : 21922.52,
  "symbol" : "BANSANDER-B"
}, {
  "date" : "2007-12-14",
  "value" : 21631.49,
  "symbol" : "BANSANDER-B"
}, {
  "date" : "2007-12-15",
  "value" : 21631.49,
  "symbol" : "BANSANDER-B"
}, {
  "date" : "2007-12-16",
  "value" : 21631.49,
  "symbol" : "BANSANDER-B"
}, {
  "date" : "2007-12-17",
  "value" : 21431.28,
  "symbol" : "BANSANDER-B"
}, {
  "date" : "2007-12-18",
  "value" : 21212.13,
  "symbol" : "BANSANDER-B"
}, {
  "date" : "2007-12-19",
  "value" : 21107.11,
  "symbol" : "BANSANDER-B"
}, {
  "date" : "2007-12-20",
  "value" : 21127.38,
  "symbol" : "BANSANDER-B"
}, {
  "date" : "2007-12-21",
  "value" : 21169.79,
  "symbol" : "BANSANDER-B"
}, {
  "date" : "2007-12-22",
  "value" : 21169.79,
  "symbol" : "BANSANDER-B"
}, {
  "date" : "2007-12-23",
  "value" : 21169.79,
  "symbol" : "BANSANDER-B"
}, {
  "date" : "2007-12-24",
  "value" : 21344.97,
  "symbol" : "BANSANDER-B"
}, {
  "date" : "2007-12-25",
  "value" : 21344.97,
  "symbol" : "BANSANDER-B"
}, {
  "date" : "2007-12-26",
  "value" : 21446.03,
  "symbol" : "BANSANDER-B"
}, {
  "date" : "2007-12-27",
  "value" : 21459.46,
  "symbol" : "BANSANDER-B"
}, {
  "date" : "2007-12-28",
  "value" : 21577.73,
  "symbol" : "BANSANDER-B"
}, {
  "date" : "2007-12-29",
  "value" : 21577.73,
  "symbol" : "BANSANDER-B"
}, {
  "date" : "2007-12-30",
  "value" : 21577.73,
  "symbol" : "BANSANDER-B"
}, {
  "date" : "2007-12-31",
  "value" : 21591.04,
  "symbol" : "BANSANDER-B"
}, {
  "date" : "2008-01-01",
  "value" : 21591.04,
  "symbol" : "BANSANDER-B"
}, {
  "date" : "2008-01-02",
  "value" : 21606.97,
  "symbol" : "BANSANDER-B"
}, {
  "date" : "2008-01-03",
  "value" : 21583.14,
  "symbol" : "BANSANDER-B"
}, {
  "date" : "2008-01-04",
  "value" : 21448.39,
  "symbol" : "BANSANDER-B"
}, {
  "date" : "2008-01-05",
  "value" : 21448.39,
  "symbol" : "BANSANDER-B"
}, {
  "date" : "2008-01-06",
  "value" : 21448.39,
  "symbol" : "BANSANDER-B"
}, {
  "date" : "2008-01-07",
  "value" : 21318.91,
  "symbol" : "BANSANDER-B"
}, {
  "date" : "2008-01-08",
  "value" : 21168.31,
  "symbol" : "BANSANDER-B"
}, {
  "date" : "2008-01-09",
  "value" : 21096.20,
  "symbol" : "BANSANDER-B"
}, {
  "date" : "2008-01-10",
  "value" : 21005.48,
  "symbol" : "BANSANDER-B"
}, {
  "date" : "2008-01-11",
  "value" : 21003.87,
  "symbol" : "BANSANDER-B"
}, {
  "date" : "2008-01-12",
  "value" : 21003.87,
  "symbol" : "BANSANDER-B"
}, {
  "date" : "2008-01-13",
  "value" : 21003.87,
  "symbol" : "BANSANDER-B"
}, {
  "date" : "2008-01-14",
  "value" : 20974.96,
  "symbol" : "BANSANDER-B"
}, {
  "date" : "2008-01-15",
  "value" : 20883.22,
  "symbol" : "BANSANDER-B"
}, {
  "date" : "2008-01-16",
  "value" : 20673.27,
  "symbol" : "BANSANDER-B"
}, {
  "date" : "2008-01-17",
  "value" : 20359.49,
  "symbol" : "BANSANDER-B"
}, {
  "date" : "2008-01-18",
  "value" : 20239.00,
  "symbol" : "BANSANDER-B"
}, {
  "date" : "2008-01-19",
  "value" : 20239.00,
  "symbol" : "BANSANDER-B"
}, {
  "date" : "2008-01-20",
  "value" : 20239.00,
  "symbol" : "BANSANDER-B"
}, {
  "date" : "2008-01-21",
  "value" : 20129.10,
  "symbol" : "BANSANDER-B"
}, {
  "date" : "2008-01-22",
  "value" : 19764.42,
  "symbol" : "BANSANDER-B"
}, {
  "date" : "2008-01-23",
  "value" : 19581.69,
  "symbol" : "BANSANDER-B"
}, {
  "date" : "2008-01-24",
  "value" : 19562.58,
  "symbol" : "BANSANDER-B"
}, {
  "date" : "2008-01-25",
  "value" : 19838.95,
  "symbol" : "BANSANDER-B"
}, {
  "date" : "2008-01-26",
  "value" : 19838.95,
  "symbol" : "BANSANDER-B"
}, {
  "date" : "2008-01-27",
  "value" : 19838.95,
  "symbol" : "BANSANDER-B"
}, {
  "date" : "2008-01-28",
  "value" : 20080.49,
  "symbol" : "BANSANDER-B"
}, {
  "date" : "2008-01-29",
  "value" : 19940.95,
  "symbol" : "BANSANDER-B"
}, {
  "date" : "2008-01-30",
  "value" : 20077.46,
  "symbol" : "BANSANDER-B"
}, {
  "date" : "2008-01-31",
  "value" : 20127.91,
  "symbol" : "BANSANDER-B"
}, {
  "date" : "2008-02-01",
  "value" : 20130.43,
  "symbol" : "BANSANDER-B"
}, {
  "date" : "2008-02-02",
  "value" : 20130.43,
  "symbol" : "BANSANDER-B"
}, {
  "date" : "2008-02-03",
  "value" : 20130.43,
  "symbol" : "BANSANDER-B"
}, {
  "date" : "2008-02-04",
  "value" : 20329.84,
  "symbol" : "BANSANDER-B"
}, {
  "date" : "2008-02-05",
  "value" : 20449.35,
  "symbol" : "BANSANDER-B"
}, {
  "date" : "2008-02-06",
  "value" : 20311.71,
  "symbol" : "BANSANDER-B"
}, {
  "date" : "2008-02-07",
  "value" : 20187.35,
  "symbol" : "BANSANDER-B"
}, {
  "date" : "2008-02-08",
  "value" : 20100.89,
  "symbol" : "BANSANDER-B"
}, {
  "date" : "2008-02-09",
  "value" : 20100.89,
  "symbol" : "BANSANDER-B"
}, {
  "date" : "2008-02-10",
  "value" : 20100.89,
  "symbol" : "BANSANDER-B"
}, {
  "date" : "2008-02-11",
  "value" : 20126.79,
  "symbol" : "BANSANDER-B"
}, {
  "date" : "2008-02-12",
  "value" : 20100.07,
  "symbol" : "BANSANDER-B"
}, {
  "date" : "2008-02-13",
  "value" : 20291.25,
  "symbol" : "BANSANDER-B"
}, {
  "date" : "2008-02-14",
  "value" : 20388.44,
  "symbol" : "BANSANDER-B"
}, {
  "date" : "2008-02-15",
  "value" : 20475.24,
  "symbol" : "BANSANDER-B"
}, {
  "date" : "2008-02-16",
  "value" : 20475.24,
  "symbol" : "BANSANDER-B"
}, {
  "date" : "2008-02-17",
  "value" : 20475.24,
  "symbol" : "BANSANDER-B"
}, {
  "date" : "2008-02-18",
  "value" : 20422.85,
  "symbol" : "BANSANDER-B"
}, {
  "date" : "2008-02-19",
  "value" : 20479.84,
  "symbol" : "BANSANDER-B"
}, {
  "date" : "2008-02-20",
  "value" : 20627.54,
  "symbol" : "BANSANDER-B"
}, {
  "date" : "2008-02-21",
  "value" : 20605.20,
  "symbol" : "BANSANDER-B"
}, {
  "date" : "2008-02-22",
  "value" : 20728.69,
  "symbol" : "BANSANDER-B"
}, {
  "date" : "2008-02-23",
  "value" : 20728.69,
  "symbol" : "BANSANDER-B"
}, {
  "date" : "2008-02-24",
  "value" : 20728.69,
  "symbol" : "BANSANDER-B"
}, {
  "date" : "2008-02-25",
  "value" : 20724.18,
  "symbol" : "BANSANDER-B"
}, {
  "date" : "2008-02-26",
  "value" : 20811.96,
  "symbol" : "BANSANDER-B"
}, {
  "date" : "2008-02-27",
  "value" : 20913.40,
  "symbol" : "BANSANDER-B"
}, {
  "date" : "2008-02-28",
  "value" : 20994.36,
  "symbol" : "BANSANDER-B"
}, {
  "date" : "2008-02-29",
  "value" : 20972.84,
  "symbol" : "BANSANDER-B"
}, {
  "date" : "2008-03-01",
  "value" : 20972.84,
  "symbol" : "BANSANDER-B"
}, {
  "date" : "2008-03-02",
  "value" : 20972.84,
  "symbol" : "BANSANDER-B"
}, {
  "date" : "2008-03-03",
  "value" : 20759.84,
  "symbol" : "BANSANDER-B"
}, {
  "date" : "2008-03-04",
  "value" : 20592.16,
  "symbol" : "BANSANDER-B"
}, {
  "date" : "2008-03-05",
  "value" : 20456.83,
  "symbol" : "BANSANDER-B"
}, {
  "date" : "2008-03-06",
  "value" : 20453.71,
  "symbol" : "BANSANDER-B"
}, {
  "date" : "2008-03-07",
  "value" : 20409.67,
  "symbol" : "BANSANDER-B"
}, {
  "date" : "2008-03-08",
  "value" : 20409.67,
  "symbol" : "BANSANDER-B"
}, {
  "date" : "2008-03-09",
  "value" : 20409.67,
  "symbol" : "BANSANDER-B"
}, {
  "date" : "2008-03-10",
  "value" : 20260.94,
  "symbol" : "BANSANDER-B"
}, {
  "date" : "2008-03-11",
  "value" : 20088.03,
  "symbol" : "BANSANDER-B"
}, {
  "date" : "2008-03-12",
  "value" : 20173.81,
  "symbol" : "BANSANDER-B"
}, {
  "date" : "2008-03-13",
  "value" : 20325.03,
  "symbol" : "BANSANDER-B"
}, {
  "date" : "2008-03-14",
  "value" : 20213.84,
  "symbol" : "BANSANDER-B"
}, {
  "date" : "2008-03-15",
  "value" : 20213.84,
  "symbol" : "BANSANDER-B"
}, {
  "date" : "2008-03-16",
  "value" : 20213.84,
  "symbol" : "BANSANDER-B"
}, {
  "date" : "2008-03-17",
  "value" : 20249.53,
  "symbol" : "BANSANDER-B"
}, {
  "date" : "2008-03-18",
  "value" : 20034.85,
  "symbol" : "BANSANDER-B"
}, {
  "date" : "2008-03-19",
  "value" : 20103.87,
  "symbol" : "BANSANDER-B"
}, {
  "date" : "2008-03-20",
  "value" : 20086.66,
  "symbol" : "BANSANDER-B"
}, {
  "date" : "2008-03-21",
  "value" : 20086.66,
  "symbol" : "BANSANDER-B"
}, {
  "date" : "2008-03-22",
  "value" : 20086.66,
  "symbol" : "BANSANDER-B"
}, {
  "date" : "2008-03-23",
  "value" : 20086.66,
  "symbol" : "BANSANDER-B"
}, {
  "date" : "2008-03-24",
  "value" : 20082.66,
  "symbol" : "BANSANDER-B"
}, {
  "date" : "2008-03-25",
  "value" : 20174.74,
  "symbol" : "BANSANDER-B"
}, {
  "date" : "2008-03-26",
  "value" : 20376.64,
  "symbol" : "BANSANDER-B"
}, {
  "date" : "2008-03-27",
  "value" : 20386.70,
  "symbol" : "BANSANDER-B"
}, {
  "date" : "2008-03-28",
  "value" : 20377.73,
  "symbol" : "BANSANDER-B"
}, {
  "date" : "2008-03-29",
  "value" : 20377.73,
  "symbol" : "BANSANDER-B"
}, {
  "date" : "2008-03-30",
  "value" : 20377.73,
  "symbol" : "BANSANDER-B"
}, {
  "date" : "2008-03-31",
  "value" : 20389.59,
  "symbol" : "BANSANDER-B"
} ]