[ {
  "date" : "2002-01-01",
  "value" : 21571.19,
  "symbol" : "MAGISTER-E"
}, {
  "date" : "2002-01-02",
  "value" : 21574.36,
  "symbol" : "MAGISTER-E"
}, {
  "date" : "2002-01-03",
  "value" : 21556.78,
  "symbol" : "MAGISTER-E"
}, {
  "date" : "2002-01-04",
  "value" : 21571.73,
  "symbol" : "MAGISTER-E"
}, {
  "date" : "2002-01-05",
  "value" : 21571.73,
  "symbol" : "MAGISTER-E"
}, {
  "date" : "2002-01-06",
  "value" : 21571.73,
  "symbol" : "MAGISTER-E"
}, {
  "date" : "2002-01-07",
  "value" : 21535.80,
  "symbol" : "MAGISTER-E"
}, {
  "date" : "2002-01-08",
  "value" : 21551.06,
  "symbol" : "MAGISTER-E"
}, {
  "date" : "2002-01-09",
  "value" : 21601.69,
  "symbol" : "MAGISTER-E"
}, {
  "date" : "2002-01-10",
  "value" : 21532.30,
  "symbol" : "MAGISTER-E"
}, {
  "date" : "2002-01-11",
  "value" : 21548.53,
  "symbol" : "MAGISTER-E"
}, {
  "date" : "2002-01-12",
  "value" : 21548.53,
  "symbol" : "MAGISTER-E"
}, {
  "date" : "2002-01-13",
  "value" : 21548.53,
  "symbol" : "MAGISTER-E"
}, {
  "date" : "2002-01-14",
  "value" : 21567.58,
  "symbol" : "MAGISTER-E"
}, {
  "date" : "2002-01-15",
  "value" : 21576.72,
  "symbol" : "MAGISTER-E"
}, {
  "date" : "2002-01-16",
  "value" : 21609.99,
  "symbol" : "MAGISTER-E"
}, {
  "date" : "2002-01-17",
  "value" : 21610.11,
  "symbol" : "MAGISTER-E"
}, {
  "date" : "2002-01-18",
  "value" : 21565.76,
  "symbol" : "MAGISTER-E"
}, {
  "date" : "2002-01-19",
  "value" : 21565.76,
  "symbol" : "MAGISTER-E"
}, {
  "date" : "2002-01-20",
  "value" : 21565.76,
  "symbol" : "MAGISTER-E"
}, {
  "date" : "2002-01-21",
  "value" : 21571.59,
  "symbol" : "MAGISTER-E"
}, {
  "date" : "2002-01-22",
  "value" : 21573.36,
  "symbol" : "MAGISTER-E"
}, {
  "date" : "2002-01-23",
  "value" : 21592.65,
  "symbol" : "MAGISTER-E"
}, {
  "date" : "2002-01-24",
  "value" : 21599.09,
  "symbol" : "MAGISTER-E"
}, {
  "date" : "2002-01-25",
  "value" : 21620.01,
  "symbol" : "MAGISTER-E"
}, {
  "date" : "2002-01-26",
  "value" : 21620.01,
  "symbol" : "MAGISTER-E"
}, {
  "date" : "2002-01-27",
  "value" : 21620.01,
  "symbol" : "MAGISTER-E"
}, {
  "date" : "2002-01-28",
  "value" : 21612.54,
  "symbol" : "MAGISTER-E"
}, {
  "date" : "2002-01-29",
  "value" : 21603.72,
  "symbol" : "MAGISTER-E"
}, {
  "date" : "2002-01-30",
  "value" : 21595.40,
  "symbol" : "MAGISTER-E"
}, {
  "date" : "2002-01-31",
  "value" : 21594.74,
  "symbol" : "MAGISTER-E"
}, {
  "date" : "2002-02-01",
  "value" : 21611.73,
  "symbol" : "MAGISTER-E"
}, {
  "date" : "2002-02-02",
  "value" : 21611.73,
  "symbol" : "MAGISTER-E"
}, {
  "date" : "2002-02-03",
  "value" : 21611.73,
  "symbol" : "MAGISTER-E"
}, {
  "date" : "2002-02-04",
  "value" : 21621.46,
  "symbol" : "MAGISTER-E"
}, {
  "date" : "2002-02-05",
  "value" : 21620.86,
  "symbol" : "MAGISTER-E"
}, {
  "date" : "2002-02-06",
  "value" : 21643.36,
  "symbol" : "MAGISTER-E"
}, {
  "date" : "2002-02-07",
  "value" : 21669.36,
  "symbol" : "MAGISTER-E"
}, {
  "date" : "2002-02-08",
  "value" : 21682.43,
  "symbol" : "MAGISTER-E"
}, {
  "date" : "2002-02-09",
  "value" : 21682.43,
  "symbol" : "MAGISTER-E"
}, {
  "date" : "2002-02-10",
  "value" : 21682.43,
  "symbol" : "MAGISTER-E"
}, {
  "date" : "2002-02-11",
  "value" : 21675.82,
  "symbol" : "MAGISTER-E"
}, {
  "date" : "2002-02-12",
  "value" : 21656.63,
  "symbol" : "MAGISTER-E"
}, {
  "date" : "2002-02-13",
  "value" : 21681.93,
  "symbol" : "MAGISTER-E"
}, {
  "date" : "2002-02-14",
  "value" : 21664.61,
  "symbol" : "MAGISTER-E"
}, {
  "date" : "2002-02-15",
  "value" : 21696.37,
  "symbol" : "MAGISTER-E"
}, {
  "date" : "2002-02-16",
  "value" : 21696.37,
  "symbol" : "MAGISTER-E"
}, {
  "date" : "2002-02-17",
  "value" : 21696.37,
  "symbol" : "MAGISTER-E"
}, {
  "date" : "2002-02-18",
  "value" : 21689.19,
  "symbol" : "MAGISTER-E"
}, {
  "date" : "2002-02-19",
  "value" : 21702.68,
  "symbol" : "MAGISTER-E"
}, {
  "date" : "2002-02-20",
  "value" : 21714.82,
  "symbol" : "MAGISTER-E"
}, {
  "date" : "2002-02-21",
  "value" : 21723.73,
  "symbol" : "MAGISTER-E"
}, {
  "date" : "2002-02-22",
  "value" : 21740.49,
  "symbol" : "MAGISTER-E"
}, {
  "date" : "2002-02-23",
  "value" : 21740.49,
  "symbol" : "MAGISTER-E"
}, {
  "date" : "2002-02-24",
  "value" : 21740.49,
  "symbol" : "MAGISTER-E"
}, {
  "date" : "2002-02-25",
  "value" : 21761.50,
  "symbol" : "MAGISTER-E"
}, {
  "date" : "2002-02-26",
  "value" : 21746.00,
  "symbol" : "MAGISTER-E"
}, {
  "date" : "2002-02-27",
  "value" : 21762.87,
  "symbol" : "MAGISTER-E"
}, {
  "date" : "2002-02-28",
  "value" : 21733.68,
  "symbol" : "MAGISTER-E"
}, {
  "date" : "2002-03-01",
  "value" : 21772.14,
  "symbol" : "MAGISTER-E"
}, {
  "date" : "2002-03-02",
  "value" : 21772.14,
  "symbol" : "MAGISTER-E"
}, {
  "date" : "2002-03-03",
  "value" : 21772.14,
  "symbol" : "MAGISTER-E"
}, {
  "date" : "2002-03-04",
  "value" : 21752.14,
  "symbol" : "MAGISTER-E"
}, {
  "date" : "2002-03-05",
  "value" : 21733.28,
  "symbol" : "MAGISTER-E"
}, {
  "date" : "2002-03-06",
  "value" : 21772.37,
  "symbol" : "MAGISTER-E"
}, {
  "date" : "2002-03-07",
  "value" : 21764.84,
  "symbol" : "MAGISTER-E"
}, {
  "date" : "2002-03-08",
  "value" : 21806.29,
  "symbol" : "MAGISTER-E"
}, {
  "date" : "2002-03-09",
  "value" : 21806.29,
  "symbol" : "MAGISTER-E"
}, {
  "date" : "2002-03-10",
  "value" : 21806.29,
  "symbol" : "MAGISTER-E"
}, {
  "date" : "2002-03-11",
  "value" : 21803.17,
  "symbol" : "MAGISTER-E"
}, {
  "date" : "2002-03-12",
  "value" : 21840.32,
  "symbol" : "MAGISTER-E"
}, {
  "date" : "2002-03-13",
  "value" : 21840.14,
  "symbol" : "MAGISTER-E"
}, {
  "date" : "2002-03-14",
  "value" : 21864.64,
  "symbol" : "MAGISTER-E"
}, {
  "date" : "2002-03-15",
  "value" : 21913.25,
  "symbol" : "MAGISTER-E"
}, {
  "date" : "2002-03-16",
  "value" : 21913.25,
  "symbol" : "MAGISTER-E"
}, {
  "date" : "2002-03-17",
  "value" : 21913.25,
  "symbol" : "MAGISTER-E"
}, {
  "date" : "2002-03-18",
  "value" : 21877.00,
  "symbol" : "MAGISTER-E"
}, {
  "date" : "2002-03-19",
  "value" : 21895.47,
  "symbol" : "MAGISTER-E"
}, {
  "date" : "2002-03-20",
  "value" : 21913.88,
  "symbol" : "MAGISTER-E"
}, {
  "date" : "2002-03-21",
  "value" : 21925.39,
  "symbol" : "MAGISTER-E"
}, {
  "date" : "2002-03-22",
  "value" : 21971.90,
  "symbol" : "MAGISTER-E"
}, {
  "date" : "2002-03-23",
  "value" : 21971.90,
  "symbol" : "MAGISTER-E"
}, {
  "date" : "2002-03-24",
  "value" : 21971.90,
  "symbol" : "MAGISTER-E"
}, {
  "date" : "2002-03-25",
  "value" : 21993.02,
  "symbol" : "MAGISTER-E"
}, {
  "date" : "2002-03-26",
  "value" : 21972.70,
  "symbol" : "MAGISTER-E"
}, {
  "date" : "2002-03-27",
  "value" : 21956.92,
  "symbol" : "MAGISTER-E"
}, {
  "date" : "2002-03-28",
  "value" : 21971.73,
  "symbol" : "MAGISTER-E"
}, {
  "date" : "2002-03-29",
  "value" : 21971.73,
  "symbol" : "MAGISTER-E"
}, {
  "date" : "2002-03-30",
  "value" : 21971.73,
  "symbol" : "MAGISTER-E"
}, {
  "date" : "2002-03-31",
  "value" : 21971.73,
  "symbol" : "MAGISTER-E"
}, {
  "date" : "2002-04-01",
  "value" : 21950.04,
  "symbol" : "MAGISTER-E"
}, {
  "date" : "2002-04-02",
  "value" : 21961.98,
  "symbol" : "MAGISTER-E"
}, {
  "date" : "2002-04-03",
  "value" : 21982.97,
  "symbol" : "MAGISTER-E"
}, {
  "date" : "2002-04-04",
  "value" : 21983.47,
  "symbol" : "MAGISTER-E"
}, {
  "date" : "2002-04-05",
  "value" : 22093.35,
  "symbol" : "MAGISTER-E"
}, {
  "date" : "2002-04-06",
  "value" : 22093.35,
  "symbol" : "MAGISTER-E"
}, {
  "date" : "2002-04-07",
  "value" : 22093.35,
  "symbol" : "MAGISTER-E"
}, {
  "date" : "2002-04-08",
  "value" : 22033.97,
  "symbol" : "MAGISTER-E"
}, {
  "date" : "2002-04-09",
  "value" : 22121.67,
  "symbol" : "MAGISTER-E"
}, {
  "date" : "2002-04-10",
  "value" : 22078.95,
  "symbol" : "MAGISTER-E"
}, {
  "date" : "2002-04-11",
  "value" : 22147.19,
  "symbol" : "MAGISTER-E"
}, {
  "date" : "2002-04-12",
  "value" : 22105.06,
  "symbol" : "MAGISTER-E"
}, {
  "date" : "2002-04-13",
  "value" : 22105.06,
  "symbol" : "MAGISTER-E"
}, {
  "date" : "2002-04-14",
  "value" : 22105.06,
  "symbol" : "MAGISTER-E"
}, {
  "date" : "2002-04-15",
  "value" : 22076.51,
  "symbol" : "MAGISTER-E"
}, {
  "date" : "2002-04-16",
  "value" : 22058.36,
  "symbol" : "MAGISTER-E"
}, {
  "date" : "2002-04-17",
  "value" : 22065.30,
  "symbol" : "MAGISTER-E"
}, {
  "date" : "2002-04-18",
  "value" : 22093.56,
  "symbol" : "MAGISTER-E"
}, {
  "date" : "2002-04-19",
  "value" : 22087.57,
  "symbol" : "MAGISTER-E"
}, {
  "date" : "2002-04-20",
  "value" : 22087.57,
  "symbol" : "MAGISTER-E"
}, {
  "date" : "2002-04-21",
  "value" : 22087.57,
  "symbol" : "MAGISTER-E"
}, {
  "date" : "2002-04-22",
  "value" : 22060.48,
  "symbol" : "MAGISTER-E"
}, {
  "date" : "2002-04-23",
  "value" : 22197.67,
  "symbol" : "MAGISTER-E"
}, {
  "date" : "2002-04-24",
  "value" : 22197.67,
  "symbol" : "MAGISTER-E"
}, {
  "date" : "2002-04-25",
  "value" : 22068.16,
  "symbol" : "MAGISTER-E"
}, {
  "date" : "2002-04-26",
  "value" : 22078.07,
  "symbol" : "MAGISTER-E"
}, {
  "date" : "2002-04-27",
  "value" : 22078.07,
  "symbol" : "MAGISTER-E"
}, {
  "date" : "2002-04-28",
  "value" : 22078.07,
  "symbol" : "MAGISTER-E"
}, {
  "date" : "2002-04-29",
  "value" : 22143.06,
  "symbol" : "MAGISTER-E"
}, {
  "date" : "2002-04-30",
  "value" : 22095.20,
  "symbol" : "MAGISTER-E"
}, {
  "date" : "2002-05-01",
  "value" : 22095.20,
  "symbol" : "MAGISTER-E"
}, {
  "date" : "2002-05-02",
  "value" : 22105.88,
  "symbol" : "MAGISTER-E"
}, {
  "date" : "2002-05-03",
  "value" : 22127.51,
  "symbol" : "MAGISTER-E"
}, {
  "date" : "2002-05-04",
  "value" : 22127.51,
  "symbol" : "MAGISTER-E"
}, {
  "date" : "2002-05-05",
  "value" : 22127.51,
  "symbol" : "MAGISTER-E"
}, {
  "date" : "2002-05-06",
  "value" : 22148.32,
  "symbol" : "MAGISTER-E"
}, {
  "date" : "2002-05-07",
  "value" : 22148.46,
  "symbol" : "MAGISTER-E"
}, {
  "date" : "2002-05-08",
  "value" : 22158.85,
  "symbol" : "MAGISTER-E"
}, {
  "date" : "2002-05-09",
  "value" : 22144.43,
  "symbol" : "MAGISTER-E"
}, {
  "date" : "2002-05-10",
  "value" : 22171.62,
  "symbol" : "MAGISTER-E"
}, {
  "date" : "2002-05-11",
  "value" : 22171.62,
  "symbol" : "MAGISTER-E"
}, {
  "date" : "2002-05-12",
  "value" : 22171.62,
  "symbol" : "MAGISTER-E"
}, {
  "date" : "2002-05-13",
  "value" : 22190.19,
  "symbol" : "MAGISTER-E"
}, {
  "date" : "2002-05-14",
  "value" : 22172.72,
  "symbol" : "MAGISTER-E"
}, {
  "date" : "2002-05-15",
  "value" : 22192.73,
  "symbol" : "MAGISTER-E"
}, {
  "date" : "2002-05-16",
  "value" : 22222.86,
  "symbol" : "MAGISTER-E"
}, {
  "date" : "2002-05-17",
  "value" : 22205.78,
  "symbol" : "MAGISTER-E"
}, {
  "date" : "2002-05-18",
  "value" : 22205.78,
  "symbol" : "MAGISTER-E"
}, {
  "date" : "2002-05-19",
  "value" : 22205.78,
  "symbol" : "MAGISTER-E"
}, {
  "date" : "2002-05-20",
  "value" : 22159.86,
  "symbol" : "MAGISTER-E"
}, {
  "date" : "2002-05-21",
  "value" : 22159.86,
  "symbol" : "MAGISTER-E"
}, {
  "date" : "2002-05-22",
  "value" : 22158.35,
  "symbol" : "MAGISTER-E"
}, {
  "date" : "2002-05-23",
  "value" : 22168.24,
  "symbol" : "MAGISTER-E"
}, {
  "date" : "2002-05-24",
  "value" : 22133.81,
  "symbol" : "MAGISTER-E"
}, {
  "date" : "2002-05-25",
  "value" : 22133.81,
  "symbol" : "MAGISTER-E"
}, {
  "date" : "2002-05-26",
  "value" : 22133.81,
  "symbol" : "MAGISTER-E"
}, {
  "date" : "2002-05-27",
  "value" : 22133.81,
  "symbol" : "MAGISTER-E"
}, {
  "date" : "2002-05-28",
  "value" : 22159.33,
  "symbol" : "MAGISTER-E"
}, {
  "date" : "2002-05-29",
  "value" : 22136.85,
  "symbol" : "MAGISTER-E"
}, {
  "date" : "2002-05-30",
  "value" : 22181.10,
  "symbol" : "MAGISTER-E"
}, {
  "date" : "2002-05-31",
  "value" : 22185.14,
  "symbol" : "MAGISTER-E"
}, {
  "date" : "2002-06-01",
  "value" : 22185.14,
  "symbol" : "MAGISTER-E"
}, {
  "date" : "2002-06-02",
  "value" : 22185.14,
  "symbol" : "MAGISTER-E"
}, {
  "date" : "2002-06-03",
  "value" : 22285.35,
  "symbol" : "MAGISTER-E"
}, {
  "date" : "2002-06-04",
  "value" : 22257.50,
  "symbol" : "MAGISTER-E"
}, {
  "date" : "2002-06-05",
  "value" : 22263.99,
  "symbol" : "MAGISTER-E"
}, {
  "date" : "2002-06-06",
  "value" : 22232.03,
  "symbol" : "MAGISTER-E"
}, {
  "date" : "2002-06-07",
  "value" : 22300.32,
  "symbol" : "MAGISTER-E"
}, {
  "date" : "2002-06-08",
  "value" : 22300.32,
  "symbol" : "MAGISTER-E"
}, {
  "date" : "2002-06-09",
  "value" : 22300.32,
  "symbol" : "MAGISTER-E"
}, {
  "date" : "2002-06-10",
  "value" : 22259.51,
  "symbol" : "MAGISTER-E"
}, {
  "date" : "2002-06-11",
  "value" : 22258.66,
  "symbol" : "MAGISTER-E"
}, {
  "date" : "2002-06-12",
  "value" : 22306.25,
  "symbol" : "MAGISTER-E"
}, {
  "date" : "2002-06-13",
  "value" : 22215.47,
  "symbol" : "MAGISTER-E"
}, {
  "date" : "2002-06-14",
  "value" : 22318.81,
  "symbol" : "MAGISTER-E"
}, {
  "date" : "2002-06-15",
  "value" : 22318.81,
  "symbol" : "MAGISTER-E"
}, {
  "date" : "2002-06-16",
  "value" : 22318.81,
  "symbol" : "MAGISTER-E"
}, {
  "date" : "2002-06-17",
  "value" : 22336.83,
  "symbol" : "MAGISTER-E"
}, {
  "date" : "2002-06-18",
  "value" : 22198.59,
  "symbol" : "MAGISTER-E"
}, {
  "date" : "2002-06-19",
  "value" : 22202.18,
  "symbol" : "MAGISTER-E"
}, {
  "date" : "2002-06-20",
  "value" : 22252.54,
  "symbol" : "MAGISTER-E"
}, {
  "date" : "2002-06-21",
  "value" : 22182.22,
  "symbol" : "MAGISTER-E"
}, {
  "date" : "2002-06-22",
  "value" : 22182.22,
  "symbol" : "MAGISTER-E"
}, {
  "date" : "2002-06-23",
  "value" : 22182.22,
  "symbol" : "MAGISTER-E"
}, {
  "date" : "2002-06-24",
  "value" : 22178.70,
  "symbol" : "MAGISTER-E"
}, {
  "date" : "2002-06-25",
  "value" : 22188.22,
  "symbol" : "MAGISTER-E"
}, {
  "date" : "2002-06-26",
  "value" : 22174.26,
  "symbol" : "MAGISTER-E"
}, {
  "date" : "2002-06-27",
  "value" : 22103.05,
  "symbol" : "MAGISTER-E"
}, {
  "date" : "2002-06-28",
  "value" : 22170.31,
  "symbol" : "MAGISTER-E"
}, {
  "date" : "2002-06-29",
  "value" : 22170.31,
  "symbol" : "MAGISTER-E"
}, {
  "date" : "2002-06-30",
  "value" : 22170.31,
  "symbol" : "MAGISTER-E"
}, {
  "date" : "2002-07-01",
  "value" : 22196.15,
  "symbol" : "MAGISTER-E"
}, {
  "date" : "2002-07-02",
  "value" : 22267.46,
  "symbol" : "MAGISTER-E"
}, {
  "date" : "2002-07-03",
  "value" : 22347.52,
  "symbol" : "MAGISTER-E"
}, {
  "date" : "2002-07-04",
  "value" : 22237.17,
  "symbol" : "MAGISTER-E"
}, {
  "date" : "2002-07-05",
  "value" : 22221.08,
  "symbol" : "MAGISTER-E"
}, {
  "date" : "2002-07-06",
  "value" : 22221.08,
  "symbol" : "MAGISTER-E"
}, {
  "date" : "2002-07-07",
  "value" : 22221.08,
  "symbol" : "MAGISTER-E"
}, {
  "date" : "2002-07-08",
  "value" : 22294.55,
  "symbol" : "MAGISTER-E"
}, {
  "date" : "2002-07-09",
  "value" : 22317.99,
  "symbol" : "MAGISTER-E"
}, {
  "date" : "2002-07-10",
  "value" : 22332.84,
  "symbol" : "MAGISTER-E"
}, {
  "date" : "2002-07-11",
  "value" : 22373.14,
  "symbol" : "MAGISTER-E"
}, {
  "date" : "2002-07-12",
  "value" : 22497.59,
  "symbol" : "MAGISTER-E"
}, {
  "date" : "2002-07-13",
  "value" : 22497.59,
  "symbol" : "MAGISTER-E"
}, {
  "date" : "2002-07-14",
  "value" : 22497.59,
  "symbol" : "MAGISTER-E"
}, {
  "date" : "2002-07-15",
  "value" : 22360.94,
  "symbol" : "MAGISTER-E"
}, {
  "date" : "2002-07-16",
  "value" : 22514.07,
  "symbol" : "MAGISTER-E"
}, {
  "date" : "2002-07-17",
  "value" : 22452.83,
  "symbol" : "MAGISTER-E"
}, {
  "date" : "2002-07-18",
  "value" : 22444.98,
  "symbol" : "MAGISTER-E"
}, {
  "date" : "2002-07-19",
  "value" : 22571.46,
  "symbol" : "MAGISTER-E"
}, {
  "date" : "2002-07-20",
  "value" : 22571.46,
  "symbol" : "MAGISTER-E"
}, {
  "date" : "2002-07-21",
  "value" : 22571.46,
  "symbol" : "MAGISTER-E"
}, {
  "date" : "2002-07-22",
  "value" : 22525.02,
  "symbol" : "MAGISTER-E"
}, {
  "date" : "2002-07-23",
  "value" : 22450.00,
  "symbol" : "MAGISTER-E"
}, {
  "date" : "2002-07-24",
  "value" : 22632.50,
  "symbol" : "MAGISTER-E"
}, {
  "date" : "2002-07-25",
  "value" : 22610.01,
  "symbol" : "MAGISTER-E"
}, {
  "date" : "2002-07-26",
  "value" : 22626.89,
  "symbol" : "MAGISTER-E"
}, {
  "date" : "2002-07-27",
  "value" : 22626.89,
  "symbol" : "MAGISTER-E"
}, {
  "date" : "2002-07-28",
  "value" : 22626.89,
  "symbol" : "MAGISTER-E"
}, {
  "date" : "2002-07-29",
  "value" : 22591.75,
  "symbol" : "MAGISTER-E"
}, {
  "date" : "2002-07-30",
  "value" : 22572.60,
  "symbol" : "MAGISTER-E"
}, {
  "date" : "2002-07-31",
  "value" : 22726.97,
  "symbol" : "MAGISTER-E"
}, {
  "date" : "2002-08-01",
  "value" : 22442.22,
  "symbol" : "MAGISTER-E"
}, {
  "date" : "2002-08-02",
  "value" : 22484.70,
  "symbol" : "MAGISTER-E"
}, {
  "date" : "2002-08-03",
  "value" : 22484.70,
  "symbol" : "MAGISTER-E"
}, {
  "date" : "2002-08-04",
  "value" : 22484.70,
  "symbol" : "MAGISTER-E"
}, {
  "date" : "2002-08-05",
  "value" : 22599.55,
  "symbol" : "MAGISTER-E"
}, {
  "date" : "2002-08-06",
  "value" : 22623.37,
  "symbol" : "MAGISTER-E"
}, {
  "date" : "2002-08-07",
  "value" : 22644.24,
  "symbol" : "MAGISTER-E"
}, {
  "date" : "2002-08-08",
  "value" : 22647.58,
  "symbol" : "MAGISTER-E"
}, {
  "date" : "2002-08-09",
  "value" : 22861.73,
  "symbol" : "MAGISTER-E"
}, {
  "date" : "2002-08-10",
  "value" : 22861.73,
  "symbol" : "MAGISTER-E"
}, {
  "date" : "2002-08-11",
  "value" : 22861.73,
  "symbol" : "MAGISTER-E"
}, {
  "date" : "2002-08-12",
  "value" : 22868.52,
  "symbol" : "MAGISTER-E"
}, {
  "date" : "2002-08-13",
  "value" : 22849.52,
  "symbol" : "MAGISTER-E"
}, {
  "date" : "2002-08-14",
  "value" : 22708.60,
  "symbol" : "MAGISTER-E"
}, {
  "date" : "2002-08-15",
  "value" : 22708.60,
  "symbol" : "MAGISTER-E"
}, {
  "date" : "2002-08-16",
  "value" : 22685.02,
  "symbol" : "MAGISTER-E"
}, {
  "date" : "2002-08-17",
  "value" : 22685.02,
  "symbol" : "MAGISTER-E"
}, {
  "date" : "2002-08-18",
  "value" : 22685.02,
  "symbol" : "MAGISTER-E"
}, {
  "date" : "2002-08-19",
  "value" : 22751.28,
  "symbol" : "MAGISTER-E"
}, {
  "date" : "2002-08-20",
  "value" : 22778.92,
  "symbol" : "MAGISTER-E"
}, {
  "date" : "2002-08-21",
  "value" : 22779.44,
  "symbol" : "MAGISTER-E"
}, {
  "date" : "2002-08-22",
  "value" : 22951.12,
  "symbol" : "MAGISTER-E"
}, {
  "date" : "2002-08-23",
  "value" : 23003.62,
  "symbol" : "MAGISTER-E"
}, {
  "date" : "2002-08-24",
  "value" : 23003.62,
  "symbol" : "MAGISTER-E"
}, {
  "date" : "2002-08-25",
  "value" : 23003.62,
  "symbol" : "MAGISTER-E"
}, {
  "date" : "2002-08-26",
  "value" : 23026.02,
  "symbol" : "MAGISTER-E"
}, {
  "date" : "2002-08-27",
  "value" : 23155.37,
  "symbol" : "MAGISTER-E"
}, {
  "date" : "2002-08-28",
  "value" : 23182.34,
  "symbol" : "MAGISTER-E"
}, {
  "date" : "2002-08-29",
  "value" : 23245.85,
  "symbol" : "MAGISTER-E"
}, {
  "date" : "2002-08-30",
  "value" : 23325.99,
  "symbol" : "MAGISTER-E"
}, {
  "date" : "2002-08-31",
  "value" : 23325.99,
  "symbol" : "MAGISTER-E"
}, {
  "date" : "2002-09-01",
  "value" : 23325.99,
  "symbol" : "MAGISTER-E"
}, {
  "date" : "2002-09-02",
  "value" : 23385.77,
  "symbol" : "MAGISTER-E"
}, {
  "date" : "2002-09-03",
  "value" : 23508.11,
  "symbol" : "MAGISTER-E"
}, {
  "date" : "2002-09-04",
  "value" : 23506.02,
  "symbol" : "MAGISTER-E"
}, {
  "date" : "2002-09-05",
  "value" : 23633.15,
  "symbol" : "MAGISTER-E"
}, {
  "date" : "2002-09-06",
  "value" : 23573.50,
  "symbol" : "MAGISTER-E"
}, {
  "date" : "2002-09-07",
  "value" : 23573.50,
  "symbol" : "MAGISTER-E"
}, {
  "date" : "2002-09-08",
  "value" : 23573.50,
  "symbol" : "MAGISTER-E"
}, {
  "date" : "2002-09-09",
  "value" : 23632.07,
  "symbol" : "MAGISTER-E"
}, {
  "date" : "2002-09-10",
  "value" : 23616.90,
  "symbol" : "MAGISTER-E"
}, {
  "date" : "2002-09-11",
  "value" : 23546.68,
  "symbol" : "MAGISTER-E"
}, {
  "date" : "2002-09-12",
  "value" : 23613.16,
  "symbol" : "MAGISTER-E"
}, {
  "date" : "2002-09-13",
  "value" : 23834.54,
  "symbol" : "MAGISTER-E"
}, {
  "date" : "2002-09-14",
  "value" : 23834.54,
  "symbol" : "MAGISTER-E"
}, {
  "date" : "2002-09-15",
  "value" : 23834.54,
  "symbol" : "MAGISTER-E"
}, {
  "date" : "2002-09-16",
  "value" : 23984.43,
  "symbol" : "MAGISTER-E"
}, {
  "date" : "2002-09-17",
  "value" : 23878.87,
  "symbol" : "MAGISTER-E"
}, {
  "date" : "2002-09-18",
  "value" : 23878.87,
  "symbol" : "MAGISTER-E"
}, {
  "date" : "2002-09-19",
  "value" : 23878.87,
  "symbol" : "MAGISTER-E"
}, {
  "date" : "2002-09-20",
  "value" : 23777.60,
  "symbol" : "MAGISTER-E"
}, {
  "date" : "2002-09-21",
  "value" : 23777.60,
  "symbol" : "MAGISTER-E"
}, {
  "date" : "2002-09-22",
  "value" : 23777.60,
  "symbol" : "MAGISTER-E"
}, {
  "date" : "2002-09-23",
  "value" : 23790.63,
  "symbol" : "MAGISTER-E"
}, {
  "date" : "2002-09-24",
  "value" : 23795.46,
  "symbol" : "MAGISTER-E"
}, {
  "date" : "2002-09-25",
  "value" : 23811.53,
  "symbol" : "MAGISTER-E"
}, {
  "date" : "2002-09-26",
  "value" : 23757.22,
  "symbol" : "MAGISTER-E"
}, {
  "date" : "2002-09-27",
  "value" : 23756.11,
  "symbol" : "MAGISTER-E"
}, {
  "date" : "2002-09-28",
  "value" : 23756.11,
  "symbol" : "MAGISTER-E"
}, {
  "date" : "2002-09-29",
  "value" : 23756.11,
  "symbol" : "MAGISTER-E"
}, {
  "date" : "2002-09-30",
  "value" : 23729.38,
  "symbol" : "MAGISTER-E"
}, {
  "date" : "2002-10-01",
  "value" : 23693.61,
  "symbol" : "MAGISTER-E"
}, {
  "date" : "2002-10-02",
  "value" : 23655.53,
  "symbol" : "MAGISTER-E"
}, {
  "date" : "2002-10-03",
  "value" : 23676.96,
  "symbol" : "MAGISTER-E"
}, {
  "date" : "2002-10-04",
  "value" : 23639.73,
  "symbol" : "MAGISTER-E"
}, {
  "date" : "2002-10-05",
  "value" : 23639.73,
  "symbol" : "MAGISTER-E"
}, {
  "date" : "2002-10-06",
  "value" : 23639.73,
  "symbol" : "MAGISTER-E"
}, {
  "date" : "2002-10-07",
  "value" : 23695.36,
  "symbol" : "MAGISTER-E"
}, {
  "date" : "2002-10-08",
  "value" : 23755.66,
  "symbol" : "MAGISTER-E"
}, {
  "date" : "2002-10-09",
  "value" : 23831.57,
  "symbol" : "MAGISTER-E"
}, {
  "date" : "2002-10-10",
  "value" : 23804.36,
  "symbol" : "MAGISTER-E"
}, {
  "date" : "2002-10-11",
  "value" : 23671.85,
  "symbol" : "MAGISTER-E"
}, {
  "date" : "2002-10-12",
  "value" : 23671.85,
  "symbol" : "MAGISTER-E"
}, {
  "date" : "2002-10-13",
  "value" : 23671.85,
  "symbol" : "MAGISTER-E"
}, {
  "date" : "2002-10-14",
  "value" : 23703.61,
  "symbol" : "MAGISTER-E"
}, {
  "date" : "2002-10-15",
  "value" : 23546.90,
  "symbol" : "MAGISTER-E"
}, {
  "date" : "2002-10-16",
  "value" : 23661.11,
  "symbol" : "MAGISTER-E"
}, {
  "date" : "2002-10-17",
  "value" : 23688.28,
  "symbol" : "MAGISTER-E"
}, {
  "date" : "2002-10-18",
  "value" : 23623.73,
  "symbol" : "MAGISTER-E"
}, {
  "date" : "2002-10-19",
  "value" : 23623.73,
  "symbol" : "MAGISTER-E"
}, {
  "date" : "2002-10-20",
  "value" : 23623.73,
  "symbol" : "MAGISTER-E"
}, {
  "date" : "2002-10-21",
  "value" : 23591.98,
  "symbol" : "MAGISTER-E"
}, {
  "date" : "2002-10-22",
  "value" : 23649.30,
  "symbol" : "MAGISTER-E"
}, {
  "date" : "2002-10-23",
  "value" : 23569.88,
  "symbol" : "MAGISTER-E"
}, {
  "date" : "2002-10-24",
  "value" : 23593.17,
  "symbol" : "MAGISTER-E"
}, {
  "date" : "2002-10-25",
  "value" : 23599.75,
  "symbol" : "MAGISTER-E"
}, {
  "date" : "2002-10-26",
  "value" : 23599.75,
  "symbol" : "MAGISTER-E"
}, {
  "date" : "2002-10-27",
  "value" : 23599.75,
  "symbol" : "MAGISTER-E"
}, {
  "date" : "2002-10-28",
  "value" : 23584.93,
  "symbol" : "MAGISTER-E"
}, {
  "date" : "2002-10-29",
  "value" : 23590.89,
  "symbol" : "MAGISTER-E"
}, {
  "date" : "2002-10-30",
  "value" : 23596.30,
  "symbol" : "MAGISTER-E"
}, {
  "date" : "2002-10-31",
  "value" : 23580.06,
  "symbol" : "MAGISTER-E"
}, {
  "date" : "2002-11-01",
  "value" : 23580.06,
  "symbol" : "MAGISTER-E"
}, {
  "date" : "2002-11-02",
  "value" : 23580.06,
  "symbol" : "MAGISTER-E"
}, {
  "date" : "2002-11-03",
  "value" : 23580.06,
  "symbol" : "MAGISTER-E"
}, {
  "date" : "2002-11-04",
  "value" : 23555.17,
  "symbol" : "MAGISTER-E"
}, {
  "date" : "2002-11-05",
  "value" : 23605.24,
  "symbol" : "MAGISTER-E"
}, {
  "date" : "2002-11-06",
  "value" : 23710.57,
  "symbol" : "MAGISTER-E"
}, {
  "date" : "2002-11-07",
  "value" : 23669.52,
  "symbol" : "MAGISTER-E"
}, {
  "date" : "2002-11-08",
  "value" : 23660.10,
  "symbol" : "MAGISTER-E"
}, {
  "date" : "2002-11-09",
  "value" : 23660.10,
  "symbol" : "MAGISTER-E"
}, {
  "date" : "2002-11-10",
  "value" : 23660.10,
  "symbol" : "MAGISTER-E"
}, {
  "date" : "2002-11-11",
  "value" : 23687.96,
  "symbol" : "MAGISTER-E"
}, {
  "date" : "2002-11-12",
  "value" : 23675.71,
  "symbol" : "MAGISTER-E"
}, {
  "date" : "2002-11-13",
  "value" : 23650.31,
  "symbol" : "MAGISTER-E"
}, {
  "date" : "2002-11-14",
  "value" : 23713.51,
  "symbol" : "MAGISTER-E"
}, {
  "date" : "2002-11-15",
  "value" : 23675.38,
  "symbol" : "MAGISTER-E"
}, {
  "date" : "2002-11-16",
  "value" : 23675.38,
  "symbol" : "MAGISTER-E"
}, {
  "date" : "2002-11-17",
  "value" : 23675.38,
  "symbol" : "MAGISTER-E"
}, {
  "date" : "2002-11-18",
  "value" : 23703.82,
  "symbol" : "MAGISTER-E"
}, {
  "date" : "2002-11-19",
  "value" : 23742.39,
  "symbol" : "MAGISTER-E"
}, {
  "date" : "2002-11-20",
  "value" : 23702.43,
  "symbol" : "MAGISTER-E"
}, {
  "date" : "2002-11-21",
  "value" : 23744.62,
  "symbol" : "MAGISTER-E"
}, {
  "date" : "2002-11-22",
  "value" : 23731.70,
  "symbol" : "MAGISTER-E"
}, {
  "date" : "2002-11-23",
  "value" : 23731.70,
  "symbol" : "MAGISTER-E"
}, {
  "date" : "2002-11-24",
  "value" : 23731.70,
  "symbol" : "MAGISTER-E"
}, {
  "date" : "2002-11-25",
  "value" : 23727.41,
  "symbol" : "MAGISTER-E"
}, {
  "date" : "2002-11-26",
  "value" : 23727.72,
  "symbol" : "MAGISTER-E"
}, {
  "date" : "2002-11-27",
  "value" : 23690.10,
  "symbol" : "MAGISTER-E"
}, {
  "date" : "2002-11-28",
  "value" : 23688.79,
  "symbol" : "MAGISTER-E"
}, {
  "date" : "2002-11-29",
  "value" : 23656.71,
  "symbol" : "MAGISTER-E"
}, {
  "date" : "2002-11-30",
  "value" : 23656.71,
  "symbol" : "MAGISTER-E"
}, {
  "date" : "2002-12-01",
  "value" : 23656.71,
  "symbol" : "MAGISTER-E"
}, {
  "date" : "2002-12-02",
  "value" : 23659.43,
  "symbol" : "MAGISTER-E"
}, {
  "date" : "2002-12-03",
  "value" : 23627.15,
  "symbol" : "MAGISTER-E"
}, {
  "date" : "2002-12-04",
  "value" : 23662.89,
  "symbol" : "MAGISTER-E"
}, {
  "date" : "2002-12-05",
  "value" : 23747.22,
  "symbol" : "MAGISTER-E"
}, {
  "date" : "2002-12-06",
  "value" : 23722.41,
  "symbol" : "MAGISTER-E"
}, {
  "date" : "2002-12-07",
  "value" : 23722.41,
  "symbol" : "MAGISTER-E"
}, {
  "date" : "2002-12-08",
  "value" : 23722.41,
  "symbol" : "MAGISTER-E"
}, {
  "date" : "2002-12-09",
  "value" : 23688.94,
  "symbol" : "MAGISTER-E"
}, {
  "date" : "2002-12-10",
  "value" : 23756.72,
  "symbol" : "MAGISTER-E"
}, {
  "date" : "2002-12-11",
  "value" : 23714.50,
  "symbol" : "MAGISTER-E"
}, {
  "date" : "2002-12-12",
  "value" : 23695.41,
  "symbol" : "MAGISTER-E"
}, {
  "date" : "2002-12-13",
  "value" : 23625.77,
  "symbol" : "MAGISTER-E"
}, {
  "date" : "2002-12-14",
  "value" : 23625.77,
  "symbol" : "MAGISTER-E"
}, {
  "date" : "2002-12-15",
  "value" : 23625.77,
  "symbol" : "MAGISTER-E"
}, {
  "date" : "2002-12-16",
  "value" : 23700.81,
  "symbol" : "MAGISTER-E"
}, {
  "date" : "2002-12-17",
  "value" : 23673.17,
  "symbol" : "MAGISTER-E"
}, {
  "date" : "2002-12-18",
  "value" : 23665.09,
  "symbol" : "MAGISTER-E"
}, {
  "date" : "2002-12-19",
  "value" : 23700.10,
  "symbol" : "MAGISTER-E"
}, {
  "date" : "2002-12-20",
  "value" : 23704.87,
  "symbol" : "MAGISTER-E"
}, {
  "date" : "2002-12-21",
  "value" : 23704.87,
  "symbol" : "MAGISTER-E"
}, {
  "date" : "2002-12-22",
  "value" : 23704.87,
  "symbol" : "MAGISTER-E"
}, {
  "date" : "2002-12-23",
  "value" : 23690.75,
  "symbol" : "MAGISTER-E"
}, {
  "date" : "2002-12-24",
  "value" : 23731.46,
  "symbol" : "MAGISTER-E"
}, {
  "date" : "2002-12-25",
  "value" : 23731.46,
  "symbol" : "MAGISTER-E"
}, {
  "date" : "2002-12-26",
  "value" : 23749.38,
  "symbol" : "MAGISTER-E"
}, {
  "date" : "2002-12-27",
  "value" : 23818.51,
  "symbol" : "MAGISTER-E"
}, {
  "date" : "2002-12-28",
  "value" : 23818.51,
  "symbol" : "MAGISTER-E"
}, {
  "date" : "2002-12-29",
  "value" : 23818.51,
  "symbol" : "MAGISTER-E"
}, {
  "date" : "2002-12-30",
  "value" : 23841.87,
  "symbol" : "MAGISTER-E"
}, {
  "date" : "2002-12-31",
  "value" : 23865.63,
  "symbol" : "MAGISTER-E"
}, {
  "date" : "2003-01-01",
  "value" : 23865.63,
  "symbol" : "MAGISTER-E"
}, {
  "date" : "2003-01-02",
  "value" : 23907.28,
  "symbol" : "MAGISTER-E"
}, {
  "date" : "2003-01-03",
  "value" : 23835.75,
  "symbol" : "MAGISTER-E"
}, {
  "date" : "2003-01-04",
  "value" : 23835.75,
  "symbol" : "MAGISTER-E"
}, {
  "date" : "2003-01-05",
  "value" : 23835.75,
  "symbol" : "MAGISTER-E"
}, {
  "date" : "2003-01-06",
  "value" : 23764.24,
  "symbol" : "MAGISTER-E"
}, {
  "date" : "2003-01-07",
  "value" : 23718.01,
  "symbol" : "MAGISTER-E"
}, {
  "date" : "2003-01-08",
  "value" : 23830.52,
  "symbol" : "MAGISTER-E"
}, {
  "date" : "2003-01-09",
  "value" : 23783.53,
  "symbol" : "MAGISTER-E"
}, {
  "date" : "2003-01-10",
  "value" : 23853.89,
  "symbol" : "MAGISTER-E"
}, {
  "date" : "2003-01-11",
  "value" : 23853.89,
  "symbol" : "MAGISTER-E"
}, {
  "date" : "2003-01-12",
  "value" : 23853.89,
  "symbol" : "MAGISTER-E"
}, {
  "date" : "2003-01-13",
  "value" : 23852.63,
  "symbol" : "MAGISTER-E"
}, {
  "date" : "2003-01-14",
  "value" : 23838.24,
  "symbol" : "MAGISTER-E"
}, {
  "date" : "2003-01-15",
  "value" : 23855.68,
  "symbol" : "MAGISTER-E"
}, {
  "date" : "2003-01-16",
  "value" : 23922.55,
  "symbol" : "MAGISTER-E"
}, {
  "date" : "2003-01-17",
  "value" : 23936.95,
  "symbol" : "MAGISTER-E"
}, {
  "date" : "2003-01-18",
  "value" : 23936.95,
  "symbol" : "MAGISTER-E"
}, {
  "date" : "2003-01-19",
  "value" : 23936.95,
  "symbol" : "MAGISTER-E"
}, {
  "date" : "2003-01-20",
  "value" : 23995.91,
  "symbol" : "MAGISTER-E"
}, {
  "date" : "2003-01-21",
  "value" : 23914.94,
  "symbol" : "MAGISTER-E"
}, {
  "date" : "2003-01-22",
  "value" : 23966.42,
  "symbol" : "MAGISTER-E"
}, {
  "date" : "2003-01-23",
  "value" : 23970.55,
  "symbol" : "MAGISTER-E"
}, {
  "date" : "2003-01-24",
  "value" : 23909.75,
  "symbol" : "MAGISTER-E"
}, {
  "date" : "2003-01-25",
  "value" : 23909.75,
  "symbol" : "MAGISTER-E"
}, {
  "date" : "2003-01-26",
  "value" : 23909.75,
  "symbol" : "MAGISTER-E"
}, {
  "date" : "2003-01-27",
  "value" : 23981.15,
  "symbol" : "MAGISTER-E"
}, {
  "date" : "2003-01-28",
  "value" : 23984.94,
  "symbol" : "MAGISTER-E"
}, {
  "date" : "2003-01-29",
  "value" : 23978.89,
  "symbol" : "MAGISTER-E"
}, {
  "date" : "2003-01-30",
  "value" : 23945.67,
  "symbol" : "MAGISTER-E"
}, {
  "date" : "2003-01-31",
  "value" : 23882.67,
  "symbol" : "MAGISTER-E"
}, {
  "date" : "2003-02-01",
  "value" : 23882.67,
  "symbol" : "MAGISTER-E"
}, {
  "date" : "2003-02-02",
  "value" : 23882.67,
  "symbol" : "MAGISTER-E"
}, {
  "date" : "2003-02-03",
  "value" : 23924.87,
  "symbol" : "MAGISTER-E"
}, {
  "date" : "2003-02-04",
  "value" : 23901.32,
  "symbol" : "MAGISTER-E"
}, {
  "date" : "2003-02-05",
  "value" : 24034.57,
  "symbol" : "MAGISTER-E"
}, {
  "date" : "2003-02-06",
  "value" : 24040.68,
  "symbol" : "MAGISTER-E"
}, {
  "date" : "2003-02-07",
  "value" : 23966.31,
  "symbol" : "MAGISTER-E"
}, {
  "date" : "2003-02-08",
  "value" : 23966.31,
  "symbol" : "MAGISTER-E"
}, {
  "date" : "2003-02-09",
  "value" : 23966.31,
  "symbol" : "MAGISTER-E"
}, {
  "date" : "2003-02-10",
  "value" : 23975.93,
  "symbol" : "MAGISTER-E"
}, {
  "date" : "2003-02-11",
  "value" : 24003.41,
  "symbol" : "MAGISTER-E"
}, {
  "date" : "2003-02-12",
  "value" : 23968.78,
  "symbol" : "MAGISTER-E"
}, {
  "date" : "2003-02-13",
  "value" : 24025.25,
  "symbol" : "MAGISTER-E"
}, {
  "date" : "2003-02-14",
  "value" : 23957.66,
  "symbol" : "MAGISTER-E"
}, {
  "date" : "2003-02-15",
  "value" : 23957.66,
  "symbol" : "MAGISTER-E"
}, {
  "date" : "2003-02-16",
  "value" : 23957.66,
  "symbol" : "MAGISTER-E"
}, {
  "date" : "2003-02-17",
  "value" : 23977.40,
  "symbol" : "MAGISTER-E"
}, {
  "date" : "2003-02-18",
  "value" : 23941.80,
  "symbol" : "MAGISTER-E"
}, {
  "date" : "2003-02-19",
  "value" : 24001.32,
  "symbol" : "MAGISTER-E"
}, {
  "date" : "2003-02-20",
  "value" : 24052.31,
  "symbol" : "MAGISTER-E"
}, {
  "date" : "2003-02-21",
  "value" : 24057.80,
  "symbol" : "MAGISTER-E"
}, {
  "date" : "2003-02-22",
  "value" : 24057.80,
  "symbol" : "MAGISTER-E"
}, {
  "date" : "2003-02-23",
  "value" : 24057.80,
  "symbol" : "MAGISTER-E"
}, {
  "date" : "2003-02-24",
  "value" : 24105.50,
  "symbol" : "MAGISTER-E"
}, {
  "date" : "2003-02-25",
  "value" : 24091.87,
  "symbol" : "MAGISTER-E"
}, {
  "date" : "2003-02-26",
  "value" : 24092.04,
  "symbol" : "MAGISTER-E"
}, {
  "date" : "2003-02-27",
  "value" : 24087.18,
  "symbol" : "MAGISTER-E"
}, {
  "date" : "2003-02-28",
  "value" : 24148.94,
  "symbol" : "MAGISTER-E"
}, {
  "date" : "2003-03-01",
  "value" : 24148.94,
  "symbol" : "MAGISTER-E"
}, {
  "date" : "2003-03-02",
  "value" : 24148.94,
  "symbol" : "MAGISTER-E"
}, {
  "date" : "2003-03-03",
  "value" : 24146.17,
  "symbol" : "MAGISTER-E"
}, {
  "date" : "2003-03-04",
  "value" : 24151.47,
  "symbol" : "MAGISTER-E"
}, {
  "date" : "2003-03-05",
  "value" : 24274.38,
  "symbol" : "MAGISTER-E"
}, {
  "date" : "2003-03-06",
  "value" : 24289.36,
  "symbol" : "MAGISTER-E"
}, {
  "date" : "2003-03-07",
  "value" : 24337.76,
  "symbol" : "MAGISTER-E"
}, {
  "date" : "2003-03-08",
  "value" : 24337.76,
  "symbol" : "MAGISTER-E"
}, {
  "date" : "2003-03-09",
  "value" : 24337.76,
  "symbol" : "MAGISTER-E"
}, {
  "date" : "2003-03-10",
  "value" : 24372.82,
  "symbol" : "MAGISTER-E"
}, {
  "date" : "2003-03-11",
  "value" : 24395.62,
  "symbol" : "MAGISTER-E"
}, {
  "date" : "2003-03-12",
  "value" : 24324.74,
  "symbol" : "MAGISTER-E"
}, {
  "date" : "2003-03-13",
  "value" : 24280.45,
  "symbol" : "MAGISTER-E"
}, {
  "date" : "2003-03-14",
  "value" : 24234.71,
  "symbol" : "MAGISTER-E"
}, {
  "date" : "2003-03-15",
  "value" : 24234.71,
  "symbol" : "MAGISTER-E"
}, {
  "date" : "2003-03-16",
  "value" : 24234.71,
  "symbol" : "MAGISTER-E"
}, {
  "date" : "2003-03-17",
  "value" : 24232.33,
  "symbol" : "MAGISTER-E"
}, {
  "date" : "2003-03-18",
  "value" : 24263.70,
  "symbol" : "MAGISTER-E"
}, {
  "date" : "2003-03-19",
  "value" : 24228.25,
  "symbol" : "MAGISTER-E"
}, {
  "date" : "2003-03-20",
  "value" : 24233.24,
  "symbol" : "MAGISTER-E"
}, {
  "date" : "2003-03-21",
  "value" : 24265.41,
  "symbol" : "MAGISTER-E"
}, {
  "date" : "2003-03-22",
  "value" : 24265.41,
  "symbol" : "MAGISTER-E"
}, {
  "date" : "2003-03-23",
  "value" : 24265.41,
  "symbol" : "MAGISTER-E"
}, {
  "date" : "2003-03-24",
  "value" : 24109.10,
  "symbol" : "MAGISTER-E"
}, {
  "date" : "2003-03-25",
  "value" : 24198.95,
  "symbol" : "MAGISTER-E"
}, {
  "date" : "2003-03-26",
  "value" : 24177.75,
  "symbol" : "MAGISTER-E"
}, {
  "date" : "2003-03-27",
  "value" : 24269.30,
  "symbol" : "MAGISTER-E"
}, {
  "date" : "2003-03-28",
  "value" : 24375.32,
  "symbol" : "MAGISTER-E"
}, {
  "date" : "2003-03-29",
  "value" : 24375.32,
  "symbol" : "MAGISTER-E"
}, {
  "date" : "2003-03-30",
  "value" : 24375.32,
  "symbol" : "MAGISTER-E"
}, {
  "date" : "2003-03-31",
  "value" : 24307.04,
  "symbol" : "MAGISTER-E"
}, {
  "date" : "2003-04-01",
  "value" : 24404.38,
  "symbol" : "MAGISTER-E"
}, {
  "date" : "2003-04-02",
  "value" : 24387.41,
  "symbol" : "MAGISTER-E"
}, {
  "date" : "2003-04-03",
  "value" : 24269.59,
  "symbol" : "MAGISTER-E"
}, {
  "date" : "2003-04-04",
  "value" : 24391.02,
  "symbol" : "MAGISTER-E"
}, {
  "date" : "2003-04-05",
  "value" : 24391.02,
  "symbol" : "MAGISTER-E"
}, {
  "date" : "2003-04-06",
  "value" : 24391.02,
  "symbol" : "MAGISTER-E"
}, {
  "date" : "2003-04-07",
  "value" : 24351.05,
  "symbol" : "MAGISTER-E"
}, {
  "date" : "2003-04-08",
  "value" : 24273.68,
  "symbol" : "MAGISTER-E"
}, {
  "date" : "2003-04-09",
  "value" : 24352.57,
  "symbol" : "MAGISTER-E"
}, {
  "date" : "2003-04-10",
  "value" : 24378.90,
  "symbol" : "MAGISTER-E"
}, {
  "date" : "2003-04-11",
  "value" : 24400.68,
  "symbol" : "MAGISTER-E"
}, {
  "date" : "2003-04-12",
  "value" : 24400.68,
  "symbol" : "MAGISTER-E"
}, {
  "date" : "2003-04-13",
  "value" : 24400.68,
  "symbol" : "MAGISTER-E"
}, {
  "date" : "2003-04-14",
  "value" : 24402.63,
  "symbol" : "MAGISTER-E"
}, {
  "date" : "2003-04-15",
  "value" : 24447.81,
  "symbol" : "MAGISTER-E"
}, {
  "date" : "2003-04-16",
  "value" : 24354.68,
  "symbol" : "MAGISTER-E"
}, {
  "date" : "2003-04-17",
  "value" : 24375.99,
  "symbol" : "MAGISTER-E"
}, {
  "date" : "2003-04-18",
  "value" : 24375.99,
  "symbol" : "MAGISTER-E"
}, {
  "date" : "2003-04-19",
  "value" : 24375.99,
  "symbol" : "MAGISTER-E"
}, {
  "date" : "2003-04-20",
  "value" : 24375.99,
  "symbol" : "MAGISTER-E"
}, {
  "date" : "2003-04-21",
  "value" : 24393.06,
  "symbol" : "MAGISTER-E"
}, {
  "date" : "2003-04-22",
  "value" : 24412.90,
  "symbol" : "MAGISTER-E"
}, {
  "date" : "2003-04-23",
  "value" : 24452.79,
  "symbol" : "MAGISTER-E"
}, {
  "date" : "2003-04-24",
  "value" : 24393.47,
  "symbol" : "MAGISTER-E"
}, {
  "date" : "2003-04-25",
  "value" : 24378.54,
  "symbol" : "MAGISTER-E"
}, {
  "date" : "2003-04-26",
  "value" : 24378.54,
  "symbol" : "MAGISTER-E"
}, {
  "date" : "2003-04-27",
  "value" : 24378.54,
  "symbol" : "MAGISTER-E"
}, {
  "date" : "2003-04-28",
  "value" : 24452.87,
  "symbol" : "MAGISTER-E"
}, {
  "date" : "2003-04-29",
  "value" : 24484.60,
  "symbol" : "MAGISTER-E"
}, {
  "date" : "2003-04-30",
  "value" : 24414.27,
  "symbol" : "MAGISTER-E"
}, {
  "date" : "2003-05-01",
  "value" : 24414.27,
  "symbol" : "MAGISTER-E"
}, {
  "date" : "2003-05-02",
  "value" : 24449.61,
  "symbol" : "MAGISTER-E"
}, {
  "date" : "2003-05-03",
  "value" : 24449.61,
  "symbol" : "MAGISTER-E"
}, {
  "date" : "2003-05-04",
  "value" : 24449.61,
  "symbol" : "MAGISTER-E"
}, {
  "date" : "2003-05-05",
  "value" : 24447.64,
  "symbol" : "MAGISTER-E"
}, {
  "date" : "2003-05-06",
  "value" : 24447.00,
  "symbol" : "MAGISTER-E"
}, {
  "date" : "2003-05-07",
  "value" : 24451.66,
  "symbol" : "MAGISTER-E"
}, {
  "date" : "2003-05-08",
  "value" : 24422.58,
  "symbol" : "MAGISTER-E"
}, {
  "date" : "2003-05-09",
  "value" : 24455.13,
  "symbol" : "MAGISTER-E"
}, {
  "date" : "2003-05-10",
  "value" : 24455.13,
  "symbol" : "MAGISTER-E"
}, {
  "date" : "2003-05-11",
  "value" : 24455.13,
  "symbol" : "MAGISTER-E"
}, {
  "date" : "2003-05-12",
  "value" : 24455.39,
  "symbol" : "MAGISTER-E"
}, {
  "date" : "2003-05-13",
  "value" : 24426.85,
  "symbol" : "MAGISTER-E"
}, {
  "date" : "2003-05-14",
  "value" : 24383.31,
  "symbol" : "MAGISTER-E"
}, {
  "date" : "2003-05-15",
  "value" : 24457.19,
  "symbol" : "MAGISTER-E"
}, {
  "date" : "2003-05-16",
  "value" : 24491.66,
  "symbol" : "MAGISTER-E"
}, {
  "date" : "2003-05-17",
  "value" : 24491.66,
  "symbol" : "MAGISTER-E"
}, {
  "date" : "2003-05-18",
  "value" : 24491.66,
  "symbol" : "MAGISTER-E"
}, {
  "date" : "2003-05-19",
  "value" : 24474.11,
  "symbol" : "MAGISTER-E"
}, {
  "date" : "2003-05-20",
  "value" : 24481.69,
  "symbol" : "MAGISTER-E"
}, {
  "date" : "2003-05-21",
  "value" : 24481.69,
  "symbol" : "MAGISTER-E"
}, {
  "date" : "2003-05-22",
  "value" : 24521.72,
  "symbol" : "MAGISTER-E"
}, {
  "date" : "2003-05-23",
  "value" : 24498.68,
  "symbol" : "MAGISTER-E"
}, {
  "date" : "2003-05-24",
  "value" : 24498.68,
  "symbol" : "MAGISTER-E"
}, {
  "date" : "2003-05-25",
  "value" : 24498.68,
  "symbol" : "MAGISTER-E"
}, {
  "date" : "2003-05-26",
  "value" : 24518.66,
  "symbol" : "MAGISTER-E"
}, {
  "date" : "2003-05-27",
  "value" : 24546.52,
  "symbol" : "MAGISTER-E"
}, {
  "date" : "2003-05-28",
  "value" : 24575.17,
  "symbol" : "MAGISTER-E"
}, {
  "date" : "2003-05-29",
  "value" : 24547.58,
  "symbol" : "MAGISTER-E"
}, {
  "date" : "2003-05-30",
  "value" : 24525.86,
  "symbol" : "MAGISTER-E"
}, {
  "date" : "2003-05-31",
  "value" : 24525.86,
  "symbol" : "MAGISTER-E"
}, {
  "date" : "2003-06-01",
  "value" : 24525.86,
  "symbol" : "MAGISTER-E"
}, {
  "date" : "2003-06-02",
  "value" : 24550.41,
  "symbol" : "MAGISTER-E"
}, {
  "date" : "2003-06-03",
  "value" : 24472.80,
  "symbol" : "MAGISTER-E"
}, {
  "date" : "2003-06-04",
  "value" : 24514.86,
  "symbol" : "MAGISTER-E"
}, {
  "date" : "2003-06-05",
  "value" : 24522.22,
  "symbol" : "MAGISTER-E"
}, {
  "date" : "2003-06-06",
  "value" : 24584.06,
  "symbol" : "MAGISTER-E"
}, {
  "date" : "2003-06-07",
  "value" : 24584.06,
  "symbol" : "MAGISTER-E"
}, {
  "date" : "2003-06-08",
  "value" : 24584.06,
  "symbol" : "MAGISTER-E"
}, {
  "date" : "2003-06-09",
  "value" : 24551.56,
  "symbol" : "MAGISTER-E"
}, {
  "date" : "2003-06-10",
  "value" : 24591.50,
  "symbol" : "MAGISTER-E"
}, {
  "date" : "2003-06-11",
  "value" : 24595.62,
  "symbol" : "MAGISTER-E"
}, {
  "date" : "2003-06-12",
  "value" : 24602.69,
  "symbol" : "MAGISTER-E"
}, {
  "date" : "2003-06-13",
  "value" : 24531.72,
  "symbol" : "MAGISTER-E"
}, {
  "date" : "2003-06-14",
  "value" : 24531.72,
  "symbol" : "MAGISTER-E"
}, {
  "date" : "2003-06-15",
  "value" : 24531.72,
  "symbol" : "MAGISTER-E"
}, {
  "date" : "2003-06-16",
  "value" : 24531.72,
  "symbol" : "MAGISTER-E"
}, {
  "date" : "2003-06-17",
  "value" : 24527.00,
  "symbol" : "MAGISTER-E"
}, {
  "date" : "2003-06-18",
  "value" : 24533.19,
  "symbol" : "MAGISTER-E"
}, {
  "date" : "2003-06-19",
  "value" : 24541.55,
  "symbol" : "MAGISTER-E"
}, {
  "date" : "2003-06-20",
  "value" : 24540.81,
  "symbol" : "MAGISTER-E"
}, {
  "date" : "2003-06-21",
  "value" : 24540.81,
  "symbol" : "MAGISTER-E"
}, {
  "date" : "2003-06-22",
  "value" : 24540.81,
  "symbol" : "MAGISTER-E"
}, {
  "date" : "2003-06-23",
  "value" : 24521.34,
  "symbol" : "MAGISTER-E"
}, {
  "date" : "2003-06-24",
  "value" : 24516.68,
  "symbol" : "MAGISTER-E"
}, {
  "date" : "2003-06-25",
  "value" : 24519.83,
  "symbol" : "MAGISTER-E"
}, {
  "date" : "2003-06-26",
  "value" : 24560.21,
  "symbol" : "MAGISTER-E"
}, {
  "date" : "2003-06-27",
  "value" : 24520.55,
  "symbol" : "MAGISTER-E"
}, {
  "date" : "2003-06-28",
  "value" : 24520.55,
  "symbol" : "MAGISTER-E"
}, {
  "date" : "2003-06-29",
  "value" : 24520.55,
  "symbol" : "MAGISTER-E"
}, {
  "date" : "2003-06-30",
  "value" : 24480.05,
  "symbol" : "MAGISTER-E"
}, {
  "date" : "2003-07-01",
  "value" : 24517.44,
  "symbol" : "MAGISTER-E"
}, {
  "date" : "2003-07-02",
  "value" : 24511.68,
  "symbol" : "MAGISTER-E"
}, {
  "date" : "2003-07-03",
  "value" : 24501.05,
  "symbol" : "MAGISTER-E"
}, {
  "date" : "2003-07-04",
  "value" : 24498.35,
  "symbol" : "MAGISTER-E"
}, {
  "date" : "2003-07-05",
  "value" : 24498.35,
  "symbol" : "MAGISTER-E"
}, {
  "date" : "2003-07-06",
  "value" : 24498.35,
  "symbol" : "MAGISTER-E"
}, {
  "date" : "2003-07-07",
  "value" : 24524.53,
  "symbol" : "MAGISTER-E"
}, {
  "date" : "2003-07-08",
  "value" : 24553.06,
  "symbol" : "MAGISTER-E"
}, {
  "date" : "2003-07-09",
  "value" : 24570.43,
  "symbol" : "MAGISTER-E"
}, {
  "date" : "2003-07-10",
  "value" : 24569.94,
  "symbol" : "MAGISTER-E"
}, {
  "date" : "2003-07-11",
  "value" : 24608.98,
  "symbol" : "MAGISTER-E"
}, {
  "date" : "2003-07-12",
  "value" : 24608.98,
  "symbol" : "MAGISTER-E"
}, {
  "date" : "2003-07-13",
  "value" : 24608.98,
  "symbol" : "MAGISTER-E"
}, {
  "date" : "2003-07-14",
  "value" : 24624.95,
  "symbol" : "MAGISTER-E"
}, {
  "date" : "2003-07-15",
  "value" : 24633.79,
  "symbol" : "MAGISTER-E"
}, {
  "date" : "2003-07-16",
  "value" : 24646.05,
  "symbol" : "MAGISTER-E"
}, {
  "date" : "2003-07-17",
  "value" : 24646.17,
  "symbol" : "MAGISTER-E"
}, {
  "date" : "2003-07-18",
  "value" : 24640.34,
  "symbol" : "MAGISTER-E"
}, {
  "date" : "2003-07-19",
  "value" : 24640.34,
  "symbol" : "MAGISTER-E"
}, {
  "date" : "2003-07-20",
  "value" : 24640.34,
  "symbol" : "MAGISTER-E"
}, {
  "date" : "2003-07-21",
  "value" : 24666.85,
  "symbol" : "MAGISTER-E"
}, {
  "date" : "2003-07-22",
  "value" : 24662.90,
  "symbol" : "MAGISTER-E"
}, {
  "date" : "2003-07-23",
  "value" : 24671.87,
  "symbol" : "MAGISTER-E"
}, {
  "date" : "2003-07-24",
  "value" : 24718.50,
  "symbol" : "MAGISTER-E"
}, {
  "date" : "2003-07-25",
  "value" : 24708.08,
  "symbol" : "MAGISTER-E"
}, {
  "date" : "2003-07-26",
  "value" : 24708.08,
  "symbol" : "MAGISTER-E"
}, {
  "date" : "2003-07-27",
  "value" : 24708.08,
  "symbol" : "MAGISTER-E"
}, {
  "date" : "2003-07-28",
  "value" : 24755.17,
  "symbol" : "MAGISTER-E"
}, {
  "date" : "2003-07-29",
  "value" : 24743.92,
  "symbol" : "MAGISTER-E"
}, {
  "date" : "2003-07-30",
  "value" : 24796.03,
  "symbol" : "MAGISTER-E"
}, {
  "date" : "2003-07-31",
  "value" : 24764.05,
  "symbol" : "MAGISTER-E"
}, {
  "date" : "2003-08-01",
  "value" : 24750.27,
  "symbol" : "MAGISTER-E"
}, {
  "date" : "2003-08-02",
  "value" : 24750.27,
  "symbol" : "MAGISTER-E"
}, {
  "date" : "2003-08-03",
  "value" : 24750.27,
  "symbol" : "MAGISTER-E"
}, {
  "date" : "2003-08-04",
  "value" : 24770.76,
  "symbol" : "MAGISTER-E"
}, {
  "date" : "2003-08-05",
  "value" : 24849.65,
  "symbol" : "MAGISTER-E"
}, {
  "date" : "2003-08-06",
  "value" : 24814.84,
  "symbol" : "MAGISTER-E"
}, {
  "date" : "2003-08-07",
  "value" : 24750.82,
  "symbol" : "MAGISTER-E"
}, {
  "date" : "2003-08-08",
  "value" : 24752.36,
  "symbol" : "MAGISTER-E"
}, {
  "date" : "2003-08-09",
  "value" : 24752.36,
  "symbol" : "MAGISTER-E"
}, {
  "date" : "2003-08-10",
  "value" : 24752.36,
  "symbol" : "MAGISTER-E"
}, {
  "date" : "2003-08-11",
  "value" : 24754.52,
  "symbol" : "MAGISTER-E"
}, {
  "date" : "2003-08-12",
  "value" : 24750.60,
  "symbol" : "MAGISTER-E"
}, {
  "date" : "2003-08-13",
  "value" : 24773.07,
  "symbol" : "MAGISTER-E"
}, {
  "date" : "2003-08-14",
  "value" : 24803.28,
  "symbol" : "MAGISTER-E"
}, {
  "date" : "2003-08-15",
  "value" : 24803.28,
  "symbol" : "MAGISTER-E"
}, {
  "date" : "2003-08-16",
  "value" : 24803.28,
  "symbol" : "MAGISTER-E"
}, {
  "date" : "2003-08-17",
  "value" : 24803.28,
  "symbol" : "MAGISTER-E"
}, {
  "date" : "2003-08-18",
  "value" : 24723.72,
  "symbol" : "MAGISTER-E"
}, {
  "date" : "2003-08-19",
  "value" : 24728.99,
  "symbol" : "MAGISTER-E"
}, {
  "date" : "2003-08-20",
  "value" : 24773.21,
  "symbol" : "MAGISTER-E"
}, {
  "date" : "2003-08-21",
  "value" : 24735.63,
  "symbol" : "MAGISTER-E"
}, {
  "date" : "2003-08-22",
  "value" : 24766.37,
  "symbol" : "MAGISTER-E"
}, {
  "date" : "2003-08-23",
  "value" : 24766.37,
  "symbol" : "MAGISTER-E"
}, {
  "date" : "2003-08-24",
  "value" : 24766.37,
  "symbol" : "MAGISTER-E"
}, {
  "date" : "2003-08-25",
  "value" : 24764.30,
  "symbol" : "MAGISTER-E"
}, {
  "date" : "2003-08-26",
  "value" : 24733.85,
  "symbol" : "MAGISTER-E"
}, {
  "date" : "2003-08-27",
  "value" : 24739.44,
  "symbol" : "MAGISTER-E"
}, {
  "date" : "2003-08-28",
  "value" : 24760.87,
  "symbol" : "MAGISTER-E"
}, {
  "date" : "2003-08-29",
  "value" : 24719.81,
  "symbol" : "MAGISTER-E"
}, {
  "date" : "2003-08-30",
  "value" : 24719.81,
  "symbol" : "MAGISTER-E"
}, {
  "date" : "2003-08-31",
  "value" : 24719.81,
  "symbol" : "MAGISTER-E"
}, {
  "date" : "2003-09-01",
  "value" : 24748.91,
  "symbol" : "MAGISTER-E"
}, {
  "date" : "2003-09-02",
  "value" : 24696.31,
  "symbol" : "MAGISTER-E"
}, {
  "date" : "2003-09-03",
  "value" : 24694.06,
  "symbol" : "MAGISTER-E"
}, {
  "date" : "2003-09-04",
  "value" : 24659.94,
  "symbol" : "MAGISTER-E"
}, {
  "date" : "2003-09-05",
  "value" : 24622.81,
  "symbol" : "MAGISTER-E"
}, {
  "date" : "2003-09-06",
  "value" : 24622.81,
  "symbol" : "MAGISTER-E"
}, {
  "date" : "2003-09-07",
  "value" : 24622.81,
  "symbol" : "MAGISTER-E"
}, {
  "date" : "2003-09-08",
  "value" : 24656.51,
  "symbol" : "MAGISTER-E"
}, {
  "date" : "2003-09-09",
  "value" : 24725.72,
  "symbol" : "MAGISTER-E"
}, {
  "date" : "2003-09-10",
  "value" : 24744.08,
  "symbol" : "MAGISTER-E"
}, {
  "date" : "2003-09-11",
  "value" : 24690.10,
  "symbol" : "MAGISTER-E"
}, {
  "date" : "2003-09-12",
  "value" : 24646.06,
  "symbol" : "MAGISTER-E"
}, {
  "date" : "2003-09-13",
  "value" : 24646.06,
  "symbol" : "MAGISTER-E"
}, {
  "date" : "2003-09-14",
  "value" : 24646.06,
  "symbol" : "MAGISTER-E"
}, {
  "date" : "2003-09-15",
  "value" : 24602.11,
  "symbol" : "MAGISTER-E"
}, {
  "date" : "2003-09-16",
  "value" : 24623.50,
  "symbol" : "MAGISTER-E"
}, {
  "date" : "2003-09-17",
  "value" : 24612.80,
  "symbol" : "MAGISTER-E"
}, {
  "date" : "2003-09-18",
  "value" : 24612.80,
  "symbol" : "MAGISTER-E"
}, {
  "date" : "2003-09-19",
  "value" : 24612.80,
  "symbol" : "MAGISTER-E"
}, {
  "date" : "2003-09-20",
  "value" : 24612.80,
  "symbol" : "MAGISTER-E"
}, {
  "date" : "2003-09-21",
  "value" : 24612.80,
  "symbol" : "MAGISTER-E"
}, {
  "date" : "2003-09-22",
  "value" : 24626.64,
  "symbol" : "MAGISTER-E"
}, {
  "date" : "2003-09-23",
  "value" : 24613.82,
  "symbol" : "MAGISTER-E"
}, {
  "date" : "2003-09-24",
  "value" : 24604.45,
  "symbol" : "MAGISTER-E"
}, {
  "date" : "2003-09-25",
  "value" : 24646.46,
  "symbol" : "MAGISTER-E"
}, {
  "date" : "2003-09-26",
  "value" : 24648.21,
  "symbol" : "MAGISTER-E"
}, {
  "date" : "2003-09-27",
  "value" : 24648.21,
  "symbol" : "MAGISTER-E"
}, {
  "date" : "2003-09-28",
  "value" : 24648.21,
  "symbol" : "MAGISTER-E"
}, {
  "date" : "2003-09-29",
  "value" : 24667.55,
  "symbol" : "MAGISTER-E"
}, {
  "date" : "2003-09-30",
  "value" : 24597.18,
  "symbol" : "MAGISTER-E"
}, {
  "date" : "2003-10-01",
  "value" : 24499.35,
  "symbol" : "MAGISTER-E"
}, {
  "date" : "2003-10-02",
  "value" : 24504.74,
  "symbol" : "MAGISTER-E"
}, {
  "date" : "2003-10-03",
  "value" : 24581.61,
  "symbol" : "MAGISTER-E"
}, {
  "date" : "2003-10-04",
  "value" : 24581.61,
  "symbol" : "MAGISTER-E"
}, {
  "date" : "2003-10-05",
  "value" : 24581.61,
  "symbol" : "MAGISTER-E"
}, {
  "date" : "2003-10-06",
  "value" : 24537.55,
  "symbol" : "MAGISTER-E"
}, {
  "date" : "2003-10-07",
  "value" : 24550.41,
  "symbol" : "MAGISTER-E"
}, {
  "date" : "2003-10-08",
  "value" : 24515.21,
  "symbol" : "MAGISTER-E"
}, {
  "date" : "2003-10-09",
  "value" : 24471.80,
  "symbol" : "MAGISTER-E"
}, {
  "date" : "2003-10-10",
  "value" : 24549.42,
  "symbol" : "MAGISTER-E"
}, {
  "date" : "2003-10-11",
  "value" : 24549.42,
  "symbol" : "MAGISTER-E"
}, {
  "date" : "2003-10-12",
  "value" : 24549.42,
  "symbol" : "MAGISTER-E"
}, {
  "date" : "2003-10-13",
  "value" : 24605.54,
  "symbol" : "MAGISTER-E"
}, {
  "date" : "2003-10-14",
  "value" : 24612.47,
  "symbol" : "MAGISTER-E"
}, {
  "date" : "2003-10-15",
  "value" : 24716.13,
  "symbol" : "MAGISTER-E"
}, {
  "date" : "2003-10-16",
  "value" : 24791.55,
  "symbol" : "MAGISTER-E"
}, {
  "date" : "2003-10-17",
  "value" : 24732.23,
  "symbol" : "MAGISTER-E"
}, {
  "date" : "2003-10-18",
  "value" : 24732.23,
  "symbol" : "MAGISTER-E"
}, {
  "date" : "2003-10-19",
  "value" : 24732.23,
  "symbol" : "MAGISTER-E"
}, {
  "date" : "2003-10-20",
  "value" : 24746.28,
  "symbol" : "MAGISTER-E"
}, {
  "date" : "2003-10-21",
  "value" : 24729.44,
  "symbol" : "MAGISTER-E"
}, {
  "date" : "2003-10-22",
  "value" : 24755.88,
  "symbol" : "MAGISTER-E"
}, {
  "date" : "2003-10-23",
  "value" : 24759.67,
  "symbol" : "MAGISTER-E"
}, {
  "date" : "2003-10-24",
  "value" : 24740.91,
  "symbol" : "MAGISTER-E"
}, {
  "date" : "2003-10-25",
  "value" : 24740.91,
  "symbol" : "MAGISTER-E"
}, {
  "date" : "2003-10-26",
  "value" : 24740.91,
  "symbol" : "MAGISTER-E"
}, {
  "date" : "2003-10-27",
  "value" : 24756.84,
  "symbol" : "MAGISTER-E"
}, {
  "date" : "2003-10-28",
  "value" : 24782.02,
  "symbol" : "MAGISTER-E"
}, {
  "date" : "2003-10-29",
  "value" : 24785.82,
  "symbol" : "MAGISTER-E"
}, {
  "date" : "2003-10-30",
  "value" : 24789.01,
  "symbol" : "MAGISTER-E"
}, {
  "date" : "2003-10-31",
  "value" : 24683.35,
  "symbol" : "MAGISTER-E"
}, {
  "date" : "2003-11-01",
  "value" : 24683.35,
  "symbol" : "MAGISTER-E"
}, {
  "date" : "2003-11-02",
  "value" : 24683.35,
  "symbol" : "MAGISTER-E"
}, {
  "date" : "2003-11-03",
  "value" : 24714.07,
  "symbol" : "MAGISTER-E"
}, {
  "date" : "2003-11-04",
  "value" : 24731.16,
  "symbol" : "MAGISTER-E"
}, {
  "date" : "2003-11-05",
  "value" : 24734.92,
  "symbol" : "MAGISTER-E"
}, {
  "date" : "2003-11-06",
  "value" : 24747.10,
  "symbol" : "MAGISTER-E"
}, {
  "date" : "2003-11-07",
  "value" : 24777.79,
  "symbol" : "MAGISTER-E"
}, {
  "date" : "2003-11-08",
  "value" : 24777.79,
  "symbol" : "MAGISTER-E"
}, {
  "date" : "2003-11-09",
  "value" : 24777.79,
  "symbol" : "MAGISTER-E"
}, {
  "date" : "2003-11-10",
  "value" : 24655.80,
  "symbol" : "MAGISTER-E"
}, {
  "date" : "2003-11-11",
  "value" : 24720.07,
  "symbol" : "MAGISTER-E"
}, {
  "date" : "2003-11-12",
  "value" : 24814.02,
  "symbol" : "MAGISTER-E"
}, {
  "date" : "2003-11-13",
  "value" : 24791.12,
  "symbol" : "MAGISTER-E"
}, {
  "date" : "2003-11-14",
  "value" : 24762.33,
  "symbol" : "MAGISTER-E"
}, {
  "date" : "2003-11-15",
  "value" : 24762.33,
  "symbol" : "MAGISTER-E"
}, {
  "date" : "2003-11-16",
  "value" : 24762.33,
  "symbol" : "MAGISTER-E"
}, {
  "date" : "2003-11-17",
  "value" : 24778.20,
  "symbol" : "MAGISTER-E"
}, {
  "date" : "2003-11-18",
  "value" : 24741.12,
  "symbol" : "MAGISTER-E"
}, {
  "date" : "2003-11-19",
  "value" : 24846.91,
  "symbol" : "MAGISTER-E"
}, {
  "date" : "2003-11-20",
  "value" : 24818.81,
  "symbol" : "MAGISTER-E"
}, {
  "date" : "2003-11-21",
  "value" : 24779.03,
  "symbol" : "MAGISTER-E"
}, {
  "date" : "2003-11-22",
  "value" : 24779.03,
  "symbol" : "MAGISTER-E"
}, {
  "date" : "2003-11-23",
  "value" : 24779.03,
  "symbol" : "MAGISTER-E"
}, {
  "date" : "2003-11-24",
  "value" : 24782.24,
  "symbol" : "MAGISTER-E"
}, {
  "date" : "2003-11-25",
  "value" : 24739.09,
  "symbol" : "MAGISTER-E"
}, {
  "date" : "2003-11-26",
  "value" : 24722.12,
  "symbol" : "MAGISTER-E"
}, {
  "date" : "2003-11-27",
  "value" : 24760.41,
  "symbol" : "MAGISTER-E"
}, {
  "date" : "2003-11-28",
  "value" : 24727.75,
  "symbol" : "MAGISTER-E"
}, {
  "date" : "2003-11-29",
  "value" : 24727.75,
  "symbol" : "MAGISTER-E"
}, {
  "date" : "2003-11-30",
  "value" : 24727.75,
  "symbol" : "MAGISTER-E"
}, {
  "date" : "2003-12-01",
  "value" : 24695.47,
  "symbol" : "MAGISTER-E"
}, {
  "date" : "2003-12-02",
  "value" : 24655.64,
  "symbol" : "MAGISTER-E"
}, {
  "date" : "2003-12-03",
  "value" : 24623.65,
  "symbol" : "MAGISTER-E"
}, {
  "date" : "2003-12-04",
  "value" : 24584.34,
  "symbol" : "MAGISTER-E"
}, {
  "date" : "2003-12-05",
  "value" : 24615.73,
  "symbol" : "MAGISTER-E"
}, {
  "date" : "2003-12-06",
  "value" : 24615.73,
  "symbol" : "MAGISTER-E"
}, {
  "date" : "2003-12-07",
  "value" : 24615.73,
  "symbol" : "MAGISTER-E"
}, {
  "date" : "2003-12-08",
  "value" : 24615.73,
  "symbol" : "MAGISTER-E"
}, {
  "date" : "2003-12-09",
  "value" : 24653.65,
  "symbol" : "MAGISTER-E"
}, {
  "date" : "2003-12-10",
  "value" : 24639.29,
  "symbol" : "MAGISTER-E"
}, {
  "date" : "2003-12-11",
  "value" : 24663.04,
  "symbol" : "MAGISTER-E"
}, {
  "date" : "2003-12-12",
  "value" : 24652.16,
  "symbol" : "MAGISTER-E"
}, {
  "date" : "2003-12-13",
  "value" : 24652.16,
  "symbol" : "MAGISTER-E"
}, {
  "date" : "2003-12-14",
  "value" : 24652.16,
  "symbol" : "MAGISTER-E"
}, {
  "date" : "2003-12-15",
  "value" : 24688.28,
  "symbol" : "MAGISTER-E"
}, {
  "date" : "2003-12-16",
  "value" : 24699.65,
  "symbol" : "MAGISTER-E"
}, {
  "date" : "2003-12-17",
  "value" : 24708.74,
  "symbol" : "MAGISTER-E"
}, {
  "date" : "2003-12-18",
  "value" : 24700.54,
  "symbol" : "MAGISTER-E"
}, {
  "date" : "2003-12-19",
  "value" : 24639.39,
  "symbol" : "MAGISTER-E"
}, {
  "date" : "2003-12-20",
  "value" : 24639.39,
  "symbol" : "MAGISTER-E"
}, {
  "date" : "2003-12-21",
  "value" : 24639.39,
  "symbol" : "MAGISTER-E"
}, {
  "date" : "2003-12-22",
  "value" : 24661.37,
  "symbol" : "MAGISTER-E"
}, {
  "date" : "2003-12-23",
  "value" : 24664.69,
  "symbol" : "MAGISTER-E"
}, {
  "date" : "2003-12-24",
  "value" : 24666.22,
  "symbol" : "MAGISTER-E"
}, {
  "date" : "2003-12-25",
  "value" : 24666.22,
  "symbol" : "MAGISTER-E"
}, {
  "date" : "2003-12-26",
  "value" : 24660.21,
  "symbol" : "MAGISTER-E"
}, {
  "date" : "2003-12-27",
  "value" : 24660.21,
  "symbol" : "MAGISTER-E"
}, {
  "date" : "2003-12-28",
  "value" : 24660.21,
  "symbol" : "MAGISTER-E"
}, {
  "date" : "2003-12-29",
  "value" : 24678.97,
  "symbol" : "MAGISTER-E"
}, {
  "date" : "2003-12-30",
  "value" : 24718.17,
  "symbol" : "MAGISTER-E"
}, {
  "date" : "2003-12-31",
  "value" : 24679.59,
  "symbol" : "MAGISTER-E"
}, {
  "date" : "2004-01-01",
  "value" : 24679.59,
  "symbol" : "MAGISTER-E"
}, {
  "date" : "2004-01-02",
  "value" : 24652.20,
  "symbol" : "MAGISTER-E"
}, {
  "date" : "2004-01-03",
  "value" : 24652.20,
  "symbol" : "MAGISTER-E"
}, {
  "date" : "2004-01-04",
  "value" : 24652.20,
  "symbol" : "MAGISTER-E"
}, {
  "date" : "2004-01-05",
  "value" : 24652.11,
  "symbol" : "MAGISTER-E"
}, {
  "date" : "2004-01-06",
  "value" : 24657.79,
  "symbol" : "MAGISTER-E"
}, {
  "date" : "2004-01-07",
  "value" : 24673.94,
  "symbol" : "MAGISTER-E"
}, {
  "date" : "2004-01-08",
  "value" : 24701.18,
  "symbol" : "MAGISTER-E"
}, {
  "date" : "2004-01-09",
  "value" : 24706.42,
  "symbol" : "MAGISTER-E"
}, {
  "date" : "2004-01-10",
  "value" : 24706.42,
  "symbol" : "MAGISTER-E"
}, {
  "date" : "2004-01-11",
  "value" : 24706.42,
  "symbol" : "MAGISTER-E"
}, {
  "date" : "2004-01-12",
  "value" : 24756.09,
  "symbol" : "MAGISTER-E"
}, {
  "date" : "2004-01-13",
  "value" : 24746.46,
  "symbol" : "MAGISTER-E"
}, {
  "date" : "2004-01-14",
  "value" : 24776.35,
  "symbol" : "MAGISTER-E"
}, {
  "date" : "2004-01-15",
  "value" : 24821.57,
  "symbol" : "MAGISTER-E"
}, {
  "date" : "2004-01-16",
  "value" : 24786.21,
  "symbol" : "MAGISTER-E"
}, {
  "date" : "2004-01-17",
  "value" : 24786.21,
  "symbol" : "MAGISTER-E"
}, {
  "date" : "2004-01-18",
  "value" : 24786.21,
  "symbol" : "MAGISTER-E"
}, {
  "date" : "2004-01-19",
  "value" : 24855.82,
  "symbol" : "MAGISTER-E"
}, {
  "date" : "2004-01-20",
  "value" : 24831.70,
  "symbol" : "MAGISTER-E"
}, {
  "date" : "2004-01-21",
  "value" : 24818.85,
  "symbol" : "MAGISTER-E"
}, {
  "date" : "2004-01-22",
  "value" : 24827.37,
  "symbol" : "MAGISTER-E"
}, {
  "date" : "2004-01-23",
  "value" : 24878.43,
  "symbol" : "MAGISTER-E"
}, {
  "date" : "2004-01-24",
  "value" : 24878.43,
  "symbol" : "MAGISTER-E"
}, {
  "date" : "2004-01-25",
  "value" : 24878.43,
  "symbol" : "MAGISTER-E"
}, {
  "date" : "2004-01-26",
  "value" : 24928.98,
  "symbol" : "MAGISTER-E"
}, {
  "date" : "2004-01-27",
  "value" : 24955.92,
  "symbol" : "MAGISTER-E"
}, {
  "date" : "2004-01-28",
  "value" : 24951.21,
  "symbol" : "MAGISTER-E"
}, {
  "date" : "2004-01-29",
  "value" : 24978.90,
  "symbol" : "MAGISTER-E"
}, {
  "date" : "2004-01-30",
  "value" : 25053.40,
  "symbol" : "MAGISTER-E"
}, {
  "date" : "2004-01-31",
  "value" : 25053.40,
  "symbol" : "MAGISTER-E"
}, {
  "date" : "2004-02-01",
  "value" : 25053.40,
  "symbol" : "MAGISTER-E"
}, {
  "date" : "2004-02-02",
  "value" : 25024.66,
  "symbol" : "MAGISTER-E"
}, {
  "date" : "2004-02-03",
  "value" : 24950.90,
  "symbol" : "MAGISTER-E"
}, {
  "date" : "2004-02-04",
  "value" : 25019.72,
  "symbol" : "MAGISTER-E"
}, {
  "date" : "2004-02-05",
  "value" : 25079.78,
  "symbol" : "MAGISTER-E"
}, {
  "date" : "2004-02-06",
  "value" : 25137.77,
  "symbol" : "MAGISTER-E"
}, {
  "date" : "2004-02-07",
  "value" : 25137.77,
  "symbol" : "MAGISTER-E"
}, {
  "date" : "2004-02-08",
  "value" : 25137.77,
  "symbol" : "MAGISTER-E"
}, {
  "date" : "2004-02-09",
  "value" : 25130.35,
  "symbol" : "MAGISTER-E"
}, {
  "date" : "2004-02-10",
  "value" : 25084.57,
  "symbol" : "MAGISTER-E"
}, {
  "date" : "2004-02-11",
  "value" : 25108.43,
  "symbol" : "MAGISTER-E"
}, {
  "date" : "2004-02-12",
  "value" : 25118.25,
  "symbol" : "MAGISTER-E"
}, {
  "date" : "2004-02-13",
  "value" : 25106.28,
  "symbol" : "MAGISTER-E"
}, {
  "date" : "2004-02-14",
  "value" : 25106.28,
  "symbol" : "MAGISTER-E"
}, {
  "date" : "2004-02-15",
  "value" : 25106.28,
  "symbol" : "MAGISTER-E"
}, {
  "date" : "2004-02-16",
  "value" : 25131.76,
  "symbol" : "MAGISTER-E"
}, {
  "date" : "2004-02-17",
  "value" : 25150.85,
  "symbol" : "MAGISTER-E"
}, {
  "date" : "2004-02-18",
  "value" : 25102.35,
  "symbol" : "MAGISTER-E"
}, {
  "date" : "2004-02-19",
  "value" : 25105.53,
  "symbol" : "MAGISTER-E"
}, {
  "date" : "2004-02-20",
  "value" : 25166.47,
  "symbol" : "MAGISTER-E"
}, {
  "date" : "2004-02-21",
  "value" : 25166.47,
  "symbol" : "MAGISTER-E"
}, {
  "date" : "2004-02-22",
  "value" : 25166.47,
  "symbol" : "MAGISTER-E"
}, {
  "date" : "2004-02-23",
  "value" : 25189.24,
  "symbol" : "MAGISTER-E"
}, {
  "date" : "2004-02-24",
  "value" : 25222.98,
  "symbol" : "MAGISTER-E"
}, {
  "date" : "2004-02-25",
  "value" : 25272.56,
  "symbol" : "MAGISTER-E"
}, {
  "date" : "2004-02-26",
  "value" : 25250.38,
  "symbol" : "MAGISTER-E"
}, {
  "date" : "2004-02-27",
  "value" : 25320.28,
  "symbol" : "MAGISTER-E"
}, {
  "date" : "2004-02-28",
  "value" : 25320.28,
  "symbol" : "MAGISTER-E"
}, {
  "date" : "2004-02-29",
  "value" : 25320.28,
  "symbol" : "MAGISTER-E"
} ]